Workbook

Sheet README
A1: Public statements on critical minerals: China, the US and Latin America
A2: Source file: statements.csv (provided by the user). No values were changed; only formatting, country names and readable labels were added.
A4: Sheets
A5: Statements | B5: Readable table, one row per statement, sorted by date. Filter with the header arrows. The Source column links to the original article or document.
A6: Coverage | B6: Count tables by country, speaker bloc, stance and mineral. All counts are formulas on the Data sheet.
A7: Data | B7: All 29 original fields from statements.csv, in the original row order, unchanged.
A9: Key facts
A10: Statements | B10: =COUNTA(Data!$A$2:$A$418)
A11: Date range | B11: =MIN(Data!$C$2:$C$418)&" to "&MAX(Data!$C$2:$C$418)
A12: In 12-country scope | B12: =COUNTA(Data!$A$2:$A$418)-COUNTIF(Data!$D$2:$D$418,"MEX")-COUNTIF(Data!$D$2:$D$418,"PAN")-COUNTIF(Data!$D$2:$D$418,"REG")
A13: Outside scope | B13: Mexico (MEX) and Panama (PAN) are outside the 12 South American states; REG marks region-wide statements. They are kept and flagged in the "In 12-country scope" column.
A15: Added labels
A16: Country | B16: ISO-3 codes from the "country" field mapped to names (REG = Regional).
A17: In 12-country scope | B17: Yes if the country is one of Argentina, Bolivia, Brazil, Chile, Colombia, Ecuador, Guyana, Paraguay, Peru, Suriname, Uruguay, Venezuela.
A18: Labels | B18: Underscores replaced with spaces and semicolons with commas in channel, minerals, themes, stance, source type and verification. Raw codes remain on the Data sheet.
A19: Verification | B19: Taken as given in the CSV: primary verified, secondary reported, or unverified.
A21: Regenerated from political_statements_minerals.csv by pipeline/scripts/statements_workbook.py on 2026-10-09: 417 records.

Sheet Statements
A1: ID | B1: Date | C1: Country | D1: In 12-country scope | E1: Speaker | F1: Role | G1: Speaker bloc | H1: Channel | I1: Event / context | J1: Summary | K1: Minerals | L1: Themes | M1: Stance on China | N1: Stance on US | O1: Quote (original) | P1: Quote (English) | Q1: Language | R1: Source | S1: Source type | T1: Verification | U1: Notes
A2: PS-0001 | B2: 2019-03 | C2: Peru | D2: Yes | E2: Paola Bustamante | F2: Minister of Development and Social Inclusion of Peru | G2: LatAm executive | H2: press conference | I2: Fuerabamba blockade of Las Bambas mining road; failed ministerial negotiation visit | J2: After protesters threw rocks at a government helicopter carrying a three-minister delegation to negotiate an end to a 51-day Fuerabamba community blockade of the Las Bambas copper mine road, Bustamante said the government would maintain its willingness to dialogue. | K2: copper | L2: labor social conflict, indigenous community rights | M2: not mentioned | N2: not mentioned | O2: We went with a disposition for dialogue and that's why we're going to continue with that disposition and see how things shape up tomorrow. | P2: We went with a disposition for dialogue and that's why we're going to continue with that disposition and see how things shape up tomorrow. | Q2: en | R2: Reuters via The Borneo Post (PressReader) | S2: news media | T2: secondary reported | U2: Exact day not given (Wednesday before 29 Mar 2019, likely 27 Mar); quote is English wire translation of Spanish original
A3: PS-0002 | B3: 2019-03-05 | C3: Brazil | D3: Yes | E3: Bento Albuquerque | F3: Minister of Mines and Energy of Brazil | G3: LatAm executive | H3: speech | I3: Meeting with mining investors in Canada (PDAC, Toronto) | J3: Albuquerque told investors in Canada that the government was studying authorising mining in indigenous lands and border areas, arguing restrictions fostered illegal activity, and favoured opening uranium research to private investment. | K3: mining general | L3: indigenous community rights, foreign investment, sovereignty | M3: not mentioned | N3: not mentioned | O3: As restrições aplicadas a essas áreas não têm favorecido seu desenvolvimento. | P3: The restrictions applied to these areas have not favoured their development. | Q3: pt | R3: Congresso em Foco | S3: news media | T3: secondary reported | U3: Event name PDAC inferred from date/location
A4: PS-0003 | B4: 2019-07-16 | C4: Peru | D4: Yes | E4: Elmer Cáceres Llica | F4: Regional Governor of Arequipa | G4: LatAm executive | H4: press conference | I4: Tía María license protests, Tambo Valley | J4: The Arequipa governor, backed by over 50 civil organizations, gave the central government 72 hours to declare the Tía María construction license null, while pursuing legal remedies and peaceful protests. | K4: copper | L4: environment water, labor social conflict | M4: not mentioned | N4: not mentioned | O4: Le daremos al Gobierno central 72 horas para que resuelva el tema de la licencia de construcción, o sea que declare su nulidad de oficio | P4: We will give the central government 72 hours to resolve the construction license issue, that is, to declare it null ex officio | Q4: es | R4: La República | S4: news media | T4: secondary reported
A5: PS-0004 | B5: 2019-07-16 | C5: Peru | D5: Yes | E5: Martín Vizcarra | F5: President of Peru | G5: LatAm executive | H5: press conference | I5: Protests over Tía María construction license granted to Southern Peru (9 Jul 2019) | J5: Vizcarra said the construction license granted to Southern Peru for Tía María could not be annulled because the company had completed the administrative process, but called for dialogue and said construction would need proper conditions. | K5: copper | L5: labor social conflict, environment water, foreign investment | M5: not mentioned | N5: not mentioned | O5: No se puede anular, tenemos que conversar y fruto del diálogo, encontremos las soluciones y consensos | P5: It cannot be annulled; we have to talk, and through dialogue find solutions and consensus | Q5: es | R5: El Búho | S5: news media | T5: secondary reported
A6: PS-0005 | B6: 2019-09-06 | C6: Chile | D6: Yes | E6: Pablo Terrazas | F6: Executive Vice President of CORFO | G6: LatAm executive | H6: legislative debate | I6: Chamber of Deputies Economy Commission session on lithium and Tianqi-SQM | J6: CORFO head briefed deputies on lithium contracts, Tianqi's stake in SQM and the planned Chilean Institute of Clean Technologies in Antofagasta, funded with SQM contributions, for lithium R&D. | K6: lithium | L6: technology transfer, value added industrialization, foreign investment | M6: neutral | N6: not mentioned | O6: De aquí a fin de año, ya vamos a tener a algún consorcio liderando la creación de este instituto | P6: By the end of the year we will have a consortium leading the creation of this institute | Q6: es | R6: Cámara de Diputadas y Diputados | S6: legislative record | T6: primary verified | U6: Quote truncated to stay within 30 words; institute to have >US$200m for R&D
A7: PS-0006 | B7: 2019-09-06 | C7: Chile | D7: Yes | E7: Renato Garín | F7: Deputy, Chair-level member of Economy Commission | G7: LatAm legislature | H7: legislative debate | I7: Chamber of Deputies Economy Commission session on lithium and Tianqi-SQM | J7: Deputy Garín voiced concern about Chinese state influence over SQM through Tianqi and said Chile must retain sovereignty over its lithium resources and technology development. | K7: lithium | L7: sovereignty, geopolitics security, technology transfer | M7: negative | N7: not mentioned | Q7: es | R7: Cámara de Diputadas y Diputados | S7: legislative record | T7: primary verified | U7: Paraphrase from Chamber press note; no verbatim quote
A8: PS-0007 | B8: 2019-10-13 | C8: Peru | D8: Yes | E8: Raúl Molina Martínez | F8: Deputy Minister of Territorial Governance (PCM) | G8: LatAm executive | H8: official statement | I8: Chumbivilcas blockade of southern mining corridor used by Las Bambas | J8: The PCM vice minister urged Chumbivilcas communities to lift their blockade of the road used by Las Bambas to haul copper concentrate, stressing it is a public road and that demands must be legally viable. | K8: copper | L8: labor social conflict, infrastructure ports | M8: not mentioned | N8: not mentioned | O8: It is not possible to prevent the free movement of vehicles through the runway, including the miner's trucks, because it is a public road. | P8: It is not possible to prevent the free movement of vehicles through the runway, including the miner's trucks, because it is a public road. | Q8: en | R8: Reuters via MINING.COM | S8: news media | T8: secondary reported | U8: Quote is English wire translation; date is article date
A9: PS-0008 | B9: 2019-10-28 | C9: Peru | D9: Yes | E9: Juan Carlos Liu | F9: Minister of Energy and Mines of Peru | G9: LatAm executive | H9: press conference | I9: Mining Council review of Tía María license | J9: Liu said the Tía María license case was for the autonomous Mining Council to decide and that the government, following presidential guidelines, would abide by its ruling while promoting dialogue in the Tambo Valley. | K9: copper | L9: corruption governance, labor social conflict | M9: not mentioned | N9: not mentioned | O9: El caso de Tía María es un caso que está para la decisión de la Comisión de Minería. | P9: The Tía María case is one awaiting the decision of the Mining Commission. | Q9: es | R9: ProActivo | S9: news media | T9: secondary reported
A10: PS-0009 | B10: 2020-04 | C10: Bolivia | D10: Yes | E10: José Luis Parada | F10: Minister of Economy and Public Finance (Áñez interim government) | G10: LatAm executive | H10: interview | I10: Interim government economic policy, COVID-19 period | J10: Interim-government economy minister Parada said two or three companies from different countries would invest in lithium from the Uyuni salt flat and that policies to attract foreign partners were being prepared. | K10: lithium | L10: foreign investment | M10: not mentioned | N10: not mentioned | Q10: es | R10: Tiempo Argentino | S10: news media | T10: secondary reported | U10: Paraphrase from secondary source (left-leaning outlet); exact day in late April 2020 unknown; no verbatim quote seen.
A11: PS-0010 | B11: 2020-07-25 | C11: Bolivia | D11: Yes | E11: Evo Morales | F11: Former President of Bolivia (in exile) | G11: Other (business, civil society, third countries) | H11: social media post | I11: Twitter exchange with Elon Musk | J11: Responding to Elon Musk's 'We will coup whoever we want' tweet, Morales said it was further proof that the 2019 coup was over Bolivian lithium and vowed to defend Bolivia's resources. | K11: lithium | L11: sovereignty, geopolitics security | M11: not mentioned | N11: negative | O11: Otra prueba más de que el golpe fue por el litio boliviano; y dos masacres como saldo. ¡Defenderemos siempre nuestros recursos! | P11: Yet more proof that the coup was over Bolivian lithium; with two massacres as the toll. We will always defend our resources! | Q11: es | R11: La República (Peru) | S11: news media | T11: secondary reported | U11: Tweet quoted by media; stance_us coded for US corporate actor (Musk/Tesla).
A12: PS-0011 | B12: 2020-09-28 | C12: Brazil | D12: Yes | E12: Jair Bolsonaro | F12: President of Brazil | G12: LatAm executive | H12: speech | I12: Launch of the Mining and Development Program (PMD), Palácio do Planalto | J12: At the launch of the government's Mining and Development Program, Bolsonaro received a niobium coin from Minister Bento Albuquerque and praised niobium combined with graphene as able to revolutionise the car industry; the program included advancing a bill on mining in indigenous lands. | K12: niobium, mining general | L12: value added industrialization, technology transfer, indigenous community rights | M12: not mentioned | N12: not mentioned | O12: juntamente com o grafeno é capaz de produzir maravilhas | P12: together with graphene it is capable of producing wonders | Q12: pt | R12: Poder360 | S12: news media | T12: secondary reported | U12: Bolsonaro left PSL in Nov 2019
A13: PS-0012 | B13: 2020-11-10 | C13: Bolivia | D13: Yes | E13: Evo Morales | F13: Former President of Bolivia; MAS leader | G13: Other (business, civil society, third countries) | H13: press conference | I13: Return to Bolivia from exile, Uyuni/Potosí tour | J13: On his return to Bolivia, Morales said lithium reserves were the motive for the 2019 'coup', that industrialized countries want Latin America only for raw materials, and that his lithium industrialization plan would resume under President Arce. | K13: lithium | L13: value added industrialization, sovereignty, geopolitics security | M13: not mentioned | N13: not mentioned | O13: allí donde los pueblos son dueños de los recursos naturales, preparan bases e intervenciones militares e incluso golpes de Estado | P13: wherever peoples own their natural resources, they prepare bases and military interventions and even coups d'état | Q13: es | R13: Público | S13: news media | T13: secondary reported | U13: Also reported by Gestión (https://gestion.pe/mundo/internacional/evo-morales-anuncia-que-se-reactivara-su-plan-de-litio-apenas-llegado-a-bolivia-noticia/): 'El plan que teníamos lo vamos a retomar ahora con el Lucho presidente'.
A14: PS-0013 | B14: 2020-12-04 | C14: Peru | D14: Yes | E14: Francisco Sagasti | F14: President of Peru (transitional) | G14: LatAm executive | H14: press conference | I14: Press conference with foreign media accredited in Peru | J14: Sagasti said his transitional government had no mandate to change economic direction and would ensure that foreign investments already under way, including in mining, continue, while arguing Peru should diversify beyond being a mining country. | K14: mining general | L14: foreign investment | M14: not mentioned | N14: not mentioned | O14: hará lo que hay que hacer para que continúen las inversiones extranjeras ya en proceso, ya sea en la minería o en otros sectores | P14: will do what must be done so that foreign investments already under way continue, whether in mining or other sectors | Q14: es | R14: ProActivo | S14: news media | T14: secondary reported | U14: Quote is in reported (third-person) form as published
A15: PS-0014 | B15: 2021-04-16 | C15: Peru | D15: Yes | E15: Ana María Córdova | F15: Legal representative of Perú Libre (Pedro Castillo campaign) | G15: LatAm party/candidate | H15: campaign statement | I15: 2021 presidential runoff campaign | J15: Speaking for candidate Pedro Castillo, Córdova said the party would not expropriate or nationalize mines but would renegotiate contract conditions so the state and local populations get a bigger share of profits. | K15: mining general, copper | L15: royalties taxation, state control nationalization, foreign investment | M15: not mentioned | N15: not mentioned | O15: Not to expropriate them, not to nationalize or anything, but so that the conditions in some way also favor populations where these industries or mining operations are involved | P15: Not to expropriate them, not to nationalize or anything, but so that the conditions in some way also favor populations where these industries or mining operations are involved | Q15: en | R15: Bloomberg via Mining Weekly | S15: news media | T15: secondary reported | U15: English translation published by Bloomberg; original Spanish wording not seen
A16: PS-0015 | B16: 2021-06-15 | C16: Argentina | D16: Yes | E16: Martín de los Ríos | F16: Minister of Production of Salta (for Gov. Gustavo Sáenz) | G16: LatAm executive | H16: interview | I16: Reaction to national lithium nationalization proposals | J16: Salta's production minister said the three lithium provinces formed the Mesa del Litio on the basis that lithium is a provincial resource and that nationalization initiatives create instability for investors. | K16: lithium | L16: state control nationalization, sovereignty, foreign investment | M16: not mentioned | N16: not mentioned | Q16: es | R16: Ámbito | S16: news media | T16: secondary reported | U16: Only translated rendering seen; quote left blank.
A17: PS-0016 | B17: 2021-06-15 | C17: Argentina | D17: Yes | E17: Miguel Soler | F17: Secretary of Mining of Jujuy (Morales government) | G17: LatAm executive | H17: interview | I17: Reaction to national lithium nationalization proposals | J17: Jujuy's mining secretary said proposals to nationalize lithium are unconstitutional because they interfere with provincial ownership of resources, and that Jujuy should make its own decisions. | K17: lithium | L17: state control nationalization, sovereignty | M17: not mentioned | N17: not mentioned | Q17: es | R17: Ámbito | S17: news media | T17: secondary reported | U17: Only translated rendering seen; quote left blank.
A18: PS-0017 | B18: 2021-09-23 | C18: Peru | D18: Yes | E18: Pedro Francke | F18: Minister of Economy and Finance of Peru | G18: LatAm executive | H18: interview | I18: Proposed tax reform targeting mining windfall profits | J18: Francke argued that with copper above US$4/lb and costs around US$1/lb, the state should capture extraordinary mining profits and redistribute mining wealth through tax reform. | K18: copper, mining general | L18: royalties taxation | M18: not mentioned | N18: not mentioned | O18: Hay que redistribuir la riqueza, en particular la riqueza minera | P18: We must redistribute wealth, particularly mining wealth | Q18: es | R18: La República | S18: news media | T18: secondary reported
A19: PS-0018 | B19: 2021-10-01 | C19: Peru | D19: Yes | E19: Iván Merino | F19: Minister of Energy and Mines of Peru | G19: LatAm executive | H19: interview | I19: Three-week blockade of Las Bambas road in Chumbivilcas | J19: Merino partly blamed MMG's short-term decision to haul Las Bambas copper concentrate on a dirt road for unrest with communities, and proposed a train line as a longer-term solution. | K19: copper | L19: labor social conflict, infrastructure ports | M19: not mentioned | N19: not mentioned | O19: They made short-term decisions and that has a cost | P19: They made short-term decisions and that has a cost | Q19: en | R19: Reuters via Mining Weekly | S19: news media | T19: secondary reported | U19: English wire translation
A20: PS-0019 | B20: 2021-11 | C20: Peru | D20: Yes | E20: Mirtha Vásquez | F20: President of the Council of Ministers of Peru | G20: LatAm executive | H20: official statement | I20: Agreement with Ayacucho communities on mine closures | J20: Vásquez signed an agreement with Ayacucho communities confirming the closure of four mining operations and said mining expansions in the province would not be approved, prompting business backlash; a vice minister later said expansion plans could still be submitted. | K20: mining general, silver | L20: environment water, indigenous community rights, labor social conflict | M20: not mentioned | N20: not mentioned | Q20: es | R20: Bloomberg Línea | S20: news media | T20: secondary reported | U20: Agreement dated c. 19-20 Nov 2021; silver tag because affected mines (Hochschild) are gold-silver operations
A21: PS-0020 | B21: 2021-11-20 | C21: Argentina | D21: Yes | E21: Gustavo Sáenz; Gerardo Morales; Raúl Jalil | F21: Governors of Salta, Jujuy and Catamarca | G21: LatAm executive | H21: joint declaration or mou | I21: Creation of the Región Minera del Litio | J21: The three governors signed a treaty forming the Lithium Mining Region to coordinate infrastructure, production, technical and environmental matters across lithium research, extraction, industrialization and trade. | K21: lithium | L21: value added industrialization, infrastructure ports, environment water | M21: not mentioned | N21: not mentioned | O21: determinar las bases para generar condiciones de reciprocidad y coordinar esfuerzos en materia de infraestructura, producción, cuestiones técnicas ambientales | P21: lay the foundations to create reciprocal conditions and coordinate efforts on infrastructure, production, technical and environmental issues | Q21: es | R21: Más Energía (LM Neuquén) | S21: news media | T21: secondary reported | U21: Quote by Sáenz; Mesa del Litio precedent.
A22: PS-0021 | B22: 2021-11-22 | C22: Peru | D22: Yes | E22: Pedro Castillo | F22: President of Peru | G22: LatAm executive | H22: official statement | I22: Controversy over PM Vásquez's announced closure of four mines in Ayacucho | J22: Amid market turmoil after the premier agreed with Ayacucho communities to close four mining operations, Castillo said there would be no unilateral or arbitrary decisions and reaffirmed his commitment to guarantee private investment including mining. | K22: mining general | L22: foreign investment, environment water, indigenous community rights | M22: not mentioned | N22: not mentioned | O22: No ha existido ni existirán decisiones unilaterales ni arbitrarias | P22: There have not been, nor will there be, unilateral or arbitrary decisions | Q22: es | R22: Bloomberg Línea | S22: news media | T22: secondary reported
A23: PS-0022 | B23: 2021-12-16 | C23: Peru | D23: Yes | E23: Mirtha Vásquez | F23: President of the Council of Ministers of Peru | G23: LatAm executive | H23: press conference | I23: Chumbivilcas blockade halting Las Bambas | J23: With the Las Bambas road blockade past 20 days, Vásquez said the government was evaluating options including eviction of protesters and, as a last resort, a state of emergency in Chumbivilcas. | K23: copper | L23: labor social conflict, corruption governance | M23: not mentioned | N23: not mentioned | O23: Hay varias opciones que evaluar. No podemos permitir que se estén vulnerando ciertos derechos | P23: There are several options to evaluate. We cannot allow certain rights to be violated | Q23: es | R23: ProActivo | S23: news media | T23: secondary reported
A24: PS-0023 | B24: 2021-12-21 | C24: Peru | D24: Yes | E24: Baltazar Lantarón | F24: Regional Governor of Apurímac | G24: LatAm executive | H24: official statement | I24: Las Bambas shutdown due to corridor blockade | J24: Lantarón criticized the Executive's negotiators as pusillanimous over the Las Bambas corridor blockade, warned of lost royalties and mining canon for Apurímac, and requested a 120-day emergency declaration on the southern mining corridor. | K24: copper | L24: royalties taxation, labor social conflict | M24: not mentioned | N24: not mentioned | O24: la actitud pusilánime de los negociadores del Ejecutivo están generado nefastas consecuencias económicas | P24: the pusillanimous attitude of the Executive's negotiators is generating disastrous economic consequences | Q24: es | R24: ProActivo | S24: news media | T24: secondary reported
A25: PS-0024 | B25: 2022-01 | C25: Chile | D25: Yes | E25: Juan Carlos Jobet | F25: Minister of Mining and Energy | G25: LatAm executive | H25: interview | I25: Defence of lithium tender against incoming government's request to postpone | J25: Jobet argued Chile had failed to raise lithium output while other countries advanced, and said the tender (about 4% of reserves) did not mortgage the next government's agenda. | K25: lithium | L25: foreign investment, state control nationalization | M25: not mentioned | N25: not mentioned | O25: hemos sido incapaces de aumentar la producción y, mientras hacemos eso, los otros países avanzan | P25: we have been unable to increase production and, while we do that, other countries advance | Q25: es | R25: CNN Chile | S25: news media | T25: secondary reported | U25: Exact day not given; January 2022
A26: PS-0025 | B26: 2022-01-06 | C26: Chile | D26: Yes | E26: Ricardo Díaz | F26: Governor of Antofagasta Region | G26: LatAm executive | H26: official statement | I26: Complaint to Comptroller over lithium tender | J26: Antofagasta governor said his government filed a complaint with the Comptroller over the Piñera administration's lithium tender, arguing regional and indigenous Atacameño voices were not consulted. | K26: lithium | L26: indigenous community rights, sovereignty, corruption governance | M26: not mentioned | N26: not mentioned | O26: No se puede hacer un proceso de consulta, en donde se hipoteca el futuro de nuestra región, sin considerar la voz de los que habitamos este territorio. | P26: You cannot carry out a consultation process that mortgages the future of our region without considering the voice of those of us who live in this territory. | Q26: es | R26: T13 | S26: news media | T26: secondary reported
A27: PS-0026 | B27: 2022-01-07 | C27: Chile | D27: Yes | E27: Sebastián Piñera | F27: President of Chile | G27: LatAm executive | H27: press conference | I27: Visit to O'Higgins Region; defence of lithium tender | J27: Piñera defended the international lithium tender for about 4.4% of known reserves as transparent and Comptroller-approved, noting Chile had lost lithium leadership to Australia and saying a national lithium company, as proposed by Boric, could be done. | K27: lithium | L27: foreign investment, state control nationalization, corruption governance | M27: not mentioned | N27: not mentioned | O27: El litio es hoy día un mineral esencial para la sociedad que viene | P27: Lithium is today an essential mineral for the society to come | Q27: es | R27: El Dínamo | S27: news media | T27: secondary reported
A28: PS-0027 | B28: 2022-01-10 | C28: Chile | D28: Yes | E28: Rodrigo Cerda | F28: Minister of Finance | G28: LatAm executive | H28: interview | I28: Canal 13 interview on lithium tender | J28: Finance minister said the lithium tender was not a lock-in ("amarre"), that lithium would remain Chilean and taxed, and that the government was listening to the president-elect's request to postpone it. | K28: lithium | L28: royalties taxation, state control nationalization | M28: not mentioned | N28: not mentioned | O28: El litio va a seguir siendo de los chilenos | P28: Lithium will continue to belong to Chileans | Q28: es | R28: CNN Chile | S28: news media | T28: secondary reported
A29: PS-0028 | B29: 2022-01-12 | C29: Chile | D29: Yes | E29: Esteban Velásquez | F29: Deputy; President of Chamber Mining Commission | G29: LatAm legislature | H29: legislative debate | I29: Chamber Mining Commission session on lithium tender | J29: Mining Commission chair criticised the Piñera government for ignoring calls to halt the lithium tender; opposition deputies announced judicial and administrative actions to annul it. | K29: lithium | L29: corruption governance, state control nationalization | M29: not mentioned | N29: not mentioned | O29: El Gobierno del Presidente Piñera no escuchó ningún llamado | P29: President Piñera's government did not listen to any call | Q29: es | R29: El Mostrador | S29: news media | T29: secondary reported
A30: PS-0029 | B30: 2022-01-12 | C30: Chile | D30: Yes | E30: Gabriel Boric | F30: President-elect of Chile | G30: LatAm party/candidate | H30: press conference | I30: Reaction to award of lithium tender to BYD and Servicios y Operaciones Mineras del Norte | J30: President-elect Boric called the outgoing government's lithium tender award bad news reminiscent of the "leyes de amarre" and said his team would review its details. | K30: lithium | L30: state control nationalization, corruption governance | M30: not mentioned | N30: not mentioned | O30: es una mala noticia y me recuerda a esas leyes de amarre | P30: it is bad news and reminds me of those lock-in laws | Q30: es | R30: El Mostrador | S30: news media | T30: secondary reported | U30: speaker_type coded as candidate because president-elect, not yet in office
A31: PS-0030 | B31: 2022-02-02 | C31: Mexico | D31: No | E31: Andrés Manuel López Obrador | F31: President of Mexico | G31: LatAm executive | H31: press conference | I31: Mañanera; announcement of state lithium company | J31: AMLO said existing mining concessions did not cover lithium, which he called a strategic mineral belonging to the nation, and that the state would exploit it; he said Mexico did not want to be a territory of conflict between Russia, China or the US. | K31: lithium | L31: state control nationalization, sovereignty, geopolitics security, foreign investment | M31: neutral | N31: neutral | O31: el litio lo va a explotar la nación. El litio ya, para que se entienda bien, no es ni siquiera del Gobierno o del Estado, el litio es del pueblo | P31: lithium will be exploited by the nation. Lithium, to be clear, does not even belong to the government or the state, lithium belongs to the people | Q31: es | R31: Emol (EFE) | S31: news media | T31: secondary reported
A32: PS-0031 | B32: 2022-02-06 | C32: Argentina | D32: Yes | E32: Xi Jinping; Alberto Fernández | F32: President of China; President of Argentina | G32: China | H32: joint declaration or mou | I32: Fernández state visit to Beijing; Argentina joins Belt and Road | J32: Chinese readout of the Xi-Fernández meeting says the sides will deepen cooperation in trade, agriculture, energy, mining, infrastructure, investment and finance, with China helping expand Argentina's exports. | K32: mining general | L32: diplomatic relations, foreign investment, infrastructure ports | M32: positive | N32: not mentioned | O32: la cooperación en áreas de comercio, agricultura, energía, minería, infraestructura, inversión, financiación y lucha antiepidémica | P32: cooperation in the areas of trade, agriculture, energy, mining, infrastructure, investment, financing and the fight against the epidemic | Q32: es | R32: Ministry of Foreign Affairs of the PRC (Spanish) | S32: primary official | T32: primary verified | U32: Mining only listed among sectors.
A33: PS-0032 | B33: 2022-03-31 | C33: Regional | D33: No | E33: Marco Rubio | F33: U.S. Senator (R-FL), Ranking Member, SFRC Subcommittee on the Western Hemisphere | G33: United States | H33: legislative debate | I33: SFRC Western Hemisphere subcommittee hearing 'China's Role in Latin America and the Caribbean' | J33: Rubio said the Chinese Communist Party pushes Latin American countries to stay dependent on mining and natural-resource exports rather than helping them develop and industrialize. | K33: mining general | L33: geopolitics security, value added industrialization | M33: negative | N33: positive | O33: the Chinese Communist Party is pushing countries to remain dependent on mining and other—and the export of other natural resources | P33: the Chinese Communist Party is pushing countries to remain dependent on mining and other—and the export of other natural resources | Q33: en | R33: U.S. Senate Foreign Relations Committee (hearing transcript) | S33: legislative record | T33: primary verified | U33: Ranking-member role inferred, not confirmed on page.
A34: PS-0033 | B34: 2022-03-31 | C34: Regional | D34: No | E34: Tim Kaine | F34: U.S. Senator (D-VA), Chair, SFRC Subcommittee on the Western Hemisphere | G34: United States | H34: legislative debate | I34: SFRC Western Hemisphere subcommittee hearing 'China's Role in Latin America and the Caribbean' | J34: In his opening statement Kaine said China continues its quest for natural resources and raw materials across Latin America, citing lithium in Argentina, Bolivia and Chile and copper in Peru. | K34: lithium, copper | L34: geopolitics security, foreign investment | M34: negative | N34: positive | O34: China continues its quest for natural resources and raw materials throughout the region, including lithium in places like Argentina, Bolivia, and Chile or copper in Peru. | P34: China continues its quest for natural resources and raw materials throughout the region, including lithium in places like Argentina, Bolivia, and Chile or copper in Peru. | Q34: en | R34: U.S. Senate Foreign Relations Committee (hearing transcript) | S34: legislative record | T34: primary verified | U34: Subcommittee chair role inferred (Kaine chaired the WH subcommittee in the 117th Congress).
A35: PS-0034 | B35: 2022-04-18 | C35: Mexico | D35: No | E35: Andrés Manuel López Obrador | F35: President of Mexico | G35: LatAm executive | H35: press conference | I35: Mañanera after failure of constitutional electricity reform; call to pass Mining Law reform | J35: AMLO urged legislators to approve his Mining Law reform nationalizing lithium, saying it should be used only for national development and that a state company would explore, extract, process and sell it. | K35: lithium | L35: state control nationalization, sovereignty, geopolitics security | M35: not mentioned | N35: not mentioned | O35: nacionalicemos el litio. Así de claro, que solo se utilice para el beneficio del desarrollo nacional. | P35: let's nationalize lithium. That clear, so that it is only used for the benefit of national development. | Q35: es | R35: El Financiero | S35: news media | T35: secondary reported
A36: PS-0035 | B36: 2022-04-18 | C36: Mexico | D36: No | E36: Cámara de Diputados de México | F36: Chamber of Deputies | G36: LatAm legislature | H36: bill or law | I36: Vote on Mining Law reform declaring lithium of public utility | J36: The Chamber of Deputies approved in general the reform to the Mining Law nationalizing lithium by 298 votes in favour and 197 abstentions; PAN and PRI deputies abstained, while Movimiento Ciudadano voted against parts of it. | K36: lithium | L36: state control nationalization, sovereignty | M36: not mentioned | N36: not mentioned | Q36: es | R36: Expansión Política | S36: news media | T36: secondary reported | U36: In particular: 275 for, 187 abstentions, 24 against (MC).
A37: PS-0036 | B37: 2022-04-18 | C37: Mexico | D37: No | E37: Salomón Chertorivski | F37: Federal Deputy (Movimiento Ciudadano) | G37: LatAm legislature | H37: legislative debate | I37: Chamber of Deputies debate on lithium Mining Law reform | J37: Chertorivski argued that lithium concessions could not be prohibited by ordinary statute and that it had to be done through the Constitution. | K37: lithium | L37: state control nationalization, corruption governance | M37: not mentioned | N37: not mentioned | O37: No se puede prohibir en una ley una concesión, se tiene que hacer desde la Constitución | P37: A concession cannot be prohibited in a law, it has to be done from the Constitution | Q37: es | R37: Expansión Política | S37: news media | T37: secondary reported
A38: PS-0037 | B38: 2022-04-19 | C38: Mexico | D38: No | E38: Alejandro Armenta | F38: Senator (Morena) | G38: LatAm legislature | H38: legislative debate | I38: Senate debate on lithium Mining Law reform | J38: Morena senator Armenta defended the reform, arguing that the private sector would still participate since the state company would sell lithium to private firms. | K38: lithium | L38: state control nationalization, foreign investment | M38: not mentioned | N38: not mentioned | O38: Se lo vende a los particulares | P38: It is sold to private parties | Q38: es | R38: Expansión Política | S38: news media | T38: secondary reported
A39: PS-0038 | B39: 2022-04-19 | C39: Mexico | D39: No | E39: Damián Zepeda | F39: Senator (PAN) | G39: LatAm legislature | H39: legislative debate | I39: Senate debate on lithium Mining Law reform | J39: PAN senator Damián Zepeda opposed the lithium reform, arguing the government should not act as a businessman in lithium exploitation. | K39: lithium | L39: state control nationalization, foreign investment | M39: not mentioned | N39: not mentioned | O39: el gobierno es pésimo para ser empresario | P39: the government is terrible at being a businessman | Q39: es | R39: Expansión Política | S39: news media | T39: secondary reported
A40: PS-0039 | B40: 2022-04-19 | C40: Mexico | D40: No | E40: José Erandi Bermúdez | F40: Senator (PAN) | G40: LatAm legislature | H40: legislative debate | I40: Senate debate on lithium Mining Law reform | J40: Bermúdez criticized the reform for lacking precision on which minerals would be considered 'strategic'. | K40: lithium, critical minerals general | L40: state control nationalization, corruption governance | M40: not mentioned | N40: not mentioned | Q40: es | R40: Expansión Política | S40: news media | T40: secondary reported
A41: PS-0040 | B41: 2022-04-19 | C41: Mexico | D41: No | E41: Senado de la República | F41: Mexican Senate | G41: LatAm legislature | H41: bill or law | I41: Senate vote on lithium Mining Law reform | J41: The Senate approved in general the Mining Law reform reserving lithium exploration and exploitation to the state, by 87 votes to 20 with 16 abstentions. | K41: lithium | L41: state control nationalization, sovereignty | M41: not mentioned | N41: not mentioned | Q41: es | R41: Expansión Política | S41: news media | T41: secondary reported | U41: In particular: 76 for, 45 against.
A42: PS-0041 | B42: 2022-05 | C42: Brazil | D42: Yes | E42: Jair Bolsonaro | F42: President of Brazil | G42: LatAm executive | H42: speech | I42: Meeting with Elon Musk, São Paulo state | J42: Bolsonaro reportedly offered niobium to Elon Musk during their 2022 meeting, citing Brazil's 98% share of world reserves and studies on niobium batteries that Tesla could use. | K42: niobium | L42: foreign investment, technology transfer | M42: not mentioned | N42: positive | Q42: pt | R42: Portal Tela | S42: news media | T42: secondary reported | U42: Paraphrase only; month from known Musk visit (May 2022), source says only 2022
A43: PS-0042 | B43: 2022-05-19 | C43: Peru | D43: Yes | E43: Aníbal Torres | F43: President of the Council of Ministers of Peru | G43: LatAm executive | H43: speech | I43: Dialogue with communities in Pumamarca, Apurímac; state of emergency over Las Bambas | J43: Torres told community members that the state of emergency in Challhuahuacho and Coyllurqui would be lifted only once they abandoned forceful actions against Las Bambas and engaged in peaceful dialogue. | K43: copper | L43: labor social conflict, indigenous community rights | M43: not mentioned | N43: not mentioned | O43: El estado de emergencia se levanta simultáneamente con el levantamiento de las actitudes de fuerza y restableciendo la paz social. | P43: The state of emergency is lifted simultaneously with the lifting of forceful actions and the restoration of social peace. | Q43: es | R43: Panamericana | S43: news media | T43: secondary reported
A44: PS-0043 | B44: 2022-06 | C44: Chile | D44: Yes | E44: Marcela Hernando | F44: Minister of Mining | G44: LatAm executive | H44: official statement | I44: Government reaction to Supreme Court annulment of lithium tender | J44: Mining minister said the Boric government would abide by the ruling, that it had warned the tender was badly designed, and that lithium would be developed through public-private partnerships with community dialogue. | K44: lithium | L44: indigenous community rights, state control nationalization | M44: not mentioned | N44: not mentioned | O44: ya habíamos advertido que la licitación estaba mal hecha | P44: we had already warned that the tender was badly done | Q44: es | R44: CNN Chile | S44: news media | T44: secondary reported | U44: Exact day not stated in source; early June 2022
A45: PS-0044 | B45: 2022-06-01 | C45: Chile | D45: Yes | E45: Supreme Court of Chile (Third Chamber) | F45: Supreme Court | G45: LatAm judiciary | H45: court ruling | I45: Ruling on appeal by Colla communities against 2021 lithium tender | J45: The Supreme Court annulled the Piñera-era lithium tender awarding 80,000 t each to BYD and Servicios y Operaciones Mineras del Norte, finding no specific area was set, which prevented prior indigenous consultation. | K45: lithium | L45: indigenous community rights, corruption governance | M45: not mentioned | N45: not mentioned | O45: no se cumplió con el requisito de fijar un área específica | P45: the requirement to set a specific area was not met | Q45: es | R45: 24 Horas (TVN) | S45: news media | T45: secondary reported | U45: Ruling reported 1 June 2022, article 2 June
A46: PS-0045 | B46: 2022-06-03 | C46: Peru | D46: Yes | E46: Margot Palacios | F46: Congresswoman (Perú Libre) | G46: LatAm legislature | H46: bill or law | I46: Bill PL 2259 to nationalize copper exploitation | J46: Palacios filed bill 2259 to create a National Copper Corporation with exclusive rights over copper exploration, extraction and initial processing, including a state company to operate the MMG-controlled Las Bambas mine. | K46: copper | L46: state control nationalization | M46: not mentioned | N46: not mentioned | O46: crear una empresa nacional para operar la mina cuprífera Las Bambas | P46: create a national company to operate the Las Bambas copper mine | Q46: es | R46: Forbes Perú | S46: news media | T46: secondary reported | U46: Quote may be Forbes' paraphrase of the bill's objective
A47: PS-0046 | B47: 2022-07-14 | C47: Regional | D47: No | E47: Laura Richardson | F47: Commander, U.S. Southern Command | G47: United States | H47: speech | I47: Concordia Americas Summit (Miami) | J47: Richardson described the region as rich in resources, rare earth minerals and lithium, noting the lithium triangle lies in the hemisphere. | K47: lithium, rare earths | L47: geopolitics security | M47: not mentioned | N47: positive | O47: This region is so rich in resources, rare earth minerals, lithium — the lithium triangle is in this region. | P47: This region is so rich in resources, rare earth minerals, lithium — the lithium triangle is in this region. | Q47: en | R47: Ludditus (blog compiling livestream quotes) | S47: think tank or ngo | T47: unverified | U47: Quote transcribed by a blog from Concordia livestream; not checked against video
A48: PS-0047 | B48: 2022-09-01 | C48: Mexico | D48: No | E48: Alfonso Durazo | F48: Governor of Sonora; coordinator of Litio para México | G48: LatAm executive | H48: interview | I48: Appointment as coordinator of LitioMx | J48: Durazo said that if lithium exploitation becomes a profitable business its benefits must be shared with local people, and that the Sonora government would hold a stake in LitioMx. | K48: lithium | L48: state control nationalization, labor social conflict, value added industrialization | M48: not mentioned | N48: not mentioned | O48: esos beneficios tienen que ser compartidos con la gente local, si no, para mí francamente no tendría ningún sentido | P48: those benefits have to be shared with local people; otherwise, frankly, it would make no sense to me | Q48: es | R48: Expansión Política | S48: news media | T48: secondary reported
A49: PS-0048 | B49: 2022-09-02 | C49: Colombia | D49: Yes | E49: Gustavo Petro | F49: President of Colombia | G49: LatAm executive | H49: speech | I49: Closing of national mining congress, Cartagena | J49: Petro told the mining industry that exploration should shift toward minerals for clean energy and fertilizers, and defended taxing coal and oil export windfall profits as world demand for hydrocarbons declines. | K49: critical minerals general, mining general | L49: energy transition, royalties taxation | M49: not mentioned | N49: not mentioned | O49: En las áreas en donde se puede explorar busquemos los minerales para las energías limpias. Busquemos los minerales para fertilizar las tierras | P49: In the areas where exploration is possible, let us look for minerals for clean energy. Let us look for minerals to fertilize the land | Q49: es | R49: Forbes Perú (EFE) | S49: news media | T49: secondary reported | U49: Also reported by Mining Weekly 2022-09-04.
A50: PS-0049 | B50: 2022-09-14 | C50: Ecuador | D50: Yes | E50: Embassy of the People's Republic of China in Ecuador | F50: Embassy spokesperson | G50: China | H50: official statement | I50: Rebuttal of SOUTHCOM Commander Laura Richardson's remarks at the South American Defense Conference (Southdec) | J50: The Chinese embassy in Ecuador called Gen. Laura Richardson's claim that large Chinese mining projects were eroding Ecuadorian water sources 'ridiculous', saying Chinese firms follow strict environmental standards and contribute to local development. It accused the US of double standards and of seeking to sow discord between China and Ecuador. | K50: mining general | L50: environment water, geopolitics security, foreign investment, diplomatic relations | M50: positive | N50: negative | O50: sus difamaciones no muestran el mínimo respeto a Ecuador | P50: her defamations show not the slightest respect for Ecuador | Q50: es | R50: Vistazo | S50: news media | T50: secondary reported | U50: Date per Vistazo report (Wednesday 14 Sep 2022); embassy statement itself not seen.
A51: PS-0050 | B51: 2022-09-20 | C51: Bolivia | D51: Yes | E51: Luis Arce | F51: President of Bolivia | G51: LatAm executive | H51: speech | I51: 77th UN General Assembly, New York | J51: At the UN General Assembly, Arce reaffirmed sovereignty over natural resources such as lithium and rejected interference and destabilization attempts aimed at controlling lithium, urging UN action against countries that do not respect non-interference. | K51: lithium | L51: sovereignty, geopolitics security, value added industrialization | M51: not mentioned | N51: not mentioned | O51: Rechazamos todo tipo de injerencias y afanes de desestabilización de las democracia en nuestro país, con el afán de controlar el litio | P51: We reject all kinds of interference and attempts to destabilize democracy in our country with the aim of controlling lithium | Q51: es | R51: Emol | S51: news media | T51: secondary reported
A52: PS-0051 | B52: 2022-09-21 | C52: Argentina | D52: Yes | E52: Sabino Vaca Narvaja | F52: Argentine Ambassador to China | G52: LatAm executive | H52: speech | I52: China Mining fair opening, Tianjin | J52: Vaca Narvaja, the only foreign speaker at the ceremony, promoted Argentina as a land of mining opportunity with clear rules and said China will play a key role in Argentine mining development. | K52: mining general, lithium | L52: foreign investment, diplomatic relations | M52: positive | N52: not mentioned | O52: China jugará un papel clave en el desarrollo minero argentino | P52: China will play a key role in Argentine mining development | Q52: es | R52: Tiempo Argentino | S52: news media | T52: secondary reported
A53: PS-0052 | B53: 2022-09-22 | C53: Argentina | D53: Yes | E53: Alberto Fernández | F53: President of Argentina | G53: LatAm executive | H53: speech | I53: Talk at The New School, New York | J53: Fernández said lithium should be considered a strategic resource while respecting that it belongs to the provinces under Argentina's federal system, contrasting Chile's and Bolivia's models. | K53: lithium | L53: state control nationalization, sovereignty | M53: not mentioned | N53: not mentioned | O53: Debemos considerar el litio como un recurso estratégico | P53: We must consider lithium a strategic resource | Q53: es | R53: Reporte Minero | S53: news media | T53: secondary reported
A54: PS-0053 | B54: 2022-09-23 | C54: Bolivia | D54: Yes | E54: Evo Morales | F54: Former President of Bolivia; MAS leader | G54: Other (business, civil society, third countries) | H54: social media post | I54: Claims about UK role in 2019 crisis | J54: Morales tweeted that evidence showed the 2019 'coup' was financed by the United Kingdom and its ambassador Jeff Glekin to take control of Bolivian lithium. | K54: lithium | L54: sovereignty, geopolitics security, diplomatic relations | M54: not mentioned | N54: not mentioned | O54: Ante la evidencia de que el golpe de Estado fue financiado por el Reino Unido y su embajador @jeffglekin para adueñarse del litio boliviano | P54: Given the evidence that the coup d'état was financed by the United Kingdom and its ambassador @jeffglekin to take over Bolivian lithium | Q54: es | R54: Correo del Sur | S54: news media | T54: secondary reported
A55: PS-0054 | B55: 2022-09-30 | C55: Argentina | D55: Yes | E55: Gerardo Morales | F55: Governor of Jujuy | G55: LatAm executive | H55: speech | I55: Presentation to US State Department and Department of Energy with governors Sáenz and Jalil | J55: Morales told US officials it is very important to deepen ties with the US and hoped more US companies would invest in the lithium provinces, calling lithium a strategic and critical mineral for the energy transition. | K55: lithium | L55: foreign investment, energy transition, diplomatic relations | M55: not mentioned | N55: positive | O55: Para nosotros es sumamente importante profundizar la relación bilateral con Estados Unidos y esperar así que más empresas norteamericanas inviertan en nuestras provincias | P55: For us it is extremely important to deepen the bilateral relationship with the United States and thus hope more American companies invest in our provinces | Q55: es | R55: TodoJujuy | S55: news media | T55: secondary reported
A56: PS-0055 | B56: 2022-10-24 | C56: Peru | D56: Yes | E56: Song Yang | F56: Chinese Ambassador to Peru | G56: China | H56: interview | I56: Interview with El Peruano on bilateral relations | J56: Song Yang said more than 10 Chinese mining companies had invested over US$23.1 billion in Peru, paying taxes and creating jobs, and presented Chancay port as a future integrated maritime hub for Latin America. | K56: mining general, copper | L56: foreign investment, infrastructure ports, diplomatic relations | M56: positive | N56: not mentioned | O56: Más de 10 empresas mineras chinas han invertido en el Perú, con una inversión total de más de 23.1 mil millones de dólares. | P56: More than 10 Chinese mining companies have invested in Peru, with total investment of over 23.1 billion dollars. | Q56: es | R56: El Peruano | S56: primary official | T56: primary verified | U56: El Peruano is the state gazette/newspaper
A57: PS-0056 | B57: 2022-11-04 | C57: Argentina | D57: Yes | E57: Sabino Vaca Narvaja | F57: Argentine Ambassador to China | G57: LatAm executive | H57: speech | I57: China International Import Expo, Shanghai; Tibet Summit lithium announcement | J57: At the CIIE, where Tibet Summit announced over US$2bn of lithium investment in Salta, Vaca Narvaja said China dominates the entire lithium chain and Argentina should exploit its privileged position hand in hand with China. | K57: lithium | L57: foreign investment, value added industrialization | M57: positive | N57: not mentioned | O57: Nuestro país tiene una posición privilegiada y debemos, explotarla al máximo de la mano de China | P57: Our country has a privileged position and we must exploit it to the fullest hand in hand with China | Q57: es | R57: La Voz de San Justo | S57: news media | T57: secondary reported | U57: Also reported by Cancillería (fetch timed out).
A58: PS-0057 | B58: 2022-12-16 | C58: Panama | D58: No | E58: Government of Panama | F58: Executive (Cortizo administration) | G58: LatAm executive | H58: official statement | I58: Breakdown of Cobre Panamá contract negotiations | J58: Panama's government halted talks with First Quantum and announced it would order suspension of Cobre Panamá operations, seeking a new contract with at least USD 375 million a year in taxes and royalties. | K58: copper | L58: royalties taxation, foreign investment, sovereignty | M58: not mentioned | N58: not mentioned | Q58: en | R58: First Quantum Minerals (company release) | S58: news media | T58: secondary reported | U58: Government position as described by the company; source is corporate.
A59: PS-0058 | B59: 2023-01-16 | C59: Colombia | D59: Yes | E59: Gustavo Petro | F59: President of Colombia | G59: LatAm executive | H59: speech | I59: Public event in Jericó, Antioquia | J59: Petro announced a ban on mining in Jericó, where AngloGold Ashanti's Quebradona copper project awaits licensing, said all mining titles would be reviewed against water protection, and announced a reform of the Mining Code. | K59: copper | L59: environment water, labor social conflict | M59: not mentioned | N59: not mentioned | O59: Entonces, nosotros escogemos el agua | P59: So we choose water | Q59: es | R59: Valora Analitik | S59: news media | T59: secondary reported
A60: PS-0059 | B60: 2023-01-19 | C60: Regional | D60: No | E60: Laura Richardson | F60: Commander, U.S. Southern Command | G60: United States | H60: interview | I60: Atlantic Council video conversation | J60: SOUTHCOM commander said Latin America matters to US security because of its resources, citing the 'lithium triangle' of Argentina, Bolivia and Chile with about 60% of world lithium, plus rare earth elements, oil and fresh water, and said the US must step up its game against adversaries. | K60: lithium, rare earths, copper | L60: geopolitics security | M60: negative | N60: positive | O60: Why this region matters with all its rich resource and rare earth elements, you've got the lithium triangle which is needed for technology today. | P60: Why this region matters with all its rich resource and rare earth elements, you've got the lithium triangle which is needed for technology today. | Q60: en | R60: Buenos Aires Herald | S60: news media | T60: secondary reported | U60: Quote as reported by Buenos Aires Herald; Spanish coverage (Conclusión https://www.conclusion.com.ar/?p=985547) adds '60% of the world's lithium is in the lithium triangle'.
A61: PS-0060 | B61: 2023-01-20 | C61: Bolivia | D61: Yes | E61: Luis Arce | F61: President of Bolivia | G61: LatAm executive | H61: speech | I61: Signing of DLE agreement between YLB and CBC consortium, La Paz | J61: Arce announced a US$1bn+ agreement with the Chinese CBC consortium (CATL, BRUNP, CMOC) to apply direct lithium extraction in Potosí and Oruro, targeting lithium battery exports by early 2025. | K61: lithium | L61: foreign investment, value added industrialization, technology transfer | M61: positive | N61: not mentioned | O61: Hoy hemos decidido darle un giro con industria con la extracción directa de litio | P61: Today we have decided to make a turn toward industry with direct lithium extraction | Q61: es | R61: Correo del Sur | S61: news media | T61: secondary reported
A62: PS-0061 | B62: 2023-01-22 | C62: Bolivia | D62: Yes | E62: Franklin Molina | F62: Minister of Hydrocarbons and Energy | G62: LatAm executive | H62: interview | I62: Interview on CBC lithium agreement | J62: Molina said the CBC deal involves joint investment in two lithium carbonate plants of 25,000 t each, with YLB retaining 100% ownership, and would generate over US$5bn in revenue. | K62: lithium | L62: foreign investment, state control nationalization, processing refining, technology transfer | M62: positive | N62: not mentioned | O62: nos va a permitir generar ingresos importantísimos para el país, que superarían los 5.000 millones de dólares | P62: it will allow us to generate very important revenues for the country, exceeding 5 billion dollars | Q62: es | R62: Correo del Sur | S62: news media | T62: secondary reported
A63: PS-0062 | B63: 2023-01-23 | C63: Regional | D63: No | E63: Laura Richardson | F63: Commander, US Southern Command | G63: United States | H63: speech | I63: Atlantic Council event, Washington | J63: The SOUTHCOM commander highlighted that about 60% of the world's lithium lies in the 'lithium triangle' of Argentina, Bolivia and Chile, framing the region's resources as strategically important to the US. | K63: lithium, rare earths | L63: geopolitics security | M63: not mentioned | N63: not mentioned | Q63: en | R63: Economía Sustentable | S63: news media | T63: secondary reported | U63: Quote as rendered by secondary source (may be back-translated); region-wide statement naming Bolivia. Quote cleared: only translated wording seen.
A64: PS-0063 | B64: 2023-02-18 | C64: Mexico | D64: No | E64: Andrés Manuel López Obrador | F64: President of Mexico | G64: LatAm executive | H64: decree or regulation | I64: Signing of lithium nationalization decree, Bacadéhuachi, Sonora | J64: In Bacadéhuachi, Sonora, AMLO signed a decree transferring lithium reserve areas to the Energy Ministry, saying lithium would be nationalized so that foreigners from Russia, China or the US could not exploit it. | K64: lithium | L64: state control nationalization, sovereignty, geopolitics security | M64: negative | N64: negative | O64: Vamos a nacionalizar el litio para que no lo puedan explotar los extranjeros ni de Rusia, ni de China, ni de Estados Unidos | P64: We are going to nationalize lithium so that foreigners from Russia, China or the United States cannot exploit it | Q64: es | R64: N+ | S64: news media | T64: secondary reported | U64: Stance toward CHN/USA coded negative regarding their exploitation of Mexican lithium.
A65: PS-0064 | B65: 2023-03 | C65: Ecuador | D65: Yes | E65: Corte Provincial de Justicia de Imbabura | F65: Provincial Court of Imbabura | G65: LatAm judiciary | H65: court ruling | I65: Protection action against Llurimagua copper project | J65: The Imbabura provincial court upheld a 2020 first-instance ruling, revoking the Llurimagua copper project's environmental license over violations of environmental rights and consultation obligations. | K65: copper | L65: environment water, indigenous community rights | M65: not mentioned | N65: not mentioned | Q65: es | R65: Primicias | S65: news media | T65: secondary reported | U65: Reported retrospectively in 2026 article; day unknown.
A66: PS-0065 | B66: 2023-03-08 | C66: Regional | D66: No | E66: Laura Richardson | F66: Commander, U.S. Southern Command | G66: United States | H66: report | I66: SOUTHCOM 2023 Posture Statement to Congress | J66: The 2023 posture statement warned that the PRC has expanded its ability to extract resources, establish ports and manipulate governments through predatory investment in the region. | K66: mining general | L66: geopolitics security, foreign investment, infrastructure ports | M66: negative | N66: positive | O66: The PRC has expanded its ability to extract resources, establish ports, manipulate governments through predatory investment practices | P66: The PRC has expanded its ability to extract resources, establish ports, manipulate governments through predatory investment practices | Q66: en | R66: U.S. Southern Command | S66: primary official | T66: primary verified
A67: PS-0066 | B67: 2023-03-08 | C67: Regional | D67: No | E67: Laura Richardson | F67: Commander, U.S. Southern Command | G67: United States | H67: legislative debate | I67: House Armed Services Committee hearing on SOUTHCOM posture | J67: Testifying to the House, Richardson said the region is full of resources exploited by adversaries who appear to invest but actually extract, and described China's lithium game in the region as very advanced and aggressive. | K67: lithium | L67: geopolitics security, foreign investment | M67: negative | N67: positive | O67: la agresividad de China y su juego en el terreno con el litio, es muy avanzado y muy agresivo | P67: China's aggressiveness and its game on the ground with lithium is very advanced and very aggressive | Q67: es | R67: El Observador (Uruguay) | S67: news media | T67: secondary reported | U67: Spanish rendering of English testimony; also reported by El Ciudadano https://www.elciudadano.com/?p=942911 (dated 10 Mar 2023)
A68: PS-0067 | B68: 2023-03-23 | C68: Regional | D68: No | E68: Laura Richardson | F68: Commander, U.S. Southern Command | G68: United States | H68: legislative debate | I68: Senate Armed Services Committee hearing on NORTHCOM/SOUTHCOM posture | J68: Testifying to the Senate, Richardson said the PRC has expanded its ability to extract resources from the region and gets 75 percent of its lithium from South America. | K68: lithium | L68: geopolitics security | M68: negative | N68: positive | O68: The PRC has expanded its ability to extract resources, and gets 36 percent of its food imports from the region and 75 percent of its lithium from South America. | P68: The PRC has expanded its ability to extract resources, and gets 36 percent of its food imports from the region and 75 percent of its lithium from South America. | Q68: en | R68: Senate Armed Services Committee transcript | S68: legislative record | T68: primary verified
A69: PS-0068 | B69: 2023-03-24 | C69: Bolivia | D69: Yes | E69: Luis Arce | F69: President of Bolivia | G69: LatAm executive | H69: speech | I69: Speech in La Paz proposing joint Latin American lithium policy | J69: Arce called for a common, sovereign Latin American lithium market policy and said Bolivia did not want its lithium in the US Southern Command's crosshairs or used to destabilize elected governments. | K69: lithium | L69: geopolitics security, sovereignty, trade deals offtake | M69: not mentioned | N69: negative | Q69: en | R69: Mining Weekly (Reuters) | S69: news media | T69: secondary reported | U69: Quote is English translation by Reuters; Spanish original not seen. Quote cleared: only translated wording seen.
A70: PS-0069 | B70: 2023-03-31 | C70: Regional | D70: No | E70: U.S. Department of the Treasury | F70: Treasury (Sec. Janet Yellen) | G70: United States | H70: decree or regulation | I70: Proposed guidance on IRA clean vehicle credit (Section 30D) critical minerals requirement | J70: Treasury's proposed IRA guidance listed free-trade-agreement countries, including Chile, Colombia, Mexico, Panama and Peru, whose extracted or processed critical minerals count toward the EV credit's rising sourcing thresholds (40% in 2023 to 80% from 2027). | K70: critical minerals general, lithium, nickel, cobalt, graphite | L70: tariffs trade policy, energy transition, trade deals offtake | M70: not mentioned | N70: positive | Q70: en | R70: U.S. Department of the Treasury | S70: primary official | T70: primary verified | U70: Argentina, Bolivia, Brazil not FTA partners (excluded unless new critical minerals agreement)
A71: PS-0070 | B71: 2023-04-06 | C71: Argentina | D71: Yes | E71: Sabino Vaca Narvaja | F71: Argentine Ambassador to China | G71: LatAm executive | H71: speech | I71: Tour of Fujian province with Catamarca governor Jalil | J71: Vaca Narvaja said mining has the potential to solve Argentina's recurrent foreign-currency crises, noting a single lithium project could account for up to 5% of national exports. | K71: lithium, mining general | L71: foreign investment, trade deals offtake | M71: positive | N71: not mentioned | O71: la minería tiene el potencial para solucionar nuestras recurrentes crisis de divisas | P71: mining has the potential to solve our recurrent foreign-currency crises | Q71: es | R71: El Economista | S71: news media | T71: secondary reported | U71: Trip followed Jalil's China visit seeking lithium investment (Zijin).
A72: PS-0071 | B72: 2023-04-09 | C72: Chile | D72: Yes | E72: Bob Menendez | F72: U.S. Senator, Chair of Senate Foreign Relations Committee | G72: United States | H72: interview | I72: Visit to Chile, April 2023 | J72: During a visit to Chile, Senator Menendez said China lacked environmental standards and sought the easiest way to extract lithium, contrasting it with US standards and China's state-controlled model. | K72: lithium | L72: geopolitics security, environment water | M72: negative | N72: positive | Q72: en | R72: Ex-Ante | S72: news media | T72: secondary reported | U72: Paraphrase; quotes reported in Spanish translation via Chinese ambassador rebuttal article
A73: PS-0072 | B73: 2023-04-09 | C73: Chile | D73: Yes | E73: Niu Qingbao | F73: Chinese Ambassador to Chile | G73: China | H73: op ed | I73: Rebuttal to Senator Menendez's remarks on Chinese lithium extraction | J73: The Chinese ambassador published a rebuttal titled "Double standards are Mr. Bob Menendez's trademark", defending China as the largest clean-energy producer and accusing the US of coercing countries through coups, threats and sanctions. | K73: lithium | L73: geopolitics security, environment water, diplomatic relations | M73: positive | N73: negative | Q73: es | R73: Ex-Ante | S73: news media | T73: secondary reported | U73: Paraphrase; article date 9 Apr 2023
A74: PS-0073 | B74: 2023-04-14 | C74: Brazil | D74: Yes | E74: Xi Jinping | F74: President of the People's Republic of China | G74: China | H74: joint declaration or mou | I74: Lula state visit to Beijing; joint statement on deepening comprehensive strategic partnership | J74: The China-Brazil joint statement issued during Lula's state visit says both sides will actively encourage their companies to invest in each other's countries, particularly in infrastructure, energy transition, logistics, energy, mining, agriculture, industry and high technology. It names no specific minerals. | K74: mining general | L74: foreign investment, energy transition, diplomatic relations | M74: positive | N74: not mentioned | O74: 双方同意积极鼓励两国企业到对方国家开展投资，特别是在基础设施、能源转型、物流、能源、矿业、农业、工业以及高科技领域。 | P74: The two sides agree to actively encourage their enterprises to invest in each other's countries, especially in infrastructure, energy transition, logistics, energy, mining, agriculture, industry and high-tech fields. | Q74: zh | R74: Ministry of Foreign Affairs of the PRC | S74: primary official | T74: primary verified | U74: Paragraph 21 of the joint statement. Joint China-Brazil text attributed to Xi as China's head of state, following the existing China-Peru joint statement record. Mining is one sector in a list; weak mineral content.
A75: PS-0074 | B75: 2023-04-17 | C75: Argentina | D75: Yes | E75: Laura Richardson | F75: Commander, U.S. Southern Command | G75: United States | H75: official statement | I75: SOUTHCOM commander visit to Argentina (Patagonia, Ushuaia) | J75: Richardson's visit to Argentina and the Southern Cone was reported as having lithium and concern over China on the agenda, following her earlier public emphasis on the lithium triangle as a US security interest. | K75: lithium | L75: geopolitics security, diplomatic relations | M75: negative | N75: positive | Q75: en | R75: Buenos Aires Times | S75: news media | T75: secondary reported | U75: Visit-level record; no direct quote on lithium during visit
A76: PS-0075 | B76: 2023-04-20 | C76: Chile | D76: Yes | E76: Gabriel Boric | F76: President of Chile | G76: LatAm executive | H76: speech | I76: National broadcast announcing the National Lithium Strategy | J76: Boric announced the National Lithium Strategy with the state as central actor, a future National Lithium Company seeking private partners, a salt-flat protection network and community involvement. | K76: lithium | L76: state control nationalization, value added industrialization, environment water, indigenous community rights | M76: not mentioned | N76: not mentioned | O76: nuestro desafío es que nuestro país se convierta en el principal productor de litio en el mundo | P76: our challenge is for our country to become the main lithium producer in the world | Q76: es | R76: El Dínamo | S76: news media | T76: secondary reported
A77: PS-0076 | B77: 2023-04-20 | C77: Chile | D77: Yes | E77: Ricardo Díaz | F77: Governor of Antofagasta Region | G77: LatAm executive | H77: interview | I77: Reaction to National Lithium Strategy | J77: Antofagasta governor welcomed the president's view that value could be added in the region but criticised the absence of indigenous communities and regional participation in the strategy's launch. | K77: lithium | L77: value added industrialization, indigenous community rights | M77: not mentioned | N77: not mentioned | O77: El Presidente vio que se puede agregar valor acá en la región con personal de la región. | P77: The President saw that value can be added here in the region with people from the region. | Q77: es | R77: El Desconcierto | S77: news media | T77: secondary reported
A78: PS-0077 | B78: 2023-04-20 | C78: Mexico | D78: No | E78: Ildefonso Guajardo | F78: Federal Deputy (PRI) | G78: LatAm legislature | H78: legislative debate | I78: Chamber of Deputies debate on 2023 Mining Law reform | J78: Former economy minister Guajardo opposed the reform, arguing that articles 10 and 10 bis would cause Mexican mining to lose its potential. | K78: mining general | L78: foreign investment, state control nationalization | M78: not mentioned | N78: not mentioned | O78: con los artículos 10 y 10 bis de la reforma, la minería mexicana perderá su potencial | P78: with articles 10 and 10 bis of the reform, Mexican mining will lose its potential | Q78: es | R78: Excélsior | S78: news media | T78: secondary reported | U78: Debate ran overnight 20-21 April 2023.
A79: PS-0078 | B79: 2023-04-20 | C79: Mexico | D79: No | E79: Manuel Rodríguez González | F79: Federal Deputy (Morena); President of the Energy Commission | G79: LatAm legislature | H79: legislative debate | I79: Chamber of Deputies debate on 2023 Mining Law and water concessions reform | J79: Presenting the reform, Rodríguez said its central aim was to recover state stewardship over mineral and water resources; the bill shortened mining concessions and water concessions for mining. | K79: mining general | L79: state control nationalization, environment water, sovereignty | M79: not mentioned | N79: not mentioned | O79: La esencia y objetivo central es recuperar la rectoría del Estado sobre los recursos minerales e hídricos del subsuelo mexicano | P79: The essence and central objective is to recover the State's stewardship over the mineral and water resources of the Mexican subsoil | Q79: es | R79: Zeta Tijuana | S79: news media | T79: secondary reported | U79: Debate ran overnight 20-21 April 2023.
A80: PS-0079 | B80: 2023-04-21 | C80: Mexico | D80: No | E80: Cámara de Diputados de México | F80: Chamber of Deputies | G80: LatAm legislature | H80: bill or law | I80: Vote on 2023 Mining Law and water concessions reform | J80: The Chamber of Deputies approved in general the AMLO-backed reform of the Mining Law, National Waters Law and environmental laws by 290 votes to 186 with 1 abstention; Morena, PT, PVEM and MC supported it while PAN, PRI and PRD opposed. | K80: mining general | L80: state control nationalization, environment water | M80: not mentioned | N80: not mentioned | Q80: es | R80: Excélsior | S80: news media | T80: secondary reported | U80: In particular: 251-209-1 (Infobae via Cámara síntesis).
A81: PS-0080 | B81: 2023-04-22 | C81: Mexico | D81: No | E81: Asociación de Ingenieros de Minas, Metalurgistas y Geólogos de México (AIMMGM) | F81: Mining professional association | G81: Other (business, civil society, third countries) | H81: official statement | I81: Reaction to Chamber approval of Mining Law reform | J81: The mining engineers' association urged the Senate to hold an open parliament before ratifying the fast-tracked reform, warning of provisions on exploration, payments and restrictions affecting the industry. | K81: mining general | L81: foreign investment, corruption governance | M81: not mentioned | N81: not mentioned | O81: Antes de ratificar la reforma aprobada por la Cámara de Diputados, el Senado de la República debe convocar a un parlamento abierto | P81: Before ratifying the reform approved by the Chamber of Deputies, the Senate must convene an open parliament | Q81: es | R81: Forbes México (via Cámara de Diputados síntesis) | S81: news media | T81: secondary reported | U81: Industry actor.
A82: PS-0081 | B82: 2023-04-23 | C82: Mexico | D82: No | E82: COPARMEX | F82: Employers' confederation | G82: Other (business, civil society, third countries) | H82: official statement | I82: Press release on Mining Law reform | J82: COPARMEX asked the Senate not to fast-track the mining reform, calling for an open parliament with experts and firms, investment certainty, and postponing approval until September. | K82: mining general | L82: foreign investment, corruption governance | M82: not mentioned | N82: not mentioned | O82: es necesario escuchar a expertos y a las empresas mediante un parlamento abierto | P82: it is necessary to listen to experts and companies through an open parliament | Q82: es | R82: COPARMEX | S82: primary official | T82: primary verified | U82: Business association, not government.
A83: PS-0082 | B83: 2023-04-26 | C83: Argentina | D83: Yes | E83: Juan Carlos Alderete | F83: National Deputy (Frente de Todos - CCC) | G83: LatAm legislature | H83: bill or law | I83: Bill declaring lithium a strategic resource (with Dep. Verónica Caliva) | J83: Alderete and Caliva promoted a bill declaring lithium a strategic natural resource, stressing sovereignty, industrialization, environmental protection and indigenous rights. | K83: lithium | L83: state control nationalization, sovereignty, value added industrialization, indigenous community rights | M83: not mentioned | N83: not mentioned | O83: Es imprescindible que tomemos la defensa de nuestra soberanía, y protejamos los intereses nacionales referidos a este recurso natural estratégico | P83: It is essential that we defend our sovereignty and protect national interests regarding this strategic natural resource | Q83: es | R83: Diario de Cuyo | S83: news media | T83: secondary reported
A84: PS-0083 | B84: 2023-04-28 | C84: Mexico | D84: No | E84: Grupo México (Leonardo Contreras) | F84: Director of Administration and Finance, Mining Division, Grupo México | G84: Other (business, civil society, third countries) | H84: press conference | I84: Analyst/investor call during Senate debate on Mining Law reform | J84: A Grupo México executive told analysts the company saw no effect of the proposed Mining Law reform on its current business and was awaiting the outcome. | K84: copper, mining general | L84: foreign investment | M84: not mentioned | N84: not mentioned | O84: No vemos ningún efecto en nuestro negocio actual, estamos esperando las resoluciones | P84: We see no effect on our current business, we are waiting for the resolutions | Q84: es | R84: Bloomberg (via Cámara de Diputados síntesis) | S84: news media | T84: secondary reported | U84: Corporate actor.
A85: PS-0084 | B85: 2023-04-29 | C85: Mexico | D85: No | E85: Senado de la República | F85: Mexican Senate | G85: LatAm legislature | H85: bill or law | I85: Senate vote on 2023 Mining Law and water concessions reform | J85: The Senate approved the Mining Law, National Waters Law and environmental law reforms with 66 votes in a session held at an alternate venue without the opposition, sending them to the executive. | K85: mining general | L85: state control nationalization, environment water | M85: not mentioned | N85: not mentioned | Q85: es | R85: Bloomberg Línea | S85: news media | T85: secondary reported | U85: Session ran late 28 April into 29 April; date of report used.
A86: PS-0085 | B86: 2023-05 | C86: Chile | D86: Yes | E86: Senate of Chile | F86: Senate (plenary) | G86: LatAm legislature | H86: bill or law | I86: Senate vote on mining royalty bill (second constitutional stage) | J86: The Senate approved the mining royalty bill on large copper and lithium producers 38-2 with one abstention, sending it to the Chamber for the third stage; Republican senators Rojo Edwards and Aravena voted against. | K86: copper, lithium | L86: royalties taxation | M86: not mentioned | N86: not mentioned | Q86: es | R86: Radio Agricultura | S86: news media | T86: secondary reported | U86: Vote 10-11 May 2023; article dated 11 May
A87: PS-0086 | B87: 2023-05-02 | C87: Mexico | D87: No | E87: Andrés Guevara Cárdenas | F87: Local Deputy, Congress of Guerrero | G87: LatAm legislature | H87: legislative debate | I87: Guerrero state congress session commenting on federal Mining Law reform | J87: In the Guerrero state congress, Guevara praised the federal mining reform as putting citizens, environment and national territory at the centre and respecting natural resources and communities. | K87: mining general | L87: environment water, indigenous community rights, state control nationalization | M87: not mentioned | N87: not mentioned | O87: Hoy estamos ante una reforma que representa el respeto a nuestros recursos naturales y a la población de las comunidades | P87: Today we are facing a reform that represents respect for our natural resources and for the population of the communities | Q87: es | R87: Congreso del Estado de Guerrero | S87: legislative record | T87: primary verified | U87: Party affiliation inferred from content of the intervention; verify.
A88: PS-0087 | B88: 2023-05-03 | C88: Argentina | D88: Yes | E88: Marc Stanley | F88: US Ambassador to Argentina | G88: United States | H88: speech | I88: Event at Inter-American Dialogue, Washington | J88: Stanley said the US needs more tools to compete with China in the region, citing a lithium trade initiative among planned US-Argentina efforts. | K88: lithium | L88: geopolitics security, trade deals offtake | M88: negative | N88: positive | Q88: es | R88: Inter-American Dialogue (reprinting Clarín) | S88: think tank or ngo | T88: secondary reported | U88: Only partial quote ('más herramientas') available; paraphrased.
A89: PS-0088 | B89: 2023-05-04 | C89: Mexico | D89: No | E89: Andrés Manuel López Obrador | F89: President of Mexico | G89: LatAm executive | H89: press conference | I89: Mañanera after Congress approved 2023 Mining Law reform | J89: AMLO said the newly approved Mining Law would apply to future concessions and that his government would not grant any new concessions, recalling environmental damage from gold mining at Cerro de San Pedro. | K89: mining general | L89: state control nationalization, environment water | M89: not mentioned | N89: not mentioned | O89: una ley para aplicarse en el futuro cuando se entreguen concesiones, si es que van a entregar concesiones, en el caso de nosotros no vamos a entregar concesiones | P89: a law to be applied in the future when concessions are granted, if they are granted; in our case we will not grant concessions | Q89: es | R89: N+ | S89: news media | T89: secondary reported
A90: PS-0089 | B90: 2023-05-08 | C90: Mexico | D90: No | E90: Andrés Manuel López Obrador | F90: President of Mexico | G90: LatAm executive | H90: bill or law | I90: Promulgation of Mining Law reform in Diario Oficial | J90: The reform package cutting mining concessions to up to 80 years and water concessions to 30 years was published in the official gazette; AMLO argued it did not harm investors, noting miners had earned record profits. | K90: mining general | L90: state control nationalization, environment water, royalties taxation | M90: not mentioned | N90: not mentioned | O90: han obtenido utilidades y en algunos casos, como nunca | P90: they have obtained profits, and in some cases like never before | Q90: es | R90: Zeta Tijuana | S90: news media | T90: secondary reported | U90: Quote date approximate (reported with promulgation).
A91: PS-0090 | B91: 2023-05-08 | C91: Mexico | D91: No | E91: Raquel Buenrostro | F91: Secretary of Economy of Mexico | G91: LatAm executive | H91: press conference | I91: Explaining new Mining Law | J91: Buenrostro said that under the new law concessions in water-scarce areas would only be granted with presidential authorization and that there would be no new concessions because people have priority over water. | K91: mining general | L91: environment water, state control nationalization | M91: not mentioned | N91: not mentioned | O91: No habrá concesiones nuevas porque no hay agua y la prioridad la tiene la gente | P91: There will be no new concessions because there is no water and people have priority | Q91: es | R91: El Financiero | S91: news media | T91: secondary reported | U91: Exact date of remark approximate (article date).
A92: PS-0091 | B92: 2023-05-09 | C92: Brazil | D92: Yes | E92: Romeu Zema | F92: Governor of Minas Gerais | G92: LatAm executive | H92: speech | I92: Launch of 'Vale do Lítio' project at Nasdaq, New York | J92: Launching the Lithium Valley initiative at Nasdaq, Zema said Minas Gerais would proceed in stages from extraction to processing and purification and had begun contacts with battery makers, pledging careful but solution-oriented environmental licensing. | K92: lithium | L92: foreign investment, value added industrialization, environment water, energy transition | M92: not mentioned | N92: not mentioned | O92: Estamos começando já acima do básico, não estamos vendendo o minério sem beneficiamento | P92: We are already starting above the basics; we are not selling the ore without processing | Q92: pt | R92: Itatiaia | S92: news media | T92: secondary reported
A93: PS-0092 | B93: 2023-05-09 | C93: Mexico | D93: No | E93: Pablo Taddei | F93: Director General of LitioMx | G93: LatAm state company | H93: interview | I93: Interview on LitioMx plans | J93: Taddei said existing concessions would be respected, that the state's role vis-a-vis private participation had been misinterpreted, and that his duty was to obtain lithium in the most economically viable way. | K93: lithium | L93: state control nationalization, foreign investment, technology transfer | M93: not mentioned | N93: not mentioned | O93: El Estado mexicano, aunque suene trillado, es respetuoso de la ley y eso ha sido una orden del presidente desde el inicio. Se respetarán las concesiones | P93: The Mexican state, trite as it sounds, respects the law and that has been the president's order from the start. Concessions will be respected | Q93: es | R93: Expansión | S93: news media | T93: secondary reported | U93: Article reports first production expected around 2028.
A94: PS-0093 | B94: 2023-05-10 | C94: Brazil | D94: Yes | E94: Alexandre Silveira | F94: Minister of Mines and Energy of Brazil | G94: LatAm executive | H94: speech | I94: Event on Vale do Lítio / mining in Minas Gerais | J94: Silveira stressed that Minas Gerais's economy depends on mining beyond iron ore, citing Jequitinhonha lithium, niobium and potash as strategic minerals for the energy transition, as his ministry engaged in Zema's Lithium Valley investor talks. | K94: lithium, niobium, iron ore | L94: energy transition, foreign investment | M94: not mentioned | N94: not mentioned | O94: Não é só a questão do minério de ferro. Os minerais estratégicos (também): o lítio do Vale do Jequitinhonha, o nióbio, o potássio | P94: It is not only about iron ore. Strategic minerals too: Jequitinhonha Valley lithium, niobium, potash | Q94: pt | R94: Itatiaia | S94: news media | T94: secondary reported | U94: Date = article date; statement may be earlier
A95: PS-0094 | B95: 2023-05-15 | C95: Chile | D95: Yes | E95: Bernadette Meehan | F95: U.S. Ambassador to Chile | G95: United States | H95: interview | I95: Interview on National Lithium Strategy and US-China competition | J95: The US ambassador said it was wrong to call Chile's lithium strategy a nationalisation, said US firms wanted to be part of the industry, denied the US forces Chile to choose sides and called for fair competition with state-backed firms. | K95: lithium | L95: foreign investment, geopolitics security, state control nationalization | M95: negative | N95: positive | O95: es un error decir que es una nacionalización de la industria | P95: it is a mistake to say it is a nationalisation of the industry | Q95: es | R95: Redimin | S95: news media | T95: secondary reported | U95: stance_china negative inferred from remarks on state-backed firms and coercion (China implied)
A96: PS-0095 | B96: 2023-05-16 | C96: Argentina | D96: Yes | E96: Juan Carlos Alderete | F96: National Deputy (Frente de Todos - CCC) | G96: LatAm legislature | H96: interview | I96: Defending lithium strategic-resource bill | J96: Alderete said his bill does not nationalize lithium but declares it strategic, keeping it provincial while the national state sets minimal regulation of companies and pushes industrialization. | K96: lithium | L96: state control nationalization, sovereignty, value added industrialization | M96: not mentioned | N96: not mentioned | O96: No es nacionalizar el litio, sino declararlo recurso estratégico, el litio seguirá siendo de las provincias | P96: It is not nationalizing lithium but declaring it a strategic resource; lithium will remain the provinces' | Q96: es | R96: Bloomberg Línea | S96: news media | T96: secondary reported
A97: PS-0399 | B97: 2023-06-08 | C97: Guyana | D97: Yes | E97: Bharrat Jagdeo | F97: Vice President of Guyana | G97: LatAm executive | H97: press conference | I97: Press conference at Freedom House after a Matthews Ridge outreach; Guyana Manganese Inc. (Bosai) disputes commitments made by the previous Canadian owner | J97: Jagdeo said the government would make the Chinese-owned Guyana Manganese Inc. honour the community commitments made when its licences were granted, rejecting the company's view that the previous owner's promises no longer apply, because the company had received substantial concessions. | K97: manganese | L97: labor social conflict, foreign investment, corruption governance | M97: mixed | N97: not mentioned | O97: the commitments have to be met because they had quite a bit of concessions granted to them | P97: the commitments have to be met because they had quite a bit of concessions granted to them | Q97: en | R97: Kaieteur News | S97: news media | T97: secondary reported | U97: Coded by an AI session (2026-10-09) under the README vocabularies, from web-search results that cite the page; the page itself was not opened. Article of 11 June 2023 reporting a press conference held 'on Thursday' (8 June 2023).
A98: PS-0096 | B98: 2023-06-20 | C98: Argentina | D98: Yes | E98: Alberto Fernández | F98: President of Argentina | G98: LatAm executive | H98: social media post | I98: Jujuy constitutional reform protests | J98: Fernández held Governor Morales solely responsible for the crisis in Jujuy, saying the constitutional reform ignores international agreements, does not listen to indigenous peoples and denies the right to protest. | K98: lithium | L98: indigenous community rights, labor social conflict | M98: not mentioned | N98: not mentioned | O98: Usted es el único responsable de haber llevado a nuestra querida provincia de Jujuy a esta situación límite | P98: You are solely responsible for bringing our beloved province of Jujuy to this breaking point | Q98: es | R98: Los Andes | S98: news media | T98: secondary reported | U98: Statement does not explicitly mention lithium; coded lithium because the reform conflict centred on lithium/land rights of indigenous communities.
A99: PS-0097 | B99: 2023-06-20 | C99: Argentina | D99: Yes | E99: Gerardo Morales | F99: Governor of Jujuy | G99: LatAm executive | H99: official statement | I99: Jujuy constitutional reform protests | J99: Morales blamed President Fernández and Vice President Kirchner for the extreme violence in Jujuy and criticized the sending of activists from elsewhere; he later described the events as an attempted coup. | K99: lithium | L99: labor social conflict, indigenous community rights | M99: not mentioned | N99: not mentioned | O99: Hago responsable al Presidente y a la Vicepresidenta de la extrema violencia que se está viviendo en la provincia de Jujuy | P99: I hold the President and Vice President responsible for the extreme violence in the province of Jujuy | Q99: es | R99: Los Andes | S99: news media | T99: secondary reported | U99: No explicit lithium mention; context is the lithium-linked reform conflict.
A100: PS-0098 | B100: 2023-06-30 | C100: Colombia | D100: Yes | E100: Gustavo Petro | F100: President of Colombia | G100: LatAm executive | H100: speech | I100: Event in Albania, La Guajira (Cerrejón area) | J100: Petro said there could be no expansion of open-pit coal mining in Colombia, calling Cerrejón's expansion economically absurd given the expected collapse of world coal demand. | K100: mining general | L100: energy transition, environment water, labor social conflict | M100: not mentioned | N100: not mentioned | O100: No puede haber expansiones de explotación de carbón a cielo abierto en Colombia | P100: There can be no expansions of open-pit coal mining in Colombia | Q100: es | R100: Blu Radio | S100: news media | T100: secondary reported | U100: Coal is outside mineral vocabulary; coded mining_general. El Espectador reports same speech.
...

Sheet Coverage
A1: Coverage of the statements dataset
A2: All counts are COUNTIFS/SUMPRODUCT formulas on the Data sheet; they update if rows are added inside the Data range.
A6: Statements by country (the "country" field) and speaker bloc
A7: Code | B7: Country | C7: LatAm executive | D7: United States | E7: LatAm legislature | F7: China | G7: Other (business, civil society, third countries) | H7: LatAm party/candidate | I7: LatAm state company | J7: LatAm judiciary | K7: Total
A8: CHL | B8: Chile | C8: =COUNTIFS(Data!$D$2:$D$418,$A8,Data!$H$2:$H$418,"LatAm executive") | D8: =COUNTIFS(Data!$D$2:$D$418,$A8,Data!$H$2:$H$418,"United States") | E8: =COUNTIFS(Data!$D$2:$D$418,$A8,Data!$H$2:$H$418,"LatAm legislature") | F8: =COUNTIFS(Data!$D$2:$D$418,$A8,Data!$H$2:$H$418,"China") | G8: =COUNTIFS(Data!$D$2:$D$418,$A8,Data!$H$2:$H$418,"Other (business, civil society, third countries)") | H8: =COUNTIFS(Data!$D$2:$D$418,$A8,Data!$H$2:$H$418,"LatAm party/candidate") | I8: =COUNTIFS(Data!$D$2:$D$418,$A8,Data!$H$2:$H$418,"LatAm state company") | J8: =COUNTIFS(Data!$D$2:$D$418,$A8,Data!$H$2:$H$418,"LatAm judiciary") | K8: =SUM(C6:J6)
A9: PER | B9: Peru | C9: =COUNTIFS(Data!$D$2:$D$418,$A9,Data!$H$2:$H$418,"LatAm executive") | D9: =COUNTIFS(Data!$D$2:$D$418,$A9,Data!$H$2:$H$418,"United States") | E9: =COUNTIFS(Data!$D$2:$D$418,$A9,Data!$H$2:$H$418,"LatAm legislature") | F9: =COUNTIFS(Data!$D$2:$D$418,$A9,Data!$H$2:$H$418,"China") | G9: =COUNTIFS(Data!$D$2:$D$418,$A9,Data!$H$2:$H$418,"Other (business, civil society, third countries)") | H9: =COUNTIFS(Data!$D$2:$D$418,$A9,Data!$H$2:$H$418,"LatAm party/candidate") | I9: =COUNTIFS(Data!$D$2:$D$418,$A9,Data!$H$2:$H$418,"LatAm state company") | J9: =COUNTIFS(Data!$D$2:$D$418,$A9,Data!$H$2:$H$418,"LatAm judiciary") | K9: =SUM(C6:J6)
A10: BRA | B10: Brazil | C10: =COUNTIFS(Data!$D$2:$D$418,$A10,Data!$H$2:$H$418,"LatAm executive") | D10: =COUNTIFS(Data!$D$2:$D$418,$A10,Data!$H$2:$H$418,"United States") | E10: =COUNTIFS(Data!$D$2:$D$418,$A10,Data!$H$2:$H$418,"LatAm legislature") | F10: =COUNTIFS(Data!$D$2:$D$418,$A10,Data!$H$2:$H$418,"China") | G10: =COUNTIFS(Data!$D$2:$D$418,$A10,Data!$H$2:$H$418,"Other (business, civil society, third countries)") | H10: =COUNTIFS(Data!$D$2:$D$418,$A10,Data!$H$2:$H$418,"LatAm party/candidate") | I10: =COUNTIFS(Data!$D$2:$D$418,$A10,Data!$H$2:$H$418,"LatAm state company") | J10: =COUNTIFS(Data!$D$2:$D$418,$A10,Data!$H$2:$H$418,"LatAm judiciary") | K10: =SUM(C6:J6)
A11: ARG | B11: Argentina | C11: =COUNTIFS(Data!$D$2:$D$418,$A11,Data!$H$2:$H$418,"LatAm executive") | D11: =COUNTIFS(Data!$D$2:$D$418,$A11,Data!$H$2:$H$418,"United States") | E11: =COUNTIFS(Data!$D$2:$D$418,$A11,Data!$H$2:$H$418,"LatAm legislature") | F11: =COUNTIFS(Data!$D$2:$D$418,$A11,Data!$H$2:$H$418,"China") | G11: =COUNTIFS(Data!$D$2:$D$418,$A11,Data!$H$2:$H$418,"Other (business, civil society, third countries)") | H11: =COUNTIFS(Data!$D$2:$D$418,$A11,Data!$H$2:$H$418,"LatAm party/candidate") | I11: =COUNTIFS(Data!$D$2:$D$418,$A11,Data!$H$2:$H$418,"LatAm state company") | J11: =COUNTIFS(Data!$D$2:$D$418,$A11,Data!$H$2:$H$418,"LatAm judiciary") | K11: =SUM(C6:J6)
A12: BOL | B12: Bolivia | C12: =COUNTIFS(Data!$D$2:$D$418,$A12,Data!$H$2:$H$418,"LatAm executive") | D12: =COUNTIFS(Data!$D$2:$D$418,$A12,Data!$H$2:$H$418,"United States") | E12: =COUNTIFS(Data!$D$2:$D$418,$A12,Data!$H$2:$H$418,"LatAm legislature") | F12: =COUNTIFS(Data!$D$2:$D$418,$A12,Data!$H$2:$H$418,"China") | G12: =COUNTIFS(Data!$D$2:$D$418,$A12,Data!$H$2:$H$418,"Other (business, civil society, third countries)") | H12: =COUNTIFS(Data!$D$2:$D$418,$A12,Data!$H$2:$H$418,"LatAm party/candidate") | I12: =COUNTIFS(Data!$D$2:$D$418,$A12,Data!$H$2:$H$418,"LatAm state company") | J12: =COUNTIFS(Data!$D$2:$D$418,$A12,Data!$H$2:$H$418,"LatAm judiciary") | K12: =SUM(C6:J6)
A13: MEX | B13: Mexico | C13: =COUNTIFS(Data!$D$2:$D$418,$A13,Data!$H$2:$H$418,"LatAm executive") | D13: =COUNTIFS(Data!$D$2:$D$418,$A13,Data!$H$2:$H$418,"United States") | E13: =COUNTIFS(Data!$D$2:$D$418,$A13,Data!$H$2:$H$418,"LatAm legislature") | F13: =COUNTIFS(Data!$D$2:$D$418,$A13,Data!$H$2:$H$418,"China") | G13: =COUNTIFS(Data!$D$2:$D$418,$A13,Data!$H$2:$H$418,"Other (business, civil society, third countries)") | H13: =COUNTIFS(Data!$D$2:$D$418,$A13,Data!$H$2:$H$418,"LatAm party/candidate") | I13: =COUNTIFS(Data!$D$2:$D$418,$A13,Data!$H$2:$H$418,"LatAm state company") | J13: =COUNTIFS(Data!$D$2:$D$418,$A13,Data!$H$2:$H$418,"LatAm judiciary") | K13: =SUM(C6:J6)
A14: REG | B14: Regional | C14: =COUNTIFS(Data!$D$2:$D$418,$A14,Data!$H$2:$H$418,"LatAm executive") | D14: =COUNTIFS(Data!$D$2:$D$418,$A14,Data!$H$2:$H$418,"United States") | E14: =COUNTIFS(Data!$D$2:$D$418,$A14,Data!$H$2:$H$418,"LatAm legislature") | F14: =COUNTIFS(Data!$D$2:$D$418,$A14,Data!$H$2:$H$418,"China") | G14: =COUNTIFS(Data!$D$2:$D$418,$A14,Data!$H$2:$H$418,"Other (business, civil society, third countries)") | H14: =COUNTIFS(Data!$D$2:$D$418,$A14,Data!$H$2:$H$418,"LatAm party/candidate") | I14: =COUNTIFS(Data!$D$2:$D$418,$A14,Data!$H$2:$H$418,"LatAm state company") | J14: =COUNTIFS(Data!$D$2:$D$418,$A14,Data!$H$2:$H$418,"LatAm judiciary") | K14: =SUM(C6:J6)
A15: ECU | B15: Ecuador | C15: =COUNTIFS(Data!$D$2:$D$418,$A15,Data!$H$2:$H$418,"LatAm executive") | D15: =COUNTIFS(Data!$D$2:$D$418,$A15,Data!$H$2:$H$418,"United States") | E15: =COUNTIFS(Data!$D$2:$D$418,$A15,Data!$H$2:$H$418,"LatAm legislature") | F15: =COUNTIFS(Data!$D$2:$D$418,$A15,Data!$H$2:$H$418,"China") | G15: =COUNTIFS(Data!$D$2:$D$418,$A15,Data!$H$2:$H$418,"Other (business, civil society, third countries)") | H15: =COUNTIFS(Data!$D$2:$D$418,$A15,Data!$H$2:$H$418,"LatAm party/candidate") | I15: =COUNTIFS(Data!$D$2:$D$418,$A15,Data!$H$2:$H$418,"LatAm state company") | J15: =COUNTIFS(Data!$D$2:$D$418,$A15,Data!$H$2:$H$418,"LatAm judiciary") | K15: =SUM(C6:J6)
A16: PAN | B16: Panama | C16: =COUNTIFS(Data!$D$2:$D$418,$A16,Data!$H$2:$H$418,"LatAm executive") | D16: =COUNTIFS(Data!$D$2:$D$418,$A16,Data!$H$2:$H$418,"United States") | E16: =COUNTIFS(Data!$D$2:$D$418,$A16,Data!$H$2:$H$418,"LatAm legislature") | F16: =COUNTIFS(Data!$D$2:$D$418,$A16,Data!$H$2:$H$418,"China") | G16: =COUNTIFS(Data!$D$2:$D$418,$A16,Data!$H$2:$H$418,"Other (business, civil society, third countries)") | H16: =COUNTIFS(Data!$D$2:$D$418,$A16,Data!$H$2:$H$418,"LatAm party/candidate") | I16: =COUNTIFS(Data!$D$2:$D$418,$A16,Data!$H$2:$H$418,"LatAm state company") | J16: =COUNTIFS(Data!$D$2:$D$418,$A16,Data!$H$2:$H$418,"LatAm judiciary") | K16: =SUM(C6:J6)
A17: COL | B17: Colombia | C17: =COUNTIFS(Data!$D$2:$D$418,$A17,Data!$H$2:$H$418,"LatAm executive") | D17: =COUNTIFS(Data!$D$2:$D$418,$A17,Data!$H$2:$H$418,"United States") | E17: =COUNTIFS(Data!$D$2:$D$418,$A17,Data!$H$2:$H$418,"LatAm legislature") | F17: =COUNTIFS(Data!$D$2:$D$418,$A17,Data!$H$2:$H$418,"China") | G17: =COUNTIFS(Data!$D$2:$D$418,$A17,Data!$H$2:$H$418,"Other (business, civil society, third countries)") | H17: =COUNTIFS(Data!$D$2:$D$418,$A17,Data!$H$2:$H$418,"LatAm party/candidate") | I17: =COUNTIFS(Data!$D$2:$D$418,$A17,Data!$H$2:$H$418,"LatAm state company") | J17: =COUNTIFS(Data!$D$2:$D$418,$A17,Data!$H$2:$H$418,"LatAm judiciary") | K17: =SUM(C6:J6)
A18: GUY | B18: Guyana | C18: =COUNTIFS(Data!$D$2:$D$418,$A18,Data!$H$2:$H$418,"LatAm executive") | D18: =COUNTIFS(Data!$D$2:$D$418,$A18,Data!$H$2:$H$418,"United States") | E18: =COUNTIFS(Data!$D$2:$D$418,$A18,Data!$H$2:$H$418,"LatAm legislature") | F18: =COUNTIFS(Data!$D$2:$D$418,$A18,Data!$H$2:$H$418,"China") | G18: =COUNTIFS(Data!$D$2:$D$418,$A18,Data!$H$2:$H$418,"Other (business, civil society, third countries)") | H18: =COUNTIFS(Data!$D$2:$D$418,$A18,Data!$H$2:$H$418,"LatAm party/candidate") | I18: =COUNTIFS(Data!$D$2:$D$418,$A18,Data!$H$2:$H$418,"LatAm state company") | J18: =COUNTIFS(Data!$D$2:$D$418,$A18,Data!$H$2:$H$418,"LatAm judiciary") | K18: =SUM(C6:J6)
A19: VEN | B19: Venezuela | C19: =COUNTIFS(Data!$D$2:$D$418,$A19,Data!$H$2:$H$418,"LatAm executive") | D19: =COUNTIFS(Data!$D$2:$D$418,$A19,Data!$H$2:$H$418,"United States") | E19: =COUNTIFS(Data!$D$2:$D$418,$A19,Data!$H$2:$H$418,"LatAm legislature") | F19: =COUNTIFS(Data!$D$2:$D$418,$A19,Data!$H$2:$H$418,"China") | G19: =COUNTIFS(Data!$D$2:$D$418,$A19,Data!$H$2:$H$418,"Other (business, civil society, third countries)") | H19: =COUNTIFS(Data!$D$2:$D$418,$A19,Data!$H$2:$H$418,"LatAm party/candidate") | I19: =COUNTIFS(Data!$D$2:$D$418,$A19,Data!$H$2:$H$418,"LatAm state company") | J19: =COUNTIFS(Data!$D$2:$D$418,$A19,Data!$H$2:$H$418,"LatAm judiciary") | K19: =SUM(C6:J6)
A20: PRY | B20: Paraguay | C20: =COUNTIFS(Data!$D$2:$D$418,$A20,Data!$H$2:$H$418,"LatAm executive") | D20: =COUNTIFS(Data!$D$2:$D$418,$A20,Data!$H$2:$H$418,"United States") | E20: =COUNTIFS(Data!$D$2:$D$418,$A20,Data!$H$2:$H$418,"LatAm legislature") | F20: =COUNTIFS(Data!$D$2:$D$418,$A20,Data!$H$2:$H$418,"China") | G20: =COUNTIFS(Data!$D$2:$D$418,$A20,Data!$H$2:$H$418,"Other (business, civil society, third countries)") | H20: =COUNTIFS(Data!$D$2:$D$418,$A20,Data!$H$2:$H$418,"LatAm party/candidate") | I20: =COUNTIFS(Data!$D$2:$D$418,$A20,Data!$H$2:$H$418,"LatAm state company") | J20: =COUNTIFS(Data!$D$2:$D$418,$A20,Data!$H$2:$H$418,"LatAm judiciary") | K20: =SUM(C6:J6)
A21: SUR | B21: Suriname | C21: =COUNTIFS(Data!$D$2:$D$418,$A21,Data!$H$2:$H$418,"LatAm executive") | D21: =COUNTIFS(Data!$D$2:$D$418,$A21,Data!$H$2:$H$418,"United States") | E21: =COUNTIFS(Data!$D$2:$D$418,$A21,Data!$H$2:$H$418,"LatAm legislature") | F21: =COUNTIFS(Data!$D$2:$D$418,$A21,Data!$H$2:$H$418,"China") | G21: =COUNTIFS(Data!$D$2:$D$418,$A21,Data!$H$2:$H$418,"Other (business, civil society, third countries)") | H21: =COUNTIFS(Data!$D$2:$D$418,$A21,Data!$H$2:$H$418,"LatAm party/candidate") | I21: =COUNTIFS(Data!$D$2:$D$418,$A21,Data!$H$2:$H$418,"LatAm state company") | J21: =COUNTIFS(Data!$D$2:$D$418,$A21,Data!$H$2:$H$418,"LatAm judiciary") | K21: =SUM(C6:J6)
B22: Total | C22: =SUM(C8:C21) | D22: =SUM(D8:D21) | E22: =SUM(E8:E21) | F22: =SUM(F8:F21) | G22: =SUM(G8:G21) | H22: =SUM(H8:H21) | I22: =SUM(I8:I21) | J22: =SUM(J8:J21) | K22: =SUM(K8:K21)
B23: Check: rows in Data | K23: =COUNTA(Data!$A$2:$A$418)
A25: Stance toward China by country
A26: Code | B26: Country | C26: positive | D26: neutral | E26: mixed | F26: negative | G26: not mentioned | H26: Total
A27: CHL | B27: Chile | C27: =COUNTIFS(Data!$D$2:$D$418,$A27,Data!$Q$2:$Q$418,"positive") | D27: =COUNTIFS(Data!$D$2:$D$418,$A27,Data!$Q$2:$Q$418,"neutral") | E27: =COUNTIFS(Data!$D$2:$D$418,$A27,Data!$Q$2:$Q$418,"mixed") | F27: =COUNTIFS(Data!$D$2:$D$418,$A27,Data!$Q$2:$Q$418,"negative") | G27: =COUNTIFS(Data!$D$2:$D$418,$A27,Data!$Q$2:$Q$418,"not_mentioned") | H27: =SUM(C21:G21)
A28: PER | B28: Peru | C28: =COUNTIFS(Data!$D$2:$D$418,$A28,Data!$Q$2:$Q$418,"positive") | D28: =COUNTIFS(Data!$D$2:$D$418,$A28,Data!$Q$2:$Q$418,"neutral") | E28: =COUNTIFS(Data!$D$2:$D$418,$A28,Data!$Q$2:$Q$418,"mixed") | F28: =COUNTIFS(Data!$D$2:$D$418,$A28,Data!$Q$2:$Q$418,"negative") | G28: =COUNTIFS(Data!$D$2:$D$418,$A28,Data!$Q$2:$Q$418,"not_mentioned") | H28: =SUM(C21:G21)
A29: BRA | B29: Brazil | C29: =COUNTIFS(Data!$D$2:$D$418,$A29,Data!$Q$2:$Q$418,"positive") | D29: =COUNTIFS(Data!$D$2:$D$418,$A29,Data!$Q$2:$Q$418,"neutral") | E29: =COUNTIFS(Data!$D$2:$D$418,$A29,Data!$Q$2:$Q$418,"mixed") | F29: =COUNTIFS(Data!$D$2:$D$418,$A29,Data!$Q$2:$Q$418,"negative") | G29: =COUNTIFS(Data!$D$2:$D$418,$A29,Data!$Q$2:$Q$418,"not_mentioned") | H29: =SUM(C21:G21)
A30: ARG | B30: Argentina | C30: =COUNTIFS(Data!$D$2:$D$418,$A30,Data!$Q$2:$Q$418,"positive") | D30: =COUNTIFS(Data!$D$2:$D$418,$A30,Data!$Q$2:$Q$418,"neutral") | E30: =COUNTIFS(Data!$D$2:$D$418,$A30,Data!$Q$2:$Q$418,"mixed") | F30: =COUNTIFS(Data!$D$2:$D$418,$A30,Data!$Q$2:$Q$418,"negative") | G30: =COUNTIFS(Data!$D$2:$D$418,$A30,Data!$Q$2:$Q$418,"not_mentioned") | H30: =SUM(C21:G21)
A31: BOL | B31: Bolivia | C31: =COUNTIFS(Data!$D$2:$D$418,$A31,Data!$Q$2:$Q$418,"positive") | D31: =COUNTIFS(Data!$D$2:$D$418,$A31,Data!$Q$2:$Q$418,"neutral") | E31: =COUNTIFS(Data!$D$2:$D$418,$A31,Data!$Q$2:$Q$418,"mixed") | F31: =COUNTIFS(Data!$D$2:$D$418,$A31,Data!$Q$2:$Q$418,"negative") | G31: =COUNTIFS(Data!$D$2:$D$418,$A31,Data!$Q$2:$Q$418,"not_mentioned") | H31: =SUM(C21:G21)
A32: MEX | B32: Mexico | C32: =COUNTIFS(Data!$D$2:$D$418,$A32,Data!$Q$2:$Q$418,"positive") | D32: =COUNTIFS(Data!$D$2:$D$418,$A32,Data!$Q$2:$Q$418,"neutral") | E32: =COUNTIFS(Data!$D$2:$D$418,$A32,Data!$Q$2:$Q$418,"mixed") | F32: =COUNTIFS(Data!$D$2:$D$418,$A32,Data!$Q$2:$Q$418,"negative") | G32: =COUNTIFS(Data!$D$2:$D$418,$A32,Data!$Q$2:$Q$418,"not_mentioned") | H32: =SUM(C21:G21)
A33: REG | B33: Regional | C33: =COUNTIFS(Data!$D$2:$D$418,$A33,Data!$Q$2:$Q$418,"positive") | D33: =COUNTIFS(Data!$D$2:$D$418,$A33,Data!$Q$2:$Q$418,"neutral") | E33: =COUNTIFS(Data!$D$2:$D$418,$A33,Data!$Q$2:$Q$418,"mixed") | F33: =COUNTIFS(Data!$D$2:$D$418,$A33,Data!$Q$2:$Q$418,"negative") | G33: =COUNTIFS(Data!$D$2:$D$418,$A33,Data!$Q$2:$Q$418,"not_mentioned") | H33: =SUM(C21:G21)
A34: ECU | B34: Ecuador | C34: =COUNTIFS(Data!$D$2:$D$418,$A34,Data!$Q$2:$Q$418,"positive") | D34: =COUNTIFS(Data!$D$2:$D$418,$A34,Data!$Q$2:$Q$418,"neutral") | E34: =COUNTIFS(Data!$D$2:$D$418,$A34,Data!$Q$2:$Q$418,"mixed") | F34: =COUNTIFS(Data!$D$2:$D$418,$A34,Data!$Q$2:$Q$418,"negative") | G34: =COUNTIFS(Data!$D$2:$D$418,$A34,Data!$Q$2:$Q$418,"not_mentioned") | H34: =SUM(C21:G21)
A35: PAN | B35: Panama | C35: =COUNTIFS(Data!$D$2:$D$418,$A35,Data!$Q$2:$Q$418,"positive") | D35: =COUNTIFS(Data!$D$2:$D$418,$A35,Data!$Q$2:$Q$418,"neutral") | E35: =COUNTIFS(Data!$D$2:$D$418,$A35,Data!$Q$2:$Q$418,"mixed") | F35: =COUNTIFS(Data!$D$2:$D$418,$A35,Data!$Q$2:$Q$418,"negative") | G35: =COUNTIFS(Data!$D$2:$D$418,$A35,Data!$Q$2:$Q$418,"not_mentioned") | H35: =SUM(C21:G21)
A36: COL | B36: Colombia | C36: =COUNTIFS(Data!$D$2:$D$418,$A36,Data!$Q$2:$Q$418,"positive") | D36: =COUNTIFS(Data!$D$2:$D$418,$A36,Data!$Q$2:$Q$418,"neutral") | E36: =COUNTIFS(Data!$D$2:$D$418,$A36,Data!$Q$2:$Q$418,"mixed") | F36: =COUNTIFS(Data!$D$2:$D$418,$A36,Data!$Q$2:$Q$418,"negative") | G36: =COUNTIFS(Data!$D$2:$D$418,$A36,Data!$Q$2:$Q$418,"not_mentioned") | H36: =SUM(C21:G21)
A37: GUY | B37: Guyana | C37: =COUNTIFS(Data!$D$2:$D$418,$A37,Data!$Q$2:$Q$418,"positive") | D37: =COUNTIFS(Data!$D$2:$D$418,$A37,Data!$Q$2:$Q$418,"neutral") | E37: =COUNTIFS(Data!$D$2:$D$418,$A37,Data!$Q$2:$Q$418,"mixed") | F37: =COUNTIFS(Data!$D$2:$D$418,$A37,Data!$Q$2:$Q$418,"negative") | G37: =COUNTIFS(Data!$D$2:$D$418,$A37,Data!$Q$2:$Q$418,"not_mentioned") | H37: =SUM(C21:G21)
A38: VEN | B38: Venezuela | C38: =COUNTIFS(Data!$D$2:$D$418,$A38,Data!$Q$2:$Q$418,"positive") | D38: =COUNTIFS(Data!$D$2:$D$418,$A38,Data!$Q$2:$Q$418,"neutral") | E38: =COUNTIFS(Data!$D$2:$D$418,$A38,Data!$Q$2:$Q$418,"mixed") | F38: =COUNTIFS(Data!$D$2:$D$418,$A38,Data!$Q$2:$Q$418,"negative") | G38: =COUNTIFS(Data!$D$2:$D$418,$A38,Data!$Q$2:$Q$418,"not_mentioned") | H38: =SUM(C21:G21)
A39: PRY | B39: Paraguay | C39: =COUNTIFS(Data!$D$2:$D$418,$A39,Data!$Q$2:$Q$418,"positive") | D39: =COUNTIFS(Data!$D$2:$D$418,$A39,Data!$Q$2:$Q$418,"neutral") | E39: =COUNTIFS(Data!$D$2:$D$418,$A39,Data!$Q$2:$Q$418,"mixed") | F39: =COUNTIFS(Data!$D$2:$D$418,$A39,Data!$Q$2:$Q$418,"negative") | G39: =COUNTIFS(Data!$D$2:$D$418,$A39,Data!$Q$2:$Q$418,"not_mentioned") | H39: =SUM(C21:G21)
A40: SUR | B40: Suriname | C40: =COUNTIFS(Data!$D$2:$D$418,$A40,Data!$Q$2:$Q$418,"positive") | D40: =COUNTIFS(Data!$D$2:$D$418,$A40,Data!$Q$2:$Q$418,"neutral") | E40: =COUNTIFS(Data!$D$2:$D$418,$A40,Data!$Q$2:$Q$418,"mixed") | F40: =COUNTIFS(Data!$D$2:$D$418,$A40,Data!$Q$2:$Q$418,"negative") | G40: =COUNTIFS(Data!$D$2:$D$418,$A40,Data!$Q$2:$Q$418,"not_mentioned") | H40: =SUM(C21:G21)
B41: Total | C41: =SUM(C27:C40) | D41: =SUM(D27:D40) | E41: =SUM(E27:E40) | F41: =SUM(F27:F40) | G41: =SUM(G27:G40) | H41: =SUM(H27:H40)
A43: Stance toward the US by country
A44: Code | B44: Country | C44: positive | D44: neutral | E44: mixed | F44: negative | G44: not mentioned | H44: Total
A45: CHL | B45: Chile | C45: =COUNTIFS(Data!$D$2:$D$418,$A45,Data!$R$2:$R$418,"positive") | D45: =COUNTIFS(Data!$D$2:$D$418,$A45,Data!$R$2:$R$418,"neutral") | E45: =COUNTIFS(Data!$D$2:$D$418,$A45,Data!$R$2:$R$418,"mixed") | F45: =COUNTIFS(Data!$D$2:$D$418,$A45,Data!$R$2:$R$418,"negative") | G45: =COUNTIFS(Data!$D$2:$D$418,$A45,Data!$R$2:$R$418,"not_mentioned") | H45: =SUM(C35:G35)
A46: PER | B46: Peru | C46: =COUNTIFS(Data!$D$2:$D$418,$A46,Data!$R$2:$R$418,"positive") | D46: =COUNTIFS(Data!$D$2:$D$418,$A46,Data!$R$2:$R$418,"neutral") | E46: =COUNTIFS(Data!$D$2:$D$418,$A46,Data!$R$2:$R$418,"mixed") | F46: =COUNTIFS(Data!$D$2:$D$418,$A46,Data!$R$2:$R$418,"negative") | G46: =COUNTIFS(Data!$D$2:$D$418,$A46,Data!$R$2:$R$418,"not_mentioned") | H46: =SUM(C35:G35)
A47: BRA | B47: Brazil | C47: =COUNTIFS(Data!$D$2:$D$418,$A47,Data!$R$2:$R$418,"positive") | D47: =COUNTIFS(Data!$D$2:$D$418,$A47,Data!$R$2:$R$418,"neutral") | E47: =COUNTIFS(Data!$D$2:$D$418,$A47,Data!$R$2:$R$418,"mixed") | F47: =COUNTIFS(Data!$D$2:$D$418,$A47,Data!$R$2:$R$418,"negative") | G47: =COUNTIFS(Data!$D$2:$D$418,$A47,Data!$R$2:$R$418,"not_mentioned") | H47: =SUM(C35:G35)
A48: ARG | B48: Argentina | C48: =COUNTIFS(Data!$D$2:$D$418,$A48,Data!$R$2:$R$418,"positive") | D48: =COUNTIFS(Data!$D$2:$D$418,$A48,Data!$R$2:$R$418,"neutral") | E48: =COUNTIFS(Data!$D$2:$D$418,$A48,Data!$R$2:$R$418,"mixed") | F48: =COUNTIFS(Data!$D$2:$D$418,$A48,Data!$R$2:$R$418,"negative") | G48: =COUNTIFS(Data!$D$2:$D$418,$A48,Data!$R$2:$R$418,"not_mentioned") | H48: =SUM(C35:G35)
A49: BOL | B49: Bolivia | C49: =COUNTIFS(Data!$D$2:$D$418,$A49,Data!$R$2:$R$418,"positive") | D49: =COUNTIFS(Data!$D$2:$D$418,$A49,Data!$R$2:$R$418,"neutral") | E49: =COUNTIFS(Data!$D$2:$D$418,$A49,Data!$R$2:$R$418,"mixed") | F49: =COUNTIFS(Data!$D$2:$D$418,$A49,Data!$R$2:$R$418,"negative") | G49: =COUNTIFS(Data!$D$2:$D$418,$A49,Data!$R$2:$R$418,"not_mentioned") | H49: =SUM(C35:G35)
A50: MEX | B50: Mexico | C50: =COUNTIFS(Data!$D$2:$D$418,$A50,Data!$R$2:$R$418,"positive") | D50: =COUNTIFS(Data!$D$2:$D$418,$A50,Data!$R$2:$R$418,"neutral") | E50: =COUNTIFS(Data!$D$2:$D$418,$A50,Data!$R$2:$R$418,"mixed") | F50: =COUNTIFS(Data!$D$2:$D$418,$A50,Data!$R$2:$R$418,"negative") | G50: =COUNTIFS(Data!$D$2:$D$418,$A50,Data!$R$2:$R$418,"not_mentioned") | H50: =SUM(C35:G35)
A51: REG | B51: Regional | C51: =COUNTIFS(Data!$D$2:$D$418,$A51,Data!$R$2:$R$418,"positive") | D51: =COUNTIFS(Data!$D$2:$D$418,$A51,Data!$R$2:$R$418,"neutral") | E51: =COUNTIFS(Data!$D$2:$D$418,$A51,Data!$R$2:$R$418,"mixed") | F51: =COUNTIFS(Data!$D$2:$D$418,$A51,Data!$R$2:$R$418,"negative") | G51: =COUNTIFS(Data!$D$2:$D$418,$A51,Data!$R$2:$R$418,"not_mentioned") | H51: =SUM(C35:G35)
A52: ECU | B52: Ecuador | C52: =COUNTIFS(Data!$D$2:$D$418,$A52,Data!$R$2:$R$418,"positive") | D52: =COUNTIFS(Data!$D$2:$D$418,$A52,Data!$R$2:$R$418,"neutral") | E52: =COUNTIFS(Data!$D$2:$D$418,$A52,Data!$R$2:$R$418,"mixed") | F52: =COUNTIFS(Data!$D$2:$D$418,$A52,Data!$R$2:$R$418,"negative") | G52: =COUNTIFS(Data!$D$2:$D$418,$A52,Data!$R$2:$R$418,"not_mentioned") | H52: =SUM(C35:G35)
A53: PAN | B53: Panama | C53: =COUNTIFS(Data!$D$2:$D$418,$A53,Data!$R$2:$R$418,"positive") | D53: =COUNTIFS(Data!$D$2:$D$418,$A53,Data!$R$2:$R$418,"neutral") | E53: =COUNTIFS(Data!$D$2:$D$418,$A53,Data!$R$2:$R$418,"mixed") | F53: =COUNTIFS(Data!$D$2:$D$418,$A53,Data!$R$2:$R$418,"negative") | G53: =COUNTIFS(Data!$D$2:$D$418,$A53,Data!$R$2:$R$418,"not_mentioned") | H53: =SUM(C35:G35)
A54: COL | B54: Colombia | C54: =COUNTIFS(Data!$D$2:$D$418,$A54,Data!$R$2:$R$418,"positive") | D54: =COUNTIFS(Data!$D$2:$D$418,$A54,Data!$R$2:$R$418,"neutral") | E54: =COUNTIFS(Data!$D$2:$D$418,$A54,Data!$R$2:$R$418,"mixed") | F54: =COUNTIFS(Data!$D$2:$D$418,$A54,Data!$R$2:$R$418,"negative") | G54: =COUNTIFS(Data!$D$2:$D$418,$A54,Data!$R$2:$R$418,"not_mentioned") | H54: =SUM(C35:G35)
A55: GUY | B55: Guyana | C55: =COUNTIFS(Data!$D$2:$D$418,$A55,Data!$R$2:$R$418,"positive") | D55: =COUNTIFS(Data!$D$2:$D$418,$A55,Data!$R$2:$R$418,"neutral") | E55: =COUNTIFS(Data!$D$2:$D$418,$A55,Data!$R$2:$R$418,"mixed") | F55: =COUNTIFS(Data!$D$2:$D$418,$A55,Data!$R$2:$R$418,"negative") | G55: =COUNTIFS(Data!$D$2:$D$418,$A55,Data!$R$2:$R$418,"not_mentioned") | H55: =SUM(C35:G35)
A56: VEN | B56: Venezuela | C56: =COUNTIFS(Data!$D$2:$D$418,$A56,Data!$R$2:$R$418,"positive") | D56: =COUNTIFS(Data!$D$2:$D$418,$A56,Data!$R$2:$R$418,"neutral") | E56: =COUNTIFS(Data!$D$2:$D$418,$A56,Data!$R$2:$R$418,"mixed") | F56: =COUNTIFS(Data!$D$2:$D$418,$A56,Data!$R$2:$R$418,"negative") | G56: =COUNTIFS(Data!$D$2:$D$418,$A56,Data!$R$2:$R$418,"not_mentioned") | H56: =SUM(C35:G35)
A57: PRY | B57: Paraguay | C57: =COUNTIFS(Data!$D$2:$D$418,$A57,Data!$R$2:$R$418,"positive") | D57: =COUNTIFS(Data!$D$2:$D$418,$A57,Data!$R$2:$R$418,"neutral") | E57: =COUNTIFS(Data!$D$2:$D$418,$A57,Data!$R$2:$R$418,"mixed") | F57: =COUNTIFS(Data!$D$2:$D$418,$A57,Data!$R$2:$R$418,"negative") | G57: =COUNTIFS(Data!$D$2:$D$418,$A57,Data!$R$2:$R$418,"not_mentioned") | H57: =SUM(C35:G35)
A58: SUR | B58: Suriname | C58: =COUNTIFS(Data!$D$2:$D$418,$A58,Data!$R$2:$R$418,"positive") | D58: =COUNTIFS(Data!$D$2:$D$418,$A58,Data!$R$2:$R$418,"neutral") | E58: =COUNTIFS(Data!$D$2:$D$418,$A58,Data!$R$2:$R$418,"mixed") | F58: =COUNTIFS(Data!$D$2:$D$418,$A58,Data!$R$2:$R$418,"negative") | G58: =COUNTIFS(Data!$D$2:$D$418,$A58,Data!$R$2:$R$418,"not_mentioned") | H58: =SUM(C35:G35)
B59: Total | C59: =SUM(C45:C58) | D59: =SUM(D45:D58) | E59: =SUM(E45:E58) | F59: =SUM(F45:F58) | G59: =SUM(G45:G58) | H59: =SUM(H45:H58)
A61: Statements naming each mineral (a statement can name several)
A62: Tag | B62: Mineral | C62: Statements
A63: lithium | B63: lithium | C63: =SUMPRODUCT(--ISNUMBER(SEARCH(";"&$A63&";",";"&Data!$M$2:$M$418&";")))
A64: copper | B64: copper | C64: =SUMPRODUCT(--ISNUMBER(SEARCH(";"&$A64&";",";"&Data!$M$2:$M$418&";")))
A65: critical_minerals_general | B65: critical minerals general | C65: =SUMPRODUCT(--ISNUMBER(SEARCH(";"&$A65&";",";"&Data!$M$2:$M$418&";")))
A66: mining_general | B66: mining general | C66: =SUMPRODUCT(--ISNUMBER(SEARCH(";"&$A66&";",";"&Data!$M$2:$M$418&";")))
A67: rare_earths | B67: rare earths | C67: =SUMPRODUCT(--ISNUMBER(SEARCH(";"&$A67&";",";"&Data!$M$2:$M$418&";")))
A68: nickel | B68: nickel | C68: =SUMPRODUCT(--ISNUMBER(SEARCH(";"&$A68&";",";"&Data!$M$2:$M$418&";")))
A69: silver | B69: silver | C69: =SUMPRODUCT(--ISNUMBER(SEARCH(";"&$A69&";",";"&Data!$M$2:$M$418&";")))
A70: cobalt | B70: cobalt | C70: =SUMPRODUCT(--ISNUMBER(SEARCH(";"&$A70&";",";"&Data!$M$2:$M$418&";")))
A71: niobium | B71: niobium | C71: =SUMPRODUCT(--ISNUMBER(SEARCH(";"&$A71&";",";"&Data!$M$2:$M$418&";")))
A72: zinc | B72: zinc | C72: =SUMPRODUCT(--ISNUMBER(SEARCH(";"&$A72&";",";"&Data!$M$2:$M$418&";")))
A73: iron_ore | B73: iron ore | C73: =SUMPRODUCT(--ISNUMBER(SEARCH(";"&$A73&";",";"&Data!$M$2:$M$418&";")))
A74: tin | B74: tin | C74: =SUMPRODUCT(--ISNUMBER(SEARCH(";"&$A74&";",";"&Data!$M$2:$M$418&";")))
... A81: uranium | B81: uranium | C81: =SUMPRODUCT(--ISNUMBER(SEARCH(";"&$A81&";",";"&Data!$M$2:$M$418&";")))

Sheet Data
A1: id | B1: date | C1: year | D1: country | E1: speaker_name | F1: speaker_role | G1: speaker_type | H1: speaker_bloc | I1: speaker_country | J1: party_or_affiliation | K1: channel | L1: event_context | M1: minerals | N1: hs6_links | O1: themes | P1: counterparts_mentioned | Q1: stance_china | R1: stance_us | S1: related_entities | T1: summary_en | U1: quote_original | V1: quote_en | W1: language | X1: source_name | Y1: source_url | Z1: source_type | AA1: verification | AB1: notes | AC1: research_batch
A2: PS-0001 | B2: 2019-03 | C2: 2019 | D2: PER | E2: Paola Bustamante | F2: Minister of Development and Social Inclusion of Peru | G2: minister_cabinet | H2: LatAm executive | I2: PER | K2: press_conference | L2: Fuerabamba blockade of Las Bambas mining road; failed ministerial negotiation visit | M2: copper | N2: 260300;740200;740311 | O2: labor_social_conflict;indigenous_community_rights | P2: CHN | Q2: not_mentioned | R2: not_mentioned | S2: Las Bambas; MMG; China Minmetals | T2: After protesters threw rocks at a government helicopter carrying a three-minister delegation to negotiate an end to a 51-day Fuerabamba community blockade of the Las Bambas copper mine road, Bustamante said the government would maintain its willingness to dialogue. | U2: We went with a disposition for dialogue and that's why we're going to continue with that disposition and see how things shape up tomorrow. | V2: We went with a disposition for dialogue and that's why we're going to continue with that disposition and see how things shape up tomorrow. | W2: en | X2: Reuters via The Borneo Post (PressReader) | Y2: https://www.pressreader.com/malaysia/the-borneo-post-sabah/20190329/282248076914526 | Z2: news_media | AA2: secondary_reported | AB2: Exact day not given (Wednesday before 29 Mar 2019, likely 27 Mar); quote is English wire translation of Spanish original | AC2: PER
A3: PS-0002 | B3: 2019-03-05 | C3: 2019 | D3: BRA | E3: Bento Albuquerque | F3: Minister of Mines and Energy of Brazil | G3: minister_cabinet | H3: LatAm executive | I3: BRA | K3: speech | L3: Meeting with mining investors in Canada (PDAC, Toronto) | M3: mining_general | O3: indigenous_community_rights;foreign_investment;sovereignty | P3: CAN | Q3: not_mentioned | R3: not_mentioned | S3: INB | T3: Albuquerque told investors in Canada that the government was studying authorising mining in indigenous lands and border areas, arguing restrictions fostered illegal activity, and favoured opening uranium research to private investment. | U3: As restrições aplicadas a essas áreas não têm favorecido seu desenvolvimento. | V3: The restrictions applied to these areas have not favoured their development. | W3: pt | X3: Congresso em Foco | Y3: https://congressoemfoco.com.br/economia/governo-planeja-liberar-mineracao-em-terras-indigenas-diz-ministro | Z3: news_media | AA3: secondary_reported | AB3: Event name PDAC inferred from date/location | AC3: BRA
A4: PS-0003 | B4: 2019-07-16 | C4: 2019 | D4: PER | E4: Elmer Cáceres Llica | F4: Regional Governor of Arequipa | G4: subnational_gov | H4: LatAm executive | I4: PER | K4: press_conference | L4: Tía María license protests, Tambo Valley | M4: copper | N4: 260300;740200;740311 | O4: environment_water;labor_social_conflict | P4: none | Q4: not_mentioned | R4: not_mentioned | S4: Tía María; Southern Copper | T4: The Arequipa governor, backed by over 50 civil organizations, gave the central government 72 hours to declare the Tía María construction license null, while pursuing legal remedies and peaceful protests. | U4: Le daremos al Gobierno central 72 horas para que resuelva el tema de la licencia de construcción, o sea que declare su nulidad de oficio | V4: We will give the central government 72 hours to resolve the construction license issue, that is, to declare it null ex officio | W4: es | X4: La República | Y4: https://larepublica.pe/sociedad/2019/07/16/gobernador-de-arequipa-da-72-horas-a-vizcarra-para-cancelar-licencia-de-tia-maria | Z4: news_media | AA4: secondary_reported | AC4: PER
A5: PS-0004 | B5: 2019-07-16 | C5: 2019 | D5: PER | E5: Martín Vizcarra | F5: President of Peru | G5: head_of_state | H5: LatAm executive | I5: PER | K5: press_conference | L5: Protests over Tía María construction license granted to Southern Peru (9 Jul 2019) | M5: copper | N5: 260300;740200;740311 | O5: labor_social_conflict;environment_water;foreign_investment | P5: none | Q5: not_mentioned | R5: not_mentioned | S5: Tía María; Southern Peru Copper; Grupo México | T5: Vizcarra said the construction license granted to Southern Peru for Tía María could not be annulled because the company had completed the administrative process, but called for dialogue and said construction would need proper conditions. | U5: No se puede anular, tenemos que conversar y fruto del diálogo, encontremos las soluciones y consensos | V5: It cannot be annulled; we have to talk, and through dialogue find solutions and consensus | W5: es | X5: El Búho | Y5: https://elbuho.pe/archivo/2019/07/16/martin-vizcarra-sobre-tia-maria-no-se-puede-anular-licencia-tenemos-que-conversar/index.html | Z5: news_media | AA5: secondary_reported | AC5: PER
A6: PS-0005 | B6: 2019-09-06 | C6: 2019 | D6: CHL | E6: Pablo Terrazas | F6: Executive Vice President of CORFO | G6: other_executive | H6: LatAm executive | I6: CHL | K6: legislative_debate | L6: Chamber of Deputies Economy Commission session on lithium and Tianqi-SQM | M6: lithium | N6: 253090;282520;283691 | O6: technology_transfer;value_added_industrialization;foreign_investment | P6: CHN | Q6: neutral | R6: not_mentioned | S6: CORFO; SQM; Tianqi; Instituto Chileno de Tecnologías Limpias | T6: CORFO head briefed deputies on lithium contracts, Tianqi's stake in SQM and the planned Chilean Institute of Clean Technologies in Antofagasta, funded with SQM contributions, for lithium R&D. | U6: De aquí a fin de año, ya vamos a tener a algún consorcio liderando la creación de este instituto | V6: By the end of the year we will have a consortium leading the creation of this institute | W6: es | X6: Cámara de Diputadas y Diputados | Y6: https://www.camara.cl/cms/2019/09/06/vicepresidente-de-corfo-informo-sobre-situacion-y-negociacion-del-litio/ | Z6: legislative_record | AA6: primary_verified | AB6: Quote truncated to stay within 30 words; institute to have >US$200m for R&D | AC6: CHL
A7: PS-0006 | B7: 2019-09-06 | C7: 2019 | D7: CHL | E7: Renato Garín | F7: Deputy, Chair-level member of Economy Commission | G7: legislator | H7: LatAm legislature | I7: CHL | J7: Independent | K7: legislative_debate | L7: Chamber of Deputies Economy Commission session on lithium and Tianqi-SQM | M7: lithium | N7: 253090;282520;283691 | O7: sovereignty;geopolitics_security;technology_transfer | P7: CHN | Q7: negative | R7: not_mentioned | S7: SQM; Tianqi | T7: Deputy Garín voiced concern about Chinese state influence over SQM through Tianqi and said Chile must retain sovereignty over its lithium resources and technology development. | W7: es | X7: Cámara de Diputadas y Diputados | Y7: https://www.camara.cl/cms/2019/09/06/vicepresidente-de-corfo-informo-sobre-situacion-y-negociacion-del-litio/ | Z7: legislative_record | AA7: primary_verified | AB7: Paraphrase from Chamber press note; no verbatim quote | AC7: CHL
A8: PS-0007 | B8: 2019-10-13 | C8: 2019 | D8: PER | E8: Raúl Molina Martínez | F8: Deputy Minister of Territorial Governance (PCM) | G8: other_executive | H8: LatAm executive | I8: PER | K8: official_statement | L8: Chumbivilcas blockade of southern mining corridor used by Las Bambas | M8: copper | N8: 260300;740200;740311 | O8: labor_social_conflict;infrastructure_ports | P8: none | Q8: not_mentioned | R8: not_mentioned | S8: Las Bambas; MMG | T8: The PCM vice minister urged Chumbivilcas communities to lift their blockade of the road used by Las Bambas to haul copper concentrate, stressing it is a public road and that demands must be legally viable. | U8: It is not possible to prevent the free movement of vehicles through the runway, including the miner's trucks, because it is a public road. | V8: It is not possible to prevent the free movement of vehicles through the runway, including the miner's trucks, because it is a public road. | W8: en | X8: Reuters via MINING.COM | Y8: https://www.mining.com/?p=1004331 | Z8: news_media | AA8: secondary_reported | AB8: Quote is English wire translation; date is article date | AC8: PER
A9: PS-0008 | B9: 2019-10-28 | C9: 2019 | D9: PER | E9: Juan Carlos Liu | F9: Minister of Energy and Mines of Peru | G9: minister_cabinet | H9: LatAm executive | I9: PER | K9: press_conference | L9: Mining Council review of Tía María license | M9: copper | N9: 260300;740200;740311 | O9: corruption_governance;labor_social_conflict | P9: none | Q9: not_mentioned | R9: not_mentioned | S9: Tía María; Southern Copper; Consejo de Minería | T9: Liu said the Tía María license case was for the autonomous Mining Council to decide and that the government, following presidential guidelines, would abide by its ruling while promoting dialogue in the Tambo Valley. | U9: El caso de Tía María es un caso que está para la decisión de la Comisión de Minería. | V9: The Tía María case is one awaiting the decision of the Mining Commission. | W9: es | X9: ProActivo | Y9: https://proactivo.com.pe/juan-carlos-liu-gobierno-respetara-decision-del-consejo-de-mineria-sobre-tia-maria/ | Z9: news_media | AA9: secondary_reported | AC9: PER
A10: PS-0009 | B10: 2020-04 | C10: 2020 | D10: BOL | E10: José Luis Parada | F10: Minister of Economy and Public Finance (Áñez interim government) | G10: minister_cabinet | H10: LatAm executive | I10: BOL | J10: Áñez interim government | K10: interview | L10: Interim government economic policy, COVID-19 period | M10: lithium | N10: 253090;282520;283691 | O10: foreign_investment | P10: none | Q10: not_mentioned | R10: not_mentioned | S10: Salar de Uyuni | T10: Interim-government economy minister Parada said two or three companies from different countries would invest in lithium from the Uyuni salt flat and that policies to attract foreign partners were being prepared. | W10: es | X10: Tiempo Argentino | Y10: https://www.tiempoar.com.ar/ta_article/la-guerra-del-litio-entre-la-privatizacion-y-la-quiebra/ | Z10: news_media | AA10: secondary_reported | AB10: Paraphrase from secondary source (left-leaning outlet); exact day in late April 2020 unknown; no verbatim quote seen. | AC10: BOL
A11: PS-0010 | B11: 2020-07-25 | C11: 2020 | D11: BOL | E11: Evo Morales | F11: Former President of Bolivia (in exile) | G11: other | H11: Other (business, civil society, third countries) | I11: BOL | J11: Movimiento al Socialismo (MAS) | K11: social_media_post | L11: Twitter exchange with Elon Musk | M11: lithium | N11: 253090;282520;283691 | O11: sovereignty;geopolitics_security | P11: USA | Q11: not_mentioned | R11: negative | S11: Tesla | T11: Responding to Elon Musk's 'We will coup whoever we want' tweet, Morales said it was further proof that the 2019 coup was over Bolivian lithium and vowed to defend Bolivia's resources. | U11: Otra prueba más de que el golpe fue por el litio boliviano; y dos masacres como saldo. ¡Defenderemos siempre nuestros recursos! | V11: Yet more proof that the coup was over Bolivian lithium; with two massacres as the toll. We will always defend our resources! | W11: es | X11: La República (Peru) | Y11: https://larepublica.pe/mundo/2020/07/25/elon-musk-y-evo-morales-enfrentados-en-twitter-daremos-un-golpe-a-quien-queramos | Z11: news_media | AA11: secondary_reported | AB11: Tweet quoted by media; stance_us coded for US corporate actor (Musk/Tesla). | AC11: BOL
A12: PS-0011 | B12: 2020-09-28 | C12: 2020 | D12: BRA | E12: Jair Bolsonaro | F12: President of Brazil | G12: head_of_state | H12: LatAm executive | I12: BRA | J12: no party (ex-PSL) | K12: speech | L12: Launch of the Mining and Development Program (PMD), Palácio do Planalto | M12: niobium;mining_general | N12: 261590;720293 | O12: value_added_industrialization;technology_transfer;indigenous_community_rights | P12: none | Q12: not_mentioned | R12: not_mentioned | T12: At the launch of the government's Mining and Development Program, Bolsonaro received a niobium coin from Minister Bento Albuquerque and praised niobium combined with graphene as able to revolutionise the car industry; the program included advancing a bill on mining in indigenous lands. | U12: juntamente com o grafeno é capaz de produzir maravilhas | V12: together with graphene it is capable of producing wonders | W12: pt | X12: Poder360 | Y12: https://www.poder360.com.br/governo/em-lancamento-de-programa-de-mineracao-do-governo-bolsonaro-exalta-niobio/ | Z12: news_media | AA12: secondary_reported | AB12: Bolsonaro left PSL in Nov 2019 | AC12: BRA
A13: PS-0012 | B13: 2020-11-10 | C13: 2020 | D13: BOL | E13: Evo Morales | F13: Former President of Bolivia; MAS leader | G13: other | H13: Other (business, civil society, third countries) | I13: BOL | J13: Movimiento al Socialismo (MAS) | K13: press_conference | L13: Return to Bolivia from exile, Uyuni/Potosí tour | M13: lithium | N13: 253090;282520;283691 | O13: value_added_industrialization;sovereignty;geopolitics_security | P13: none | Q13: not_mentioned | R13: not_mentioned | T13: On his return to Bolivia, Morales said lithium reserves were the motive for the 2019 'coup', that industrialized countries want Latin America only for raw materials, and that his lithium industrialization plan would resume under President Arce. | U13: allí donde los pueblos son dueños de los recursos naturales, preparan bases e intervenciones militares e incluso golpes de Estado | V13: wherever peoples own their natural resources, they prepare bases and military interventions and even coups d'état | W13: es | X13: Público | Y13: https://www.publico.es/internacional/evo-morales-ve-litio-causa-golpe-bolivia.html | Z13: news_media | AA13: secondary_reported | AB13: Also reported by Gestión (https://gestion.pe/mundo/internacional/evo-morales-anuncia-que-se-reactivara-su-plan-de-litio-apenas-llegado-a-bolivia-noticia/): 'El plan que teníamos lo vamos a retomar ahora con el Lucho presidente'. | AC13: BOL
A14: PS-0013 | B14: 2020-12-04 | C14: 2020 | D14: PER | E14: Francisco Sagasti | F14: President of Peru (transitional) | G14: head_of_state | H14: LatAm executive | I14: PER | J14: Partido Morado | K14: press_conference | L14: Press conference with foreign media accredited in Peru | M14: mining_general | O14: foreign_investment | P14: none | Q14: not_mentioned | R14: not_mentioned | T14: Sagasti said his transitional government had no mandate to change economic direction and would ensure that foreign investments already under way, including in mining, continue, while arguing Peru should diversify beyond being a mining country. | U14: hará lo que hay que hacer para que continúen las inversiones extranjeras ya en proceso, ya sea en la minería o en otros sectores | V14: will do what must be done so that foreign investments already under way continue, whether in mining or other sectors | W14: es | X14: ProActivo | Y14: https://proactivo.com.pe/presidente-sagasti-reitera-la-necesidad-de-continuar-con-las-inversiones-mineras/ | Z14: news_media | AA14: secondary_reported | AB14: Quote is in reported (third-person) form as published | AC14: PER
A15: PS-0014 | B15: 2021-04-16 | C15: 2021 | D15: PER | E15: Ana María Córdova | F15: Legal representative of Perú Libre (Pedro Castillo campaign) | G15: political_party_candidate | H15: LatAm party/candidate | I15: PER | J15: Perú Libre | K15: campaign_statement | L15: 2021 presidential runoff campaign | M15: mining_general;copper | N15: 260300;740200;740311 | O15: royalties_taxation;state_control_nationalization;foreign_investment | P15: none | Q15: not_mentioned | R15: not_mentioned | T15: Speaking for candidate Pedro Castillo, Córdova said the party would not expropriate or nationalize mines but would renegotiate contract conditions so the state and local populations get a bigger share of profits. | U15: Not to expropriate them, not to nationalize or anything, but so that the conditions in some way also favor populations where these industries or mining operations are involved | V15: Not to expropriate them, not to nationalize or anything, but so that the conditions in some way also favor populations where these industries or mining operations are involved | W15: en | X15: Bloomberg via Mining Weekly | Y15: https://www.miningweekly.com/print-version/peru-candidate-seeks-bigger-cut-from-mining-not-state-control-2021-04-16 | Z15: news_media | AA15: secondary_reported | AB15: English translation published by Bloomberg; original Spanish wording not seen | AC15: PER
A16: PS-0015 | B16: 2021-06-15 | C16: 2021 | D16: ARG | E16: Martín de los Ríos | F16: Minister of Production of Salta (for Gov. Gustavo Sáenz) | G16: subnational_gov | H16: LatAm executive | I16: ARG | K16: interview | L16: Reaction to national lithium nationalization proposals | M16: lithium | N16: 253090;282520;283691 | O16: state_control_nationalization;sovereignty;foreign_investment | P16: none | Q16: not_mentioned | R16: not_mentioned | T16: Salta's production minister said the three lithium provinces formed the Mesa del Litio on the basis that lithium is a provincial resource and that nationalization initiatives create instability for investors. | W16: es | X16: Ámbito | Y16: https://www.ambito.com/ambito-nacional/litio/norte-rechaza-proyecto-nacionalizar-el-n5202043 | Z16: news_media | AA16: secondary_reported | AB16: Only translated rendering seen; quote left blank. | AC16: ARG
A17: PS-0016 | B17: 2021-06-15 | C17: 2021 | D17: ARG | E17: Miguel Soler | F17: Secretary of Mining of Jujuy (Morales government) | G17: subnational_gov | H17: LatAm executive | I17: ARG | J17: UCR | K17: interview | L17: Reaction to national lithium nationalization proposals | M17: lithium | N17: 253090;282520;283691 | O17: state_control_nationalization;sovereignty | P17: none | Q17: not_mentioned | R17: not_mentioned | T17: Jujuy's mining secretary said proposals to nationalize lithium are unconstitutional because they interfere with provincial ownership of resources, and that Jujuy should make its own decisions. | W17: es | X17: Ámbito | Y17: https://www.ambito.com/ambito-nacional/litio/norte-rechaza-proyecto-nacionalizar-el-n5202043 | Z17: news_media | AA17: secondary_reported | AB17: Only translated rendering seen; quote left blank. | AC17: ARG
A18: PS-0017 | B18: 2021-09-23 | C18: 2021 | D18: PER | E18: Pedro Francke | F18: Minister of Economy and Finance of Peru | G18: minister_cabinet | H18: LatAm executive | I18: PER | K18: interview | L18: Proposed tax reform targeting mining windfall profits | M18: copper;mining_general | N18: 260300;740200;740311 | O18: royalties_taxation | P18: none | Q18: not_mentioned | R18: not_mentioned | T18: Francke argued that with copper above US$4/lb and costs around US$1/lb, the state should capture extraordinary mining profits and redistribute mining wealth through tax reform. | U18: Hay que redistribuir la riqueza, en particular la riqueza minera | V18: We must redistribute wealth, particularly mining wealth | W18: es | X18: La República | Y18: https://larepublica.pe/economia/2021/09/23/hay-resistencia-en-el-sector-minero-por-reforma-tributaria-ministerio-de-economia | Z18: news_media | AA18: secondary_reported | AC18: PER
A19: PS-0018 | B19: 2021-10-01 | C19: 2021 | D19: PER | E19: Iván Merino | F19: Minister of Energy and Mines of Peru | G19: minister_cabinet | H19: LatAm executive | I19: PER | K19: interview | L19: Three-week blockade of Las Bambas road in Chumbivilcas | M19: copper | N19: 260300;740200;740311 | O19: labor_social_conflict;infrastructure_ports | P19: none | Q19: not_mentioned | R19: not_mentioned | S19: Las Bambas; MMG | T19: Merino partly blamed MMG's short-term decision to haul Las Bambas copper concentrate on a dirt road for unrest with communities, and proposed a train line as a longer-term solution. | U19: They made short-term decisions and that has a cost | V19: They made short-term decisions and that has a cost | W19: en | X19: Reuters via Mining Weekly | Y19: https://www.miningweekly.com/article/peru-minister-partly-blames-mmg-for-las-bambas-unrest-sees-solution-in-train-line-2021-10-01 | Z19: news_media | AA19: secondary_reported | AB19: English wire translation | AC19: PER
A20: PS-0019 | B20: 2021-11 | C20: 2021 | D20: PER | E20: Mirtha Vásquez | F20: President of the Council of Ministers of Peru | G20: minister_cabinet | H20: LatAm executive | I20: PER | K20: official_statement | L20: Agreement with Ayacucho communities on mine closures | M20: mining_general;silver | N20: 261610;710691 | O20: environment_water;indigenous_community_rights;labor_social_conflict | P20: none | Q20: not_mentioned | R20: not_mentioned | S20: Hochschild; Ares; Apumayo; Sami | T20: Vásquez signed an agreement with Ayacucho communities confirming the closure of four mining operations and said mining expansions in the province would not be approved, prompting business backlash; a vice minister later said expansion plans could still be submitted. | W20: es | X20: Bloomberg Línea | Y20: https://www.bloomberglinea.com/2021/11/22/castillo-no-ha-existido-ni-existiran-decisiones-unilaterales-ni-arbitrarias-en-peru/ | Z20: news_media | AA20: secondary_reported | AB20: Agreement dated c. 19-20 Nov 2021; silver tag because affected mines (Hochschild) are gold-silver operations | AC20: PER
A21: PS-0020 | B21: 2021-11-20 | C21: 2021 | D21: ARG | E21: Gustavo Sáenz; Gerardo Morales; Raúl Jalil | F21: Governors of Salta, Jujuy and Catamarca | G21: subnational_gov | H21: LatAm executive | I21: ARG | K21: joint_declaration_or_mou | L21: Creation of the Región Minera del Litio | M21: lithium | N21: 253090;282520;283691 | O21: value_added_industrialization;infrastructure_ports;environment_water | P21: none | Q21: not_mentioned | R21: not_mentioned | S21: YPF; Región Minera del Litio | T21: The three governors signed a treaty forming the Lithium Mining Region to coordinate infrastructure, production, technical and environmental matters across lithium research, extraction, industrialization and trade. | U21: determinar las bases para generar condiciones de reciprocidad y coordinar esfuerzos en materia de infraestructura, producción, cuestiones técnicas ambientales | V21: lay the foundations to create reciprocal conditions and coordinate efforts on infrastructure, production, technical and environmental issues | W21: es | X21: Más Energía (LM Neuquén) | Y21: https://mase.lmneuquen.com/politica/se-conformo-la-region-minera-del-litio-n862429 | Z21: news_media | AA21: secondary_reported | AB21: Quote by Sáenz; Mesa del Litio precedent. | AC21: ARG
A22: PS-0021 | B22: 2021-11-22 | C22: 2021 | D22: PER | E22: Pedro Castillo | F22: President of Peru | G22: head_of_state | H22: LatAm executive | I22: PER | J22: Perú Libre | K22: official_statement | L22: Controversy over PM Vásquez's announced closure of four mines in Ayacucho | M22: mining_general | O22: foreign_investment;environment_water;indigenous_community_rights | P22: none | Q22: not_mentioned | R22: not_mentioned | S22: Hochschild; Ares; Apumayo | T22: Amid market turmoil after the premier agreed with Ayacucho communities to close four mining operations, Castillo said there would be no unilateral or arbitrary decisions and reaffirmed his commitment to guarantee private investment including mining. | U22: No ha existido ni existirán decisiones unilaterales ni arbitrarias | V22: There have not been, nor will there be, unilateral or arbitrary decisions | W22: es | X22: Bloomberg Línea | Y22: https://www.bloomberglinea.com/2021/11/22/castillo-no-ha-existido-ni-existiran-decisiones-unilaterales-ni-arbitrarias-en-peru/ | Z22: news_media | AA22: secondary_reported | AC22: PER
A23: PS-0022 | B23: 2021-12-16 | C23: 2021 | D23: PER | E23: Mirtha Vásquez | F23: President of the Council of Ministers of Peru | G23: minister_cabinet | H23: LatAm executive | I23: PER | K23: press_conference | L23: Chumbivilcas blockade halting Las Bambas | M23: copper | N23: 260300;740200;740311 | O23: labor_social_conflict;corruption_governance | P23: none | Q23: not_mentioned | R23: not_mentioned | S23: Las Bambas; MMG | T23: With the Las Bambas road blockade past 20 days, Vásquez said the government was evaluating options including eviction of protesters and, as a last resort, a state of emergency in Chumbivilcas. | U23: Hay varias opciones que evaluar. No podemos permitir que se estén vulnerando ciertos derechos | V23: There are several options to evaluate. We cannot allow certain rights to be violated | W23: es | X23: ProActivo | Y23: https://proactivo.com.pe/las-bambas-gobierno-evalua-desalojar-manifestantes-y-en-ultima-instancia-decretar-estado-de-emergencia-en-chumbivilcas/ | Z23: news_media | AA23: secondary_reported | AC23: PER
A24: PS-0023 | B24: 2021-12-21 | C24: 2021 | D24: PER | E24: Baltazar Lantarón | F24: Regional Governor of Apurímac | G24: subnational_gov | H24: LatAm executive | I24: PER | K24: official_statement | L24: Las Bambas shutdown due to corridor blockade | M24: copper | N24: 260300;740200;740311 | O24: royalties_taxation;labor_social_conflict | P24: none | Q24: not_mentioned | R24: not_mentioned | S24: Las Bambas; MMG | T24: Lantarón criticized the Executive's negotiators as pusillanimous over the Las Bambas corridor blockade, warned of lost royalties and mining canon for Apurímac, and requested a 120-day emergency declaration on the southern mining corridor. | U24: la actitud pusilánime de los negociadores del Ejecutivo están generado nefastas consecuencias económicas | V24: the pusillanimous attitude of the Executive's negotiators is generating disastrous economic consequences | W24: es | X24: ProActivo | Y24: https://proactivo.com.pe/las-bambas-gobernador-regional-de-apurimac-califica-como-pusilanime-actitud-del-ejecutivo/ | Z24: news_media | AA24: secondary_reported | AC24: PER
A25: PS-0024 | B25: 2022-01 | C25: 2022 | D25: CHL | E25: Juan Carlos Jobet | F25: Minister of Mining and Energy | G25: minister_cabinet | H25: LatAm executive | I25: CHL | J25: Independent (Piñera government) | K25: interview | L25: Defence of lithium tender against incoming government's request to postpone | M25: lithium | N25: 253090;282520;283691 | O25: foreign_investment;state_control_nationalization | P25: none | Q25: not_mentioned | R25: not_mentioned | T25: Jobet argued Chile had failed to raise lithium output while other countries advanced, and said the tender (about 4% of reserves) did not mortgage the next government's agenda. | U25: hemos sido incapaces de aumentar la producción y, mientras hacemos eso, los otros países avanzan | V25: we have been unable to increase production and, while we do that, other countries advance | W25: es | X25: CNN Chile | Y25: https://www.cnnchile.com/sin-categoria/ministro-jobet-licitacion-litio-no-pone-riesgo-agenda-proximo-gobierno/ | Z25: news_media | AA25: secondary_reported | AB25: Exact day not given; January 2022 | AC25: CHL
A26: PS-0025 | B26: 2022-01-06 | C26: 2022 | D26: CHL | E26: Ricardo Díaz | F26: Governor of Antofagasta Region | G26: subnational_gov | H26: LatAm executive | I26: CHL | J26: Independent | K26: official_statement | L26: Complaint to Comptroller over lithium tender | M26: lithium | N26: 253090;282520;283691 | O26: indigenous_community_rights;sovereignty;corruption_governance | P26: none | Q26: not_mentioned | R26: not_mentioned | S26: Salar de Atacama | T26: Antofagasta governor said his government filed a complaint with the Comptroller over the Piñera administration's lithium tender, arguing regional and indigenous Atacameño voices were not consulted. | U26: No se puede hacer un proceso de consulta, en donde se hipoteca el futuro de nuestra región, sin considerar la voz de los que habitamos este territorio. | V26: You cannot carry out a consultation process that mortgages the future of our region without considering the voice of those of us who live in this territory. | W26: es | X26: T13 | Y26: https://www.t13.cl/noticia/nacional/gobernador-antofagasta-oficia-contraloria-proceso-licitacion-del-litio-06-01-2022 | Z26: news_media | AA26: secondary_reported | AC26: CHL
A27: PS-0026 | B27: 2022-01-07 | C27: 2022 | D27: CHL | E27: Sebastián Piñera | F27: President of Chile | G27: head_of_state | H27: LatAm executive | I27: CHL | J27: Renovación Nacional | K27: press_conference | L27: Visit to O'Higgins Region; defence of lithium tender | M27: lithium | N27: 253090;282520;283691 | O27: foreign_investment;state_control_nationalization;corruption_governance | P27: AUS | Q27: not_mentioned | R27: not_mentioned | T27: Piñera defended the international lithium tender for about 4.4% of known reserves as transparent and Comptroller-approved, noting Chile had lost lithium leadership to Australia and saying a national lithium company, as proposed by Boric, could be done. | U27: El litio es hoy día un mineral esencial para la sociedad que viene | V27: Lithium is today an essential mineral for the society to come | W27: es | X27: El Dínamo | Y27: https://www.eldinamo.cl/politica/2022/01/07/pinera-defiende-licitacion-del-litio-y-asegura-que-es-transparente/ | Z27: news_media | AA27: secondary_reported | AC27: CHL
A28: PS-0027 | B28: 2022-01-10 | C28: 2022 | D28: CHL | E28: Rodrigo Cerda | F28: Minister of Finance | G28: minister_cabinet | H28: LatAm executive | I28: CHL | J28: Independent (Piñera government) | K28: interview | L28: Canal 13 interview on lithium tender | M28: lithium | N28: 253090;282520;283691 | O28: royalties_taxation;state_control_nationalization | P28: none | Q28: not_mentioned | R28: not_mentioned | T28: Finance minister said the lithium tender was not a lock-in ("amarre"), that lithium would remain Chilean and taxed, and that the government was listening to the president-elect's request to postpone it. | U28: El litio va a seguir siendo de los chilenos | V28: Lithium will continue to belong to Chileans | W28: es | X28: CNN Chile | Y28: https://www.cnnchile.com/pais/ministro-cerda-licitacion-litio-seguir-siendo-chilenos-cobrando-impuestos_20220110/ | Z28: news_media | AA28: secondary_reported | AC28: CHL
A29: PS-0028 | B29: 2022-01-12 | C29: 2022 | D29: CHL | E29: Esteban Velásquez | F29: Deputy; President of Chamber Mining Commission | G29: legislator | H29: LatAm legislature | I29: CHL | J29: FRVS | K29: legislative_debate | L29: Chamber Mining Commission session on lithium tender | M29: lithium | N29: 253090;282520;283691 | O29: corruption_governance;state_control_nationalization | P29: none | Q29: not_mentioned | R29: not_mentioned | S29: BYD Chile SpA | T29: Mining Commission chair criticised the Piñera government for ignoring calls to halt the lithium tender; opposition deputies announced judicial and administrative actions to annul it. | U29: El Gobierno del Presidente Piñera no escuchó ningún llamado | V29: President Piñera's government did not listen to any call | W29: es | X29: El Mostrador | Y29: https://www.elmostrador.cl/noticias/pais/2022/01/12/boric-califica-licitacion-del-litio-como-una-mala-noticia-que-recuerda-a-las-leyes-de-amarre-y-oposicion-buscara-anular-proceso-por-via-judicial-administrativa-y-legislativa/ | Z29: news_media | AA29: secondary_reported | AC29: CHL
A30: PS-0029 | B30: 2022-01-12 | C30: 2022 | D30: CHL | E30: Gabriel Boric | F30: President-elect of Chile | G30: political_party_candidate | H30: LatAm party/candidate | I30: CHL | J30: Convergencia Social / Apruebo Dignidad | K30: press_conference | L30: Reaction to award of lithium tender to BYD and Servicios y Operaciones Mineras del Norte | M30: lithium | N30: 253090;282520;283691 | O30: state_control_nationalization;corruption_governance | P30: none | Q30: not_mentioned | R30: not_mentioned | S30: BYD Chile SpA; Servicios y Operaciones Mineras del Norte (SQM-linked) | T30: President-elect Boric called the outgoing government's lithium tender award bad news reminiscent of the "leyes de amarre" and said his team would review its details. | U30: es una mala noticia y me recuerda a esas leyes de amarre | V30: it is bad news and reminds me of those lock-in laws | W30: es | X30: El Mostrador | Y30: https://www.elmostrador.cl/noticias/pais/2022/01/12/boric-califica-licitacion-del-litio-como-una-mala-noticia-que-recuerda-a-las-leyes-de-amarre-y-oposicion-buscara-anular-proceso-por-via-judicial-administrativa-y-legislativa/ | Z30: news_media | AA30: secondary_reported | AB30: speaker_type coded as candidate because president-elect, not yet in office | AC30: CHL
A31: PS-0030 | B31: 2022-02-02 | C31: 2022 | D31: MEX | E31: Andrés Manuel López Obrador | F31: President of Mexico | G31: head_of_state | H31: LatAm executive | I31: MEX | J31: Morena | K31: press_conference | L31: Mañanera; announcement of state lithium company | M31: lithium | N31: 253090;282520;283691 | O31: state_control_nationalization;sovereignty;geopolitics_security;foreign_investment | P31: RUS;CHN;USA | Q31: neutral | R31: neutral | T31: AMLO said existing mining concessions did not cover lithium, which he called a strategic mineral belonging to the nation, and that the state would exploit it; he said Mexico did not want to be a territory of conflict between Russia, China or the US. | U31: el litio lo va a explotar la nación. El litio ya, para que se entienda bien, no es ni siquiera del Gobierno o del Estado, el litio es del pueblo | V31: lithium will be exploited by the nation. Lithium, to be clear, does not even belong to the government or the state, lithium belongs to the people | W31: es | X31: Emol (EFE) | Y31: https://www.emol.com/noticias/Economia/2022/02/02/1045744/amlo-prohibe-extranjeros-explotar-litio.html | Z31: news_media | AA31: secondary_reported | AC31: MEX
A32: PS-0031 | B32: 2022-02-06 | C32: 2022 | D32: ARG | E32: Xi Jinping; Alberto Fernández | F32: President of China; President of Argentina | G32: china_central_gov | H32: China | I32: CHN | J32: CCP | K32: joint_declaration_or_mou | L32: Fernández state visit to Beijing; Argentina joins Belt and Road | M32: mining_general | O32: diplomatic_relations;foreign_investment;infrastructure_ports | P32: ARG | Q32: positive | R32: not_mentioned | T32: Chinese readout of the Xi-Fernández meeting says the sides will deepen cooperation in trade, agriculture, energy, mining, infrastructure, investment and finance, with China helping expand Argentina's exports. | U32: la cooperación en áreas de comercio, agricultura, energía, minería, infraestructura, inversión, financiación y lucha antiepidémica | V32: cooperation in the areas of trade, agriculture, energy, mining, infrastructure, investment, financing and the fight against the epidemic | W32: es | X32: Ministry of Foreign Affairs of the PRC (Spanish) | Y32: https://www.mfa.gov.cn/esp/gjhdq/ldmz/3453/3455/202202/t20220206_10639512.html | Z32: primary_official | AA32: primary_verified | AB32: Mining only listed among sectors. | AC32: ARG
A33: PS-0032 | B33: 2022-03-31 | C33: 2022 | D33: REG | E33: Marco Rubio | F33: U.S. Senator (R-FL), Ranking Member, SFRC Subcommittee on the Western Hemisphere | G33: us_congress | H33: United States | I33: USA | J33: Republican | K33: legislative_debate | L33: SFRC Western Hemisphere subcommittee hearing 'China's Role in Latin America and the Caribbean' | M33: mining_general | O33: geopolitics_security;value_added_industrialization | P33: CHN | Q33: negative | R33: positive | T33: Rubio said the Chinese Communist Party pushes Latin American countries to stay dependent on mining and natural-resource exports rather than helping them develop and industrialize. | U33: the Chinese Communist Party is pushing countries to remain dependent on mining and other—and the export of other natural resources | V33: the Chinese Communist Party is pushing countries to remain dependent on mining and other—and the export of other natural resources | W33: en | X33: U.S. Senate Foreign Relations Committee (hearing transcript) | Y33: https://www.foreign.senate.gov/download/transcript03312201 | Z33: legislative_record | AA33: primary_verified | AB33: Ranking-member role inferred, not confirmed on page. | AC33: USA_gov
A34: PS-0033 | B34: 2022-03-31 | C34: 2022 | D34: REG | E34: Tim Kaine | F34: U.S. Senator (D-VA), Chair, SFRC Subcommittee on the Western Hemisphere | G34: us_congress | H34: United States | I34: USA | J34: Democratic | K34: legislative_debate | L34: SFRC Western Hemisphere subcommittee hearing 'China's Role in Latin America and the Caribbean' | M34: lithium;copper | N34: 253090;260300;282520;283691;740200;740311 | O34: geopolitics_security;foreign_investment | P34: CHN;ARG;BOL;CHL;PER | Q34: negative | R34: positive | T34: In his opening statement Kaine said China continues its quest for natural resources and raw materials across Latin America, citing lithium in Argentina, Bolivia and Chile and copper in Peru. | U34: China continues its quest for natural resources and raw materials throughout the region, including lithium in places like Argentina, Bolivia, and Chile or copper in Peru. | V34: China continues its quest for natural resources and raw materials throughout the region, including lithium in places like Argentina, Bolivia, and Chile or copper in Peru. | W34: en | X34: U.S. Senate Foreign Relations Committee (hearing transcript) | Y34: https://www.foreign.senate.gov/download/transcript03312201 | Z34: legislative_record | AA34: primary_verified | AB34: Subcommittee chair role inferred (Kaine chaired the WH subcommittee in the 117th Congress). | AC34: USA_gov
A35: PS-0034 | B35: 2022-04-18 | C35: 2022 | D35: MEX | E35: Andrés Manuel López Obrador | F35: President of Mexico | G35: head_of_state | H35: LatAm executive | I35: MEX | J35: Morena | K35: press_conference | L35: Mañanera after failure of constitutional electricity reform; call to pass Mining Law reform | M35: lithium | N35: 253090;282520;283691 | O35: state_control_nationalization;sovereignty;geopolitics_security | P35: none | Q35: not_mentioned | R35: not_mentioned | T35: AMLO urged legislators to approve his Mining Law reform nationalizing lithium, saying it should be used only for national development and that a state company would explore, extract, process and sell it. | U35: nacionalicemos el litio. Así de claro, que solo se utilice para el beneficio del desarrollo nacional. | V35: let's nationalize lithium. That clear, so that it is only used for the benefit of national development. | W35: es | X35: El Financiero | Y35: https://www.elfinanciero.com.mx/nacional/2022/04/18/amlo-llama-a-legisladores-a-aprobar-este-lunes-la-nacionalizacion-del-litio/ | Z35: news_media | AA35: secondary_reported | AC35: MEX
A36: PS-0035 | B36: 2022-04-18 | C36: 2022 | D36: MEX | E36: Cámara de Diputados de México | F36: Chamber of Deputies | G36: legislature_body | H36: LatAm legislature | I36: MEX | K36: bill_or_law | L36: Vote on Mining Law reform declaring lithium of public utility | M36: lithium | N36: 253090;282520;283691 | O36: state_control_nationalization;sovereignty | P36: none | Q36: not_mentioned | R36: not_mentioned | T36: The Chamber of Deputies approved in general the reform to the Mining Law nationalizing lithium by 298 votes in favour and 197 abstentions; PAN and PRI deputies abstained, while Movimiento Ciudadano voted against parts of it. | W36: es | X36: Expansión Política | Y36: https://politica.expansion.mx/congreso/2022/04/18/la-camara-de-diputados-aprueba-en-lo-general-reforma-a-la-ley-minera | Z36: news_media | AA36: secondary_reported | AB36: In particular: 275 for, 187 abstentions, 24 against (MC). | AC36: MEX
A37: PS-0036 | B37: 2022-04-18 | C37: 2022 | D37: MEX | E37: Salomón Chertorivski | F37: Federal Deputy (Movimiento Ciudadano) | G37: legislator | H37: LatAm legislature | I37: MEX | J37: Movimiento Ciudadano | K37: legislative_debate | L37: Chamber of Deputies debate on lithium Mining Law reform | M37: lithium | N37: 253090;282520;283691 | O37: state_control_nationalization;corruption_governance | P37: none | Q37: not_mentioned | R37: not_mentioned | T37: Chertorivski argued that lithium concessions could not be prohibited by ordinary statute and that it had to be done through the Constitution. | U37: No se puede prohibir en una ley una concesión, se tiene que hacer desde la Constitución | V37: A concession cannot be prohibited in a law, it has to be done from the Constitution | W37: es | X37: Expansión Política | Y37: https://politica.expansion.mx/congreso/2022/04/18/la-camara-de-diputados-aprueba-en-lo-general-reforma-a-la-ley-minera | Z37: news_media | AA37: secondary_reported | AC37: MEX
A38: PS-0037 | B38: 2022-04-19 | C38: 2022 | D38: MEX | E38: Alejandro Armenta | F38: Senator (Morena) | G38: legislator | H38: LatAm legislature | I38: MEX | J38: Morena | K38: legislative_debate | L38: Senate debate on lithium Mining Law reform | M38: lithium | N38: 253090;282520;283691 | O38: state_control_nationalization;foreign_investment | P38: none | Q38: not_mentioned | R38: not_mentioned | T38: Morena senator Armenta defended the reform, arguing that the private sector would still participate since the state company would sell lithium to private firms. | U38: Se lo vende a los particulares | V38: It is sold to private parties | W38: es | X38: Expansión Política | Y38: https://politica.expansion.mx/mexico/2022/04/19/el-senado-aprueba-la-reforma-a-la-ley-minera-de-lopez-obrador | Z38: news_media | AA38: secondary_reported | AC38: MEX
A39: PS-0038 | B39: 2022-04-19 | C39: 2022 | D39: MEX | E39: Damián Zepeda | F39: Senator (PAN) | G39: legislator | H39: LatAm legislature | I39: MEX | J39: PAN | K39: legislative_debate | L39: Senate debate on lithium Mining Law reform | M39: lithium | N39: 253090;282520;283691 | O39: state_control_nationalization;foreign_investment | P39: none | Q39: not_mentioned | R39: not_mentioned | T39: PAN senator Damián Zepeda opposed the lithium reform, arguing the government should not act as a businessman in lithium exploitation. | U39: el gobierno es pésimo para ser empresario | V39: the government is terrible at being a businessman | W39: es | X39: Expansión Política | Y39: https://politica.expansion.mx/mexico/2022/04/19/el-senado-aprueba-la-reforma-a-la-ley-minera-de-lopez-obrador | Z39: news_media | AA39: secondary_reported | AC39: MEX
A40: PS-0039 | B40: 2022-04-19 | C40: 2022 | D40: MEX | E40: José Erandi Bermúdez | F40: Senator (PAN) | G40: legislator | H40: LatAm legislature | I40: MEX | J40: PAN | K40: legislative_debate | L40: Senate debate on lithium Mining Law reform | M40: lithium;critical_minerals_general | N40: 253090;282520;283691 | O40: state_control_nationalization;corruption_governance | P40: none | Q40: not_mentioned | R40: not_mentioned | T40: Bermúdez criticized the reform for lacking precision on which minerals would be considered 'strategic'. | W40: es | X40: Expansión Política | Y40: https://politica.expansion.mx/mexico/2022/04/19/el-senado-aprueba-la-reforma-a-la-ley-minera-de-lopez-obrador | Z40: news_media | AA40: secondary_reported | AC40: MEX
A41: PS-0040 | B41: 2022-04-19 | C41: 2022 | D41: MEX | E41: Senado de la República | F41: Mexican Senate | G41: legislature_body | H41: LatAm legislature | I41: MEX | K41: bill_or_law | L41: Senate vote on lithium Mining Law reform | M41: lithium | N41: 253090;282520;283691 | O41: state_control_nationalization;sovereignty | P41: none | Q41: not_mentioned | R41: not_mentioned | S41: LitioMx | T41: The Senate approved in general the Mining Law reform reserving lithium exploration and exploitation to the state, by 87 votes to 20 with 16 abstentions. | W41: es | X41: Expansión Política | Y41: https://politica.expansion.mx/mexico/2022/04/19/el-senado-aprueba-la-reforma-a-la-ley-minera-de-lopez-obrador | Z41: news_media | AA41: secondary_reported | AB41: In particular: 76 for, 45 against. | AC41: MEX
A42: PS-0041 | B42: 2022-05 | C42: 2022 | D42: BRA | E42: Jair Bolsonaro | F42: President of Brazil | G42: head_of_state | H42: LatAm executive | I42: BRA | J42: PL | K42: speech | L42: Meeting with Elon Musk, São Paulo state | M42: niobium | N42: 261590;720293 | O42: foreign_investment;technology_transfer | P42: USA | Q42: not_mentioned | R42: positive | S42: Tesla | T42: Bolsonaro reportedly offered niobium to Elon Musk during their 2022 meeting, citing Brazil's 98% share of world reserves and studies on niobium batteries that Tesla could use. | W42: pt | X42: Portal Tela | Y42: https://www.portaltela.com/noticias/economia/2025/07/25/bolsonaro-oferece-mineral-estrategico-a-elon-musk-atraindo-interesse-de-trump/ | Z42: news_media | AA42: secondary_reported | AB42: Paraphrase only; month from known Musk visit (May 2022), source says only 2022 | AC42: BRA
A43: PS-0042 | B43: 2022-05-19 | C43: 2022 | D43: PER | E43: Aníbal Torres | F43: President of the Council of Ministers of Peru | G43: minister_cabinet | H43: LatAm executive | I43: PER | K43: speech | L43: Dialogue with communities in Pumamarca, Apurímac; state of emergency over Las Bambas | M43: copper | N43: 260300;740200;740311 | O43: labor_social_conflict;indigenous_community_rights | P43: none | Q43: not_mentioned | R43: not_mentioned | S43: Las Bambas; MMG | T43: Torres told community members that the state of emergency in Challhuahuacho and Coyllurqui would be lifted only once they abandoned forceful actions against Las Bambas and engaged in peaceful dialogue. | U43: El estado de emergencia se levanta simultáneamente con el levantamiento de las actitudes de fuerza y restableciendo la paz social. | V43: The state of emergency is lifted simultaneously with the lifting of forceful actions and the restoration of social peace. | W43: es | X43: Panamericana | Y43: https://panamericana.pe/nacionales/349610-bambas-premier-asegura-emergencia-levantara-deponga-actitudes-fuerza | Z43: news_media | AA43: secondary_reported | AC43: PER
A44: PS-0043 | B44: 2022-06 | C44: 2022 | D44: CHL | E44: Marcela Hernando | F44: Minister of Mining | G44: minister_cabinet | H44: LatAm executive | I44: CHL | J44: Partido Radical | K44: official_statement | L44: Government reaction to Supreme Court annulment of lithium tender | M44: lithium | N44: 253090;282520;283691 | O44: indigenous_community_rights;state_control_nationalization | P44: none | Q44: not_mentioned | R44: not_mentioned | T44: Mining minister said the Boric government would abide by the ruling, that it had warned the tender was badly designed, and that lithium would be developed through public-private partnerships with community dialogue. | U44: ya habíamos advertido que la licitación estaba mal hecha | V44: we had already warned that the tender was badly done | W44: es | X44: CNN Chile | Y44: https://www.cnnchile.com/sin-categoria/gobierno-fin-licitacion-litio-pinera-corte-suprema/ | Z44: news_media | AA44: secondary_reported | AB44: Exact day not stated in source; early June 2022 | AC44: CHL
A45: PS-0044 | B45: 2022-06-01 | C45: 2022 | D45: CHL | E45: Supreme Court of Chile (Third Chamber) | F45: Supreme Court | G45: judiciary | H45: LatAm judiciary | I45: CHL | K45: court_ruling | L45: Ruling on appeal by Colla communities against 2021 lithium tender | M45: lithium | N45: 253090;282520;283691 | O45: indigenous_community_rights;corruption_governance | P45: none | Q45: not_mentioned | R45: not_mentioned | S45: BYD Chile SpA; Servicios y Operaciones Mineras del Norte | T45: The Supreme Court annulled the Piñera-era lithium tender awarding 80,000 t each to BYD and Servicios y Operaciones Mineras del Norte, finding no specific area was set, which prevented prior indigenous consultation. | U45: no se cumplió con el requisito de fijar un área específica | V45: the requirement to set a specific area was not met | W45: es | X45: 24 Horas (TVN) | Y45: https://www.24horas.cl/regiones/atacama/corte-suprema-deja-sin-efecto-licitacion-del-litio-hecha-durante-gobierno-de-pinera-5329930 | Z45: news_media | AA45: secondary_reported | AB45: Ruling reported 1 June 2022, article 2 June | AC45: CHL
A46: PS-0045 | B46: 2022-06-03 | C46: 2022 | D46: PER | E46: Margot Palacios | F46: Congresswoman (Perú Libre) | G46: legislator | H46: LatAm legislature | I46: PER | J46: Perú Libre | K46: bill_or_law | L46: Bill PL 2259 to nationalize copper exploitation | M46: copper | N46: 260300;740200;740311 | O46: state_control_nationalization | P46: CHN | Q46: not_mentioned | R46: not_mentioned | S46: Las Bambas; MMG | T46: Palacios filed bill 2259 to create a National Copper Corporation with exclusive rights over copper exploration, extraction and initial processing, including a state company to operate the MMG-controlled Las Bambas mine. | U46: crear una empresa nacional para operar la mina cuprífera Las Bambas | V46: create a national company to operate the Las Bambas copper mine | W46: es | X46: Forbes Perú | Y46: https://forbes.pe/actualidad/2022-06-03/oficialismo-presenta-un-proyecto-para-nacionalizar-la-explotacion-del-cobre/ | Z46: news_media | AA46: secondary_reported | AB46: Quote may be Forbes' paraphrase of the bill's objective | AC46: PER
A47: PS-0046 | B47: 2022-07-14 | C47: 2022 | D47: REG | E47: Laura Richardson | F47: Commander, U.S. Southern Command | G47: us_central_gov | H47: United States | I47: USA | J47: U.S. Department of Defense | K47: speech | L47: Concordia Americas Summit (Miami) | M47: lithium;rare_earths | N47: 253090;282520;283691;284690 | O47: geopolitics_security | P47: none | Q47: not_mentioned | R47: positive | T47: Richardson described the region as rich in resources, rare earth minerals and lithium, noting the lithium triangle lies in the hemisphere. | U47: This region is so rich in resources, rare earth minerals, lithium — the lithium triangle is in this region. | V47: This region is so rich in resources, rare earth minerals, lithium — the lithium triangle is in this region. | W47: en | X47: Ludditus (blog compiling livestream quotes) | Y47: https://ludditus.com/?p=75497 | Z47: think_tank_or_ngo | AA47: unverified | AB47: Quote transcribed by a blog from Concordia livestream; not checked against video | AC47: USA_gov
A48: PS-0047 | B48: 2022-09-01 | C48: 2022 | D48: MEX | E48: Alfonso Durazo | F48: Governor of Sonora; coordinator of Litio para México | G48: subnational_gov | H48: LatAm executive | I48: MEX | J48: Morena | K48: interview | L48: Appointment as coordinator of LitioMx | M48: lithium | N48: 253090;282520;283691 | O48: state_control_nationalization;labor_social_conflict;value_added_industrialization | P48: none | Q48: not_mentioned | R48: not_mentioned | S48: LitioMx | T48: Durazo said that if lithium exploitation becomes a profitable business its benefits must be shared with local people, and that the Sonora government would hold a stake in LitioMx. | U48: esos beneficios tienen que ser compartidos con la gente local, si no, para mí francamente no tendría ningún sentido | V48: those benefits have to be shared with local people; otherwise, frankly, it would make no sense to me | W48: es | X48: Expansión Política | Y48: https://politica.expansion.mx/estados/2022/09/01/durazo-coordinador-de-litio-para-mexico-cuidare-los-intereses-de-la-gente | Z48: news_media | AA48: secondary_reported | AC48: MEX
A49: PS-0048 | B49: 2022-09-02 | C49: 2022 | D49: COL | E49: Gustavo Petro | F49: President of Colombia | G49: head_of_state | H49: LatAm executive | I49: COL | J49: Pacto Histórico | K49: speech | L49: Closing of national mining congress, Cartagena | M49: critical_minerals_general;mining_general | O49: energy_transition;royalties_taxation | P49: none | Q49: not_mentioned | R49: not_mentioned | T49: Petro told the mining industry that exploration should shift toward minerals for clean energy and fertilizers, and defended taxing coal and oil export windfall profits as world demand for hydrocarbons declines. | U49: En las áreas en donde se puede explorar busquemos los minerales para las energías limpias. Busquemos los minerales para fertilizar las tierras | V49: In the areas where exploration is possible, let us look for minerals for clean energy. Let us look for minerals to fertilize the land | W49: es | X49: Forbes Perú (EFE) | Y49: https://forbes.pe/economia-y-finanzas/2022-09-02/colombia-petro-propone-buscar-minerales-para-transformacion-energetica/ | Z49: news_media | AA49: secondary_reported | AB49: Also reported by Mining Weekly 2022-09-04. | AC49: COL_ECU_PAN
A50: PS-0049 | B50: 2022-09-14 | C50: 2022 | D50: ECU | E50: Embassy of the People's Republic of China in Ecuador | F50: Embassy spokesperson | G50: china_embassy | H50: China | I50: CHN | K50: official_statement | L50: Rebuttal of SOUTHCOM Commander Laura Richardson's remarks at the South American Defense Conference (Southdec) | M50: mining_general | O50: environment_water;geopolitics_security;foreign_investment;diplomatic_relations | P50: USA;ECU | Q50: positive | R50: negative | T50: The Chinese embassy in Ecuador called Gen. Laura Richardson's claim that large Chinese mining projects were eroding Ecuadorian water sources 'ridiculous', saying Chinese firms follow strict environmental standards and contribute to local development. It accused the US of double standards and of seeking to sow discord between China and Ecuador. | U50: sus difamaciones no muestran el mínimo respeto a Ecuador | V50: her defamations show not the slightest respect for Ecuador | W50: es | X50: Vistazo | Y50: https://www.vistazo.com/amp/actualidad/nacional/china-refuta-declaraciones-de-la-comandante-de-ee-uu-intentan-sembrar-discordia-con-ecuador-JX3099391 | Z50: news_media | AA50: secondary_reported | AB50: Date per Vistazo report (Wednesday 14 Sep 2022); embassy statement itself not seen. | AC50: CHN_gov
A51: PS-0050 | B51: 2022-09-20 | C51: 2022 | D51: BOL | E51: Luis Arce | F51: President of Bolivia | G51: head_of_state | H51: LatAm executive | I51: BOL | J51: Movimiento al Socialismo (MAS) | K51: speech | L51: 77th UN General Assembly, New York | M51: lithium | N51: 253090;282520;283691 | O51: sovereignty;geopolitics_security;value_added_industrialization | P51: none | Q51: not_mentioned | R51: not_mentioned | T51: At the UN General Assembly, Arce reaffirmed sovereignty over natural resources such as lithium and rejected interference and destabilization attempts aimed at controlling lithium, urging UN action against countries that do not respect non-interference. | U51: Rechazamos todo tipo de injerencias y afanes de desestabilización de las democracia en nuestro país, con el afán de controlar el litio | V51: We reject all kinds of interference and attempts to destabilize democracy in our country with the aim of controlling lithium | W51: es | X51: Emol | Y51: https://www.emol.com/noticias/Internacional/2022/09/20/1073368/arce-onu-medidas-intervencion-litio.html | Z51: news_media | AA51: secondary_reported | AC51: BOL
A52: PS-0051 | B52: 2022-09-21 | C52: 2022 | D52: ARG | E52: Sabino Vaca Narvaja | F52: Argentine Ambassador to China | G52: other_executive | H52: LatAm executive | I52: ARG | J52: Frente de Todos | K52: speech | L52: China Mining fair opening, Tianjin | M52: mining_general;lithium | N52: 253090;282520;283691 | O52: foreign_investment;diplomatic_relations | P52: CHN | Q52: positive | R52: not_mentioned | T52: Vaca Narvaja, the only foreign speaker at the ceremony, promoted Argentina as a land of mining opportunity with clear rules and said China will play a key role in Argentine mining development. | U52: China jugará un papel clave en el desarrollo minero argentino | V52: China will play a key role in Argentine mining development | W52: es | X52: Tiempo Argentino | Y52: https://www.tiempoar.com.ar/ta_article/argentina-en-busca-de-inversiones-chinas-para-grandes-proyectos-mineros/ | Z52: news_media | AA52: secondary_reported | AC52: ARG
A53: PS-0052 | B53: 2022-09-22 | C53: 2022 | D53: ARG | E53: Alberto Fernández | F53: President of Argentina | G53: head_of_state | H53: LatAm executive | I53: ARG | J53: Frente de Todos | K53: speech | L53: Talk at The New School, New York | M53: lithium | N53: 253090;282520;283691 | O53: state_control_nationalization;sovereignty | P53: CHL;BOL | Q53: not_mentioned | R53: not_mentioned | T53: Fernández said lithium should be considered a strategic resource while respecting that it belongs to the provinces under Argentina's federal system, contrasting Chile's and Bolivia's models. | U53: Debemos considerar el litio como un recurso estratégico | V53: We must consider lithium a strategic resource | W53: es | X53: Reporte Minero | Y53: https://www.reporteminero.cl/noticia/noticias/2022/09/presidente-alberto-fernandez-propuso-declarar-litio-recurso-estrategico | Z53: news_media | AA53: secondary_reported | AC53: ARG
A54: PS-0053 | B54: 2022-09-23 | C54: 2022 | D54: BOL | E54: Evo Morales | F54: Former President of Bolivia; MAS leader | G54: other | H54: Other (business, civil society, third countries) | I54: BOL | J54: Movimiento al Socialismo (MAS) | K54: social_media_post | L54: Claims about UK role in 2019 crisis | M54: lithium | N54: 253090;282520;283691 | O54: sovereignty;geopolitics_security;diplomatic_relations | P54: GBR | Q54: not_mentioned | R54: not_mentioned | S54: British Embassy in La Paz | T54: Morales tweeted that evidence showed the 2019 'coup' was financed by the United Kingdom and its ambassador Jeff Glekin to take control of Bolivian lithium. | U54: Ante la evidencia de que el golpe de Estado fue financiado por el Reino Unido y su embajador @jeffglekin para adueñarse del litio boliviano | V54: Given the evidence that the coup d'état was financed by the United Kingdom and its ambassador @jeffglekin to take over Bolivian lithium | W54: es | X54: Correo del Sur | Y54: https://correodelsur.com/politica/20220923/evo-dice-que-reino-unido-financio-un-golpe-en-2019-para-aduenarse-del-litio-boliviano.html | Z54: news_media | AA54: secondary_reported | AC54: BOL
A55: PS-0054 | B55: 2022-09-30 | C55: 2022 | D55: ARG | E55: Gerardo Morales | F55: Governor of Jujuy | G55: subnational_gov | H55: LatAm executive | I55: ARG | J55: UCR | K55: speech | L55: Presentation to US State Department and Department of Energy with governors Sáenz and Jalil | M55: lithium | N55: 253090;282520;283691 | O55: foreign_investment;energy_transition;diplomatic_relations | P55: USA | Q55: not_mentioned | R55: positive | T55: Morales told US officials it is very important to deepen ties with the US and hoped more US companies would invest in the lithium provinces, calling lithium a strategic and critical mineral for the energy transition. | U55: Para nosotros es sumamente importante profundizar la relación bilateral con Estados Unidos y esperar así que más empresas norteamericanas inviertan en nuestras provincias | V55: For us it is extremely important to deepen the bilateral relationship with the United States and thus hope more American companies invest in our provinces | W55: es | X55: TodoJujuy | Y55: https://www.todojujuy.com/jujuy/gerardo-morales-expuso-el-litio-y-los-proyectos-mineros-n225633 | Z55: news_media | AA55: secondary_reported | AC55: ARG
A56: PS-0055 | B56: 2022-10-24 | C56: 2022 | D56: PER | E56: Song Yang | F56: Chinese Ambassador to Peru | G56: china_embassy | H56: China | I56: CHN | J56: CCP | K56: interview | L56: Interview with El Peruano on bilateral relations | M56: mining_general;copper | N56: 260300;740200;740311 | O56: foreign_investment;infrastructure_ports;diplomatic_relations | P56: CHN | Q56: positive | R56: not_mentioned | S56: Puerto de Chancay; Chinese mining companies | T56: Song Yang said more than 10 Chinese mining companies had invested over US$23.1 billion in Peru, paying taxes and creating jobs, and presented Chancay port as a future integrated maritime hub for Latin America. | U56: Más de 10 empresas mineras chinas han invertido en el Perú, con una inversión total de más de 23.1 mil millones de dólares. | V56: More than 10 Chinese mining companies have invested in Peru, with total investment of over 23.1 billion dollars. | W56: es | X56: El Peruano | Y56: https://elperuano.pe/noticia/195514-embajador-song-yang-el-peru-y-china-estan-en-un-momento-crucial-de-transformacion-y-crecimiento | Z56: primary_official | AA56: primary_verified | AB56: El Peruano is the state gazette/newspaper | AC56: PER
A57: PS-0056 | B57: 2022-11-04 | C57: 2022 | D57: ARG | E57: Sabino Vaca Narvaja | F57: Argentine Ambassador to China | G57: other_executive | H57: LatAm executive | I57: ARG | J57: Frente de Todos | K57: speech | L57: China International Import Expo, Shanghai; Tibet Summit lithium announcement | M57: lithium | N57: 253090;282520;283691 | O57: foreign_investment;value_added_industrialization | P57: CHN | Q57: positive | R57: not_mentioned | S57: Tibet Summit Resources; Salar de Diablillos; Salar de Arizaro | T57: At the CIIE, where Tibet Summit announced over US$2bn of lithium investment in Salta, Vaca Narvaja said China dominates the entire lithium chain and Argentina should exploit its privileged position hand in hand with China. | U57: Nuestro país tiene una posición privilegiada y debemos, explotarla al máximo de la mano de China | V57: Our country has a privileged position and we must exploit it to the fullest hand in hand with China | W57: es | X57: La Voz de San Justo | Y57: https://www.lavozdesanjusto.com.ar/una-empresa-china-anuncio-inversiones-en-litio-por-us2200-millones-128580 | Z57: news_media | AA57: secondary_reported | AB57: Also reported by Cancillería (fetch timed out). | AC57: ARG
A58: PS-0057 | B58: 2022-12-16 | C58: 2022 | D58: PAN | E58: Government of Panama | F58: Executive (Cortizo administration) | G58: other_executive | H58: LatAm executive | I58: PAN | J58: PRD | K58: official_statement | L58: Breakdown of Cobre Panamá contract negotiations | M58: copper | N58: 260300;740200;740311 | O58: royalties_taxation;foreign_investment;sovereignty | P58: CAN | Q58: not_mentioned | R58: not_mentioned | S58: Cobre Panamá; First Quantum; Minera Panamá | T58: Panama's government halted talks with First Quantum and announced it would order suspension of Cobre Panamá operations, seeking a new contract with at least USD 375 million a year in taxes and royalties. | W58: en | X58: First Quantum Minerals (company release) | Y58: https://www.first-quantum.com/news/first-quantum-minerals-responds-to-latest-developments-in-panama/ | Z58: news_media | AA58: secondary_reported | AB58: Government position as described by the company; source is corporate. | AC58: COL_ECU_PAN
A59: PS-0058 | B59: 2023-01-16 | C59: 2023 | D59: COL | E59: Gustavo Petro | F59: President of Colombia | G59: head_of_state | H59: LatAm executive | I59: COL | J59: Pacto Histórico | K59: speech | L59: Public event in Jericó, Antioquia | M59: copper | N59: 260300;740200;740311 | O59: environment_water;labor_social_conflict | P59: none | Q59: not_mentioned | R59: not_mentioned | S59: Quebradona; AngloGold Ashanti | T59: Petro announced a ban on mining in Jericó, where AngloGold Ashanti's Quebradona copper project awaits licensing, said all mining titles would be reviewed against water protection, and announced a reform of the Mining Code. | U59: Entonces, nosotros escogemos el agua | V59: So we choose water | W59: es | X59: Valora Analitik | Y59: https://www.valoraanalitik.com/colombia-prohibir-mineria-en-jerico-petro-dejo-por-fuera-a-400-promineros/ | Z59: news_media | AA59: secondary_reported | AC59: COL_ECU_PAN
A60: PS-0059 | B60: 2023-01-19 | C60: 2023 | D60: REG | E60: Laura Richardson | F60: Commander, U.S. Southern Command | G60: us_central_gov | H60: United States | I60: USA | J60: U.S. Department of Defense | K60: interview | L60: Atlantic Council video conversation | M60: lithium;rare_earths;copper | N60: 253090;260300;282520;283691;284690;740200;740311 | O60: geopolitics_security | P60: CHN;RUS;ARG;BOL;CHL | Q60: negative | R60: positive | T60: SOUTHCOM commander said Latin America matters to US security because of its resources, citing the 'lithium triangle' of Argentina, Bolivia and Chile with about 60% of world lithium, plus rare earth elements, oil and fresh water, and said the US must step up its game against adversaries. | U60: Why this region matters with all its rich resource and rare earth elements, you've got the lithium triangle which is needed for technology today. | V60: Why this region matters with all its rich resource and rare earth elements, you've got the lithium triangle which is needed for technology today. | W60: en | X60: Buenos Aires Herald | Y60: https://www.buenosairesherald.com/world/international-relations/defense-ministry-held-meetings-with-us-southern-command | Z60: news_media | AA60: secondary_reported | AB60: Quote as reported by Buenos Aires Herald; Spanish coverage (Conclusión https://www.conclusion.com.ar/?p=985547) adds '60% of the world's lithium is in the lithium triangle'. | AC60: USA_gov
A61: PS-0060 | B61: 2023-01-20 | C61: 2023 | D61: BOL | E61: Luis Arce | F61: President of Bolivia | G61: head_of_state | H61: LatAm executive | I61: BOL | J61: Movimiento al Socialismo (MAS) | K61: speech | L61: Signing of DLE agreement between YLB and CBC consortium, La Paz | M61: lithium | N61: 253090;282520;283691 | O61: foreign_investment;value_added_industrialization;technology_transfer | P61: CHN | Q61: positive | R61: not_mentioned | S61: YLB; CBC; CATL; BRUNP; CMOC; Salar de Uyuni; Salar de Coipasa | T61: Arce announced a US$1bn+ agreement with the Chinese CBC consortium (CATL, BRUNP, CMOC) to apply direct lithium extraction in Potosí and Oruro, targeting lithium battery exports by early 2025. | U61: Hoy hemos decidido darle un giro con industria con la extracción directa de litio | V61: Today we have decided to make a turn toward industry with direct lithium extraction | W61: es | X61: Correo del Sur | Y61: https://correodelsur.com/economia/20230120_bolivia-firma-convenio-con-consorcio-chino-para-la-industrializacion-del-litio.html | Z61: news_media | AA61: secondary_reported | AC61: BOL
A62: PS-0061 | B62: 2023-01-22 | C62: 2023 | D62: BOL | E62: Franklin Molina | F62: Minister of Hydrocarbons and Energy | G62: minister_cabinet | H62: LatAm executive | I62: BOL | J62: Movimiento al Socialismo (MAS) | K62: interview | L62: Interview on CBC lithium agreement | M62: lithium | N62: 253090;282520;283691 | O62: foreign_investment;state_control_nationalization;processing_refining;technology_transfer | P62: CHN | Q62: positive | R62: not_mentioned | S62: YLB; CBC; CATL | T62: Molina said the CBC deal involves joint investment in two lithium carbonate plants of 25,000 t each, with YLB retaining 100% ownership, and would generate over US$5bn in revenue. | U62: nos va a permitir generar ingresos importantísimos para el país, que superarían los 5.000 millones de dólares | V62: it will allow us to generate very important revenues for the country, exceeding 5 billion dollars | W62: es | X62: Correo del Sur | Y62: https://correodelsur.com/panorama/20230122/nos-va-a-permitir-generar-ingresos-que-superarian-los-us-5-000-millones.html | Z62: news_media | AA62: secondary_reported | AC62: BOL
A63: PS-0062 | B63: 2023-01-23 | C63: 2023 | D63: REG | E63: Laura Richardson | F63: Commander, US Southern Command | G63: us_central_gov | H63: United States | I63: USA | K63: speech | L63: Atlantic Council event, Washington | M63: lithium;rare_earths | N63: 253090;282520;283691;284690 | O63: geopolitics_security | P63: ARG;BOL;CHL | Q63: not_mentioned | R63: not_mentioned | T63: The SOUTHCOM commander highlighted that about 60% of the world's lithium lies in the 'lithium triangle' of Argentina, Bolivia and Chile, framing the region's resources as strategically important to the US. | W63: en | X63: Economía Sustentable | Y63: https://economiasustentable.com/noticias/las-criticas-que-recibio-la-jefa-del-comando-sur-tras-enumerar-los-intereses-de-estados-unidos-en-america-latina | Z63: news_media | AA63: secondary_reported | AB63: Quote as rendered by secondary source (may be back-translated); region-wide statement naming Bolivia. Quote cleared: only translated wording seen. | AC63: BOL
A64: PS-0063 | B64: 2023-02-18 | C64: 2023 | D64: MEX | E64: Andrés Manuel López Obrador | F64: President of Mexico | G64: head_of_state | H64: LatAm executive | I64: MEX | J64: Morena | K64: decree_or_regulation | L64: Signing of lithium nationalization decree, Bacadéhuachi, Sonora | M64: lithium | N64: 253090;282520;283691 | O64: state_control_nationalization;sovereignty;geopolitics_security | P64: RUS;CHN;USA | Q64: negative | R64: negative | S64: LitioMx | T64: In Bacadéhuachi, Sonora, AMLO signed a decree transferring lithium reserve areas to the Energy Ministry, saying lithium would be nationalized so that foreigners from Russia, China or the US could not exploit it. | U64: Vamos a nacionalizar el litio para que no lo puedan explotar los extranjeros ni de Rusia, ni de China, ni de Estados Unidos | V64: We are going to nationalize lithium so that foreigners from Russia, China or the United States cannot exploit it | W64: es | X64: N+ | Y64: https://www.nmas.com.mx/nacional/amlo-firma-decreto-sobre-nacionalizacion-del-litio-en-sonora/ | Z64: news_media | AA64: secondary_reported | AB64: Stance toward CHN/USA coded negative regarding their exploitation of Mexican lithium. | AC64: MEX
A65: PS-0064 | B65: 2023-03 | C65: 2023 | D65: ECU | E65: Corte Provincial de Justicia de Imbabura | F65: Provincial Court of Imbabura | G65: judiciary | H65: LatAm judiciary | I65: ECU | K65: court_ruling | L65: Protection action against Llurimagua copper project | M65: copper | N65: 260300;740200;740311 | O65: environment_water;indigenous_community_rights | P65: CHL | Q65: not_mentioned | R65: not_mentioned | S65: Llurimagua; ENAMI; Codelco | T65: The Imbabura provincial court upheld a 2020 first-instance ruling, revoking the Llurimagua copper project's environmental license over violations of environmental rights and consultation obligations. | W65: es | X65: Primicias | Y65: https://www.primicias.ec/economia/licitacion-proyecto-cobre-llurimagua-mineria-consulta-ambiental-imbabura-118038/ | Z65: news_media | AA65: secondary_reported | AB65: Reported retrospectively in 2026 article; day unknown. | AC65: COL_ECU_PAN
A66: PS-0065 | B66: 2023-03-08 | C66: 2023 | D66: REG | E66: Laura Richardson | F66: Commander, U.S. Southern Command | G66: us_central_gov | H66: United States | I66: USA | J66: U.S. Department of Defense | K66: report | L66: SOUTHCOM 2023 Posture Statement to Congress | M66: mining_general | O66: geopolitics_security;foreign_investment;infrastructure_ports | P66: CHN | Q66: negative | R66: positive | T66: The 2023 posture statement warned that the PRC has expanded its ability to extract resources, establish ports and manipulate governments through predatory investment in the region. | U66: The PRC has expanded its ability to extract resources, establish ports, manipulate governments through predatory investment practices | V66: The PRC has expanded its ability to extract resources, establish ports, manipulate governments through predatory investment practices | W66: en | X66: U.S. Southern Command | Y66: https://www.southcom.mil/Media/Special-Coverage/SOUTHCOMs-2023-Posture-Statement-to-Congress/ | Z66: primary_official | AA66: primary_verified | AC66: USA_gov
A67: PS-0066 | B67: 2023-03-08 | C67: 2023 | D67: REG | E67: Laura Richardson | F67: Commander, U.S. Southern Command | G67: us_central_gov | H67: United States | I67: USA | J67: U.S. Department of Defense | K67: legislative_debate | L67: House Armed Services Committee hearing on SOUTHCOM posture | M67: lithium | N67: 253090;282520;283691 | O67: geopolitics_security;foreign_investment | P67: CHN;ARG;BOL;CHL | Q67: negative | R67: positive | T67: Testifying to the House, Richardson said the region is full of resources exploited by adversaries who appear to invest but actually extract, and described China's lithium game in the region as very advanced and aggressive. | U67: la agresividad de China y su juego en el terreno con el litio, es muy avanzado y muy agresivo | V67: China's aggressiveness and its game on the ground with lithium is very advanced and very aggressive | W67: es | X67: El Observador (Uruguay) | Y67: https://www.elobservador.com.uy/nota/la-disputa-entre-china-y-estados-unidos-por-el-litio-en-america-latina-20234128128 | Z67: news_media | AA67: secondary_reported | AB67: Spanish rendering of English testimony; also reported by El Ciudadano https://www.elciudadano.com/?p=942911 (dated 10 Mar 2023) | AC67: USA_gov
A68: PS-0067 | B68: 2023-03-23 | C68: 2023 | D68: REG | E68: Laura Richardson | F68: Commander, U.S. Southern Command | G68: us_central_gov | H68: United States | I68: USA | J68: U.S. Department of Defense | K68: legislative_debate | L68: Senate Armed Services Committee hearing on NORTHCOM/SOUTHCOM posture | M68: lithium | N68: 253090;282520;283691 | O68: geopolitics_security | P68: CHN | Q68: negative | R68: positive | T68: Testifying to the Senate, Richardson said the PRC has expanded its ability to extract resources from the region and gets 75 percent of its lithium from South America. | U68: The PRC has expanded its ability to extract resources, and gets 36 percent of its food imports from the region and 75 percent of its lithium from South America. | V68: The PRC has expanded its ability to extract resources, and gets 36 percent of its food imports from the region and 75 percent of its lithium from South America. | W68: en | X68: Senate Armed Services Committee transcript | Y68: https://www.armed-services.senate.gov/download/transcript-3232023 | Z68: legislative_record | AA68: primary_verified | AC68: USA_gov
A69: PS-0068 | B69: 2023-03-24 | C69: 2023 | D69: BOL | E69: Luis Arce | F69: President of Bolivia | G69: head_of_state | H69: LatAm executive | I69: BOL | J69: Movimiento al Socialismo (MAS) | K69: speech | L69: Speech in La Paz proposing joint Latin American lithium policy | M69: lithium | N69: 253090;282520;283691 | O69: geopolitics_security;sovereignty;trade_deals_offtake | P69: USA;ARG;CHL | Q69: not_mentioned | R69: negative | T69: Arce called for a common, sovereign Latin American lithium market policy and said Bolivia did not want its lithium in the US Southern Command's crosshairs or used to destabilize elected governments. | W69: en | X69: Mining Weekly (Reuters) | Y69: https://www.miningweekly.com/article/bolivia-president-calls-for-joint-latin-america-lithium-policy-2023-03-24 | Z69: news_media | AA69: secondary_reported | AB69: Quote is English translation by Reuters; Spanish original not seen. Quote cleared: only translated wording seen. | AC69: BOL
A70: PS-0069 | B70: 2023-03-31 | C70: 2023 | D70: REG | E70: U.S. Department of the Treasury | F70: Treasury (Sec. Janet Yellen) | G70: us_central_gov | H70: United States | I70: USA | J70: Biden administration | K70: decree_or_regulation | L70: Proposed guidance on IRA clean vehicle credit (Section 30D) critical minerals requirement | M70: critical_minerals_general;lithium;nickel;cobalt;graphite | N70: 250490;253090;260400;282520;283691;720260 | O70: tariffs_trade_policy;energy_transition;trade_deals_offtake | P70: CHL;COL;MEX;PAN;PER;other | Q70: not_mentioned | R70: positive | S70: Inflation Reduction Act | T70: Treasury's proposed IRA guidance listed free-trade-agreement countries, including Chile, Colombia, Mexico, Panama and Peru, whose extracted or processed critical minerals count toward the EV credit's rising sourcing thresholds (40% in 2023 to 80% from 2027). | W70: en | X70: U.S. Department of the Treasury | Y70: https://home.treasury.gov/news/press-releases/jy1379 | Z70: primary_official | AA70: primary_verified | AB70: Argentina, Bolivia, Brazil not FTA partners (excluded unless new critical minerals agreement) | AC70: USA_gov
A71: PS-0070 | B71: 2023-04-06 | C71: 2023 | D71: ARG | E71: Sabino Vaca Narvaja | F71: Argentine Ambassador to China | G71: other_executive | H71: LatAm executive | I71: ARG | J71: Frente de Todos | K71: speech | L71: Tour of Fujian province with Catamarca governor Jalil | M71: lithium;mining_general | N71: 253090;282520;283691 | O71: foreign_investment;trade_deals_offtake | P71: CHN | Q71: positive | R71: not_mentioned | T71: Vaca Narvaja said mining has the potential to solve Argentina's recurrent foreign-currency crises, noting a single lithium project could account for up to 5% of national exports. | U71: la minería tiene el potencial para solucionar nuestras recurrentes crisis de divisas | V71: mining has the potential to solve our recurrent foreign-currency crises | W71: es | X71: El Economista | Y71: https://eleconomista.com.ar/economia/vaca-narvaja-la-mineria-tiene-potencial-solucionar-recurrentes-crisis-divisas-n61228 | Z71: news_media | AA71: secondary_reported | AB71: Trip followed Jalil's China visit seeking lithium investment (Zijin). | AC71: ARG
A72: PS-0071 | B72: 2023-04-09 | C72: 2023 | D72: CHL | E72: Bob Menendez | F72: U.S. Senator, Chair of Senate Foreign Relations Committee | G72: us_congress | H72: United States | I72: USA | J72: Democratic | K72: interview | L72: Visit to Chile, April 2023 | M72: lithium | N72: 253090;282520;283691 | O72: geopolitics_security;environment_water | P72: CHN | Q72: negative | R72: positive | T72: During a visit to Chile, Senator Menendez said China lacked environmental standards and sought the easiest way to extract lithium, contrasting it with US standards and China's state-controlled model. | W72: en | X72: Ex-Ante | Y72: https://www.ex-ante.cl/?p=138108 | Z72: news_media | AA72: secondary_reported | AB72: Paraphrase; quotes reported in Spanish translation via Chinese ambassador rebuttal article | AC72: CHL
A73: PS-0072 | B73: 2023-04-09 | C73: 2023 | D73: CHL | E73: Niu Qingbao | F73: Chinese Ambassador to Chile | G73: china_embassy | H73: China | I73: CHN | J73: CCP | K73: op_ed | L73: Rebuttal to Senator Menendez's remarks on Chinese lithium extraction | M73: lithium | N73: 253090;282520;283691 | O73: geopolitics_security;environment_water;diplomatic_relations | P73: USA | Q73: positive | R73: negative | T73: The Chinese ambassador published a rebuttal titled "Double standards are Mr. Bob Menendez's trademark", defending China as the largest clean-energy producer and accusing the US of coercing countries through coups, threats and sanctions. | W73: es | X73: Ex-Ante | Y73: https://www.ex-ante.cl/?p=138108 | Z73: news_media | AA73: secondary_reported | AB73: Paraphrase; article date 9 Apr 2023 | AC73: CHL
A74: PS-0073 | B74: 2023-04-14 | C74: 2023 | D74: BRA | E74: Xi Jinping | F74: President of the People's Republic of China | G74: head_of_state | H74: China | I74: CHN | J74: CCP | K74: joint_declaration_or_mou | L74: Lula state visit to Beijing; joint statement on deepening comprehensive strategic partnership | M74: mining_general | O74: foreign_investment;energy_transition;diplomatic_relations | P74: BRA | Q74: positive | R74: not_mentioned | T74: The China-Brazil joint statement issued during Lula's state visit says both sides will actively encourage their companies to invest in each other's countries, particularly in infrastructure, energy transition, logistics, energy, mining, agriculture, industry and high technology. It names no specific minerals. | U74: 双方同意积极鼓励两国企业到对方国家开展投资，特别是在基础设施、能源转型、物流、能源、矿业、农业、工业以及高科技领域。 | V74: The two sides agree to actively encourage their enterprises to invest in each other's countries, especially in infrastructure, energy transition, logistics, energy, mining, agriculture, industry and high-tech fields. | W74: zh | X74: Ministry of Foreign Affairs of the PRC | Y74: https://www.mfa.gov.cn/web/gjhdq_676201/gj_676203/nmz_680924/1206_680974/1207_680986/202304/t20230414_11059627.shtml | Z74: primary_official | AA74: primary_verified | AB74: Paragraph 21 of the joint statement. Joint China-Brazil text attributed to Xi as China's head of state, following the existing China-Peru joint statement record. Mining is one sector in a list; weak mineral content. | AC74: CHN_gov
A75: PS-0074 | B75: 2023-04-17 | C75: 2023 | D75: ARG | E75: Laura Richardson | F75: Commander, U.S. Southern Command | G75: us_central_gov | H75: United States | I75: USA | J75: U.S. Department of Defense | K75: official_statement | L75: SOUTHCOM commander visit to Argentina (Patagonia, Ushuaia) | M75: lithium | N75: 253090;282520;283691 | O75: geopolitics_security;diplomatic_relations | P75: CHN;ARG | Q75: negative | R75: positive | T75: Richardson's visit to Argentina and the Southern Cone was reported as having lithium and concern over China on the agenda, following her earlier public emphasis on the lithium triangle as a US security interest. | W75: en | X75: Buenos Aires Times | Y75: https://batimes.com.ar/news/argentina/us-general-visits-southern-cone-with-patagonia-and-lithium-on-agenda.phtml | Z75: news_media | AA75: secondary_reported | AB75: Visit-level record; no direct quote on lithium during visit | AC75: USA_gov
A76: PS-0075 | B76: 2023-04-20 | C76: 2023 | D76: CHL | E76: Gabriel Boric | F76: President of Chile | G76: head_of_state | H76: LatAm executive | I76: CHL | J76: Convergencia Social / Frente Amplio | K76: speech | L76: National broadcast announcing the National Lithium Strategy | M76: lithium | N76: 253090;282520;283691 | O76: state_control_nationalization;value_added_industrialization;environment_water;indigenous_community_rights | P76: none | Q76: not_mentioned | R76: not_mentioned | S76: Empresa Nacional del Litio; Codelco | T76: Boric announced the National Lithium Strategy with the state as central actor, a future National Lithium Company seeking private partners, a salt-flat protection network and community involvement. | U76: nuestro desafío es que nuestro país se convierta en el principal productor de litio en el mundo | V76: our challenge is for our country to become the main lithium producer in the world | W76: es | X76: El Dínamo | Y76: https://www.eldinamo.cl/politica/2023/04/20/los-cinco-pilares-de-la-estrategia-nacional-del-litio-presentada-por-el-presidente-boric/ | Z76: news_media | AA76: secondary_reported | AC76: CHL
A77: PS-0076 | B77: 2023-04-20 | C77: 2023 | D77: CHL | E77: Ricardo Díaz | F77: Governor of Antofagasta Region | G77: subnational_gov | H77: LatAm executive | I77: CHL | J77: Independent | K77: interview | L77: Reaction to National Lithium Strategy | M77: lithium | N77: 253090;282520;283691 | O77: value_added_industrialization;indigenous_community_rights | P77: none | Q77: not_mentioned | R77: not_mentioned | S77: Salar de Atacama | T77: Antofagasta governor welcomed the president's view that value could be added in the region but criticised the absence of indigenous communities and regional participation in the strategy's launch. | U77: El Presidente vio que se puede agregar valor acá en la región con personal de la región. | V77: The President saw that value can be added here in the region with people from the region. | W77: es | X77: El Desconcierto | Y77: https://eldesconcierto.cl/2023/04/21/gobernador-diaz-y-estrategia-nacional-del-litio-el-presidente-vio-que-se-puede-agregar-valor-aca-en-la-region | Z77: news_media | AA77: secondary_reported | AC77: CHL
A78: PS-0077 | B78: 2023-04-20 | C78: 2023 | D78: MEX | E78: Ildefonso Guajardo | F78: Federal Deputy (PRI) | G78: legislator | H78: LatAm legislature | I78: MEX | J78: PRI | K78: legislative_debate | L78: Chamber of Deputies debate on 2023 Mining Law reform | M78: mining_general | O78: foreign_investment;state_control_nationalization | P78: none | Q78: not_mentioned | R78: not_mentioned | T78: Former economy minister Guajardo opposed the reform, arguing that articles 10 and 10 bis would cause Mexican mining to lose its potential. | U78: con los artículos 10 y 10 bis de la reforma, la minería mexicana perderá su potencial | V78: with articles 10 and 10 bis of the reform, Mexican mining will lose its potential | W78: es | X78: Excélsior | Y78: https://www.excelsior.com.mx/nacional/reducen-periodo-de-concesiones-mineras-diputados-envian-reforma-al-senado/1582870 | Z78: news_media | AA78: secondary_reported | AB78: Debate ran overnight 20-21 April 2023. | AC78: MEX
A79: PS-0078 | B79: 2023-04-20 | C79: 2023 | D79: MEX | E79: Manuel Rodríguez González | F79: Federal Deputy (Morena); President of the Energy Commission | G79: legislator | H79: LatAm legislature | I79: MEX | J79: Morena | K79: legislative_debate | L79: Chamber of Deputies debate on 2023 Mining Law and water concessions reform | M79: mining_general | O79: state_control_nationalization;environment_water;sovereignty | P79: none | Q79: not_mentioned | R79: not_mentioned | T79: Presenting the reform, Rodríguez said its central aim was to recover state stewardship over mineral and water resources; the bill shortened mining concessions and water concessions for mining. | U79: La esencia y objetivo central es recuperar la rectoría del Estado sobre los recursos minerales e hídricos del subsuelo mexicano | V79: The essence and central objective is to recover the State's stewardship over the mineral and water resources of the Mexican subsoil | W79: es | X79: Zeta Tijuana | Y79: https://zetatijuana.com/2023/04/sin-discusion-morena-pt-pvem-y-mc-aprueban-en-lo-general-reformas-para-disminuir-anos-a-concesiones-mineras/ | Z79: news_media | AA79: secondary_reported | AB79: Debate ran overnight 20-21 April 2023. | AC79: MEX
A80: PS-0079 | B80: 2023-04-21 | C80: 2023 | D80: MEX | E80: Cámara de Diputados de México | F80: Chamber of Deputies | G80: legislature_body | H80: LatAm legislature | I80: MEX | K80: bill_or_law | L80: Vote on 2023 Mining Law and water concessions reform | M80: mining_general | O80: state_control_nationalization;environment_water | P80: none | Q80: not_mentioned | R80: not_mentioned | T80: The Chamber of Deputies approved in general the AMLO-backed reform of the Mining Law, National Waters Law and environmental laws by 290 votes to 186 with 1 abstention; Morena, PT, PVEM and MC supported it while PAN, PRI and PRD opposed. | W80: es | X80: Excélsior | Y80: https://www.excelsior.com.mx/nacional/reducen-periodo-de-concesiones-mineras-diputados-envian-reforma-al-senado/1582870 | Z80: news_media | AA80: secondary_reported | AB80: In particular: 251-209-1 (Infobae via Cámara síntesis). | AC80: MEX
A81: PS-0080 | B81: 2023-04-22 | C81: 2023 | D81: MEX | E81: Asociación de Ingenieros de Minas, Metalurgistas y Geólogos de México (AIMMGM) | F81: Mining professional association | G81: other | H81: Other (business, civil society, third countries) | I81: MEX | K81: official_statement | L81: Reaction to Chamber approval of Mining Law reform | M81: mining_general | O81: foreign_investment;corruption_governance | P81: none | Q81: not_mentioned | R81: not_mentioned | T81: The mining engineers' association urged the Senate to hold an open parliament before ratifying the fast-tracked reform, warning of provisions on exploration, payments and restrictions affecting the industry. | U81: Antes de ratificar la reforma aprobada por la Cámara de Diputados, el Senado de la República debe convocar a un parlamento abierto | V81: Before ratifying the reform approved by the Chamber of Deputies, the Senate must convene an open parliament | W81: es | X81: Forbes México (via Cámara de Diputados síntesis) | Y81: https://comunicacion.diputados.gob.mx/sintesis/LINKSIN/22423_P_FORBES_0_MINEROSPIDEN_SENADOVOTERFLEYMINERA_3DIP.pdf | Z81: news_media | AA81: secondary_reported | AB81: Industry actor. | AC81: MEX
A82: PS-0081 | B82: 2023-04-23 | C82: 2023 | D82: MEX | E82: COPARMEX | F82: Employers' confederation | G82: other | H82: Other (business, civil society, third countries) | I82: MEX | K82: official_statement | L82: Press release on Mining Law reform | M82: mining_general | O82: foreign_investment;corruption_governance | P82: none | Q82: not_mentioned | R82: not_mentioned | T82: COPARMEX asked the Senate not to fast-track the mining reform, calling for an open parliament with experts and firms, investment certainty, and postponing approval until September. | U82: es necesario escuchar a expertos y a las empresas mediante un parlamento abierto | V82: it is necessary to listen to experts and companies through an open parliament | W82: es | X82: COPARMEX | Y82: https://coparmex.org.mx/downloads/ENVIOS/CP_31_EN_LA_LEY_DE_MINERIA_ES_NECESARIO_ESCUCHAR_A_EXPERTOS_E_INDUSTRIA_SENADO_DEBE_EVITAR_APROBAR_FAST_TRACK.pdf | Z82: primary_official | AA82: primary_verified | AB82: Business association, not government. | AC82: MEX
